Workbook

Sheet Read Me
A1: Persistence Model — Full Build, Graduate Programs (Method A + Method B, both computed separately)
A2: Scope: the 41 Graduate-level programs from the Revenue model's 63-program list. ADC and UG11 are intentionally excluded from this build per your instruction — ADC follows once this graduate build is reviewed and trusted; UG11 has no enrollment history to build on yet.
A4: What this is
A5: This replicates the single-program Accounting pilot (both methods, computed and compared separately) across all 41 graduate programs at once, so you can see the same New Student Retention / Returning Student Retention / survival-curve comparison for every program you manage — not just one.
A6: Method A — Pooled, definition-exact: reproduces the LTR builder's Assumptions tab literally. New Student Retention = pooled Term-3 ÷ pooled Term-1 count among mature cohorts. Returning Student Retention = a credit-hour-weighted AVERAGE of each term's cumulative retention ('% of Segment Base', term 3 onward — Term 3 is the segment's own base, always 100% of itself, so Term 4 is the first term that can show real attrition), stopping at the first term that drops below 20% of the program's Term-3 base — so a weak trailing term is dropped from the average entirely rather than dragging it down.
A7: Method B — Per-cohort survival curve: every intake cohort tracked on its own from its own Term 1, S(t) = students present at term t ÷ students present at term 1. Aggregated two ways: Pooled (student-weighted, all mature-cohort students combined) and Simple Average (cohort-weighted, every intake counted once regardless of size).
A8: Method A's New Student Retention and Method B's Pooled S(T3) are built from the same population the same way and should reconcile exactly — every program's cross-check passed in this run (see Method B Summary).
A10: How it was built
A11: Computed in Python directly from 'Online Enrolled Student Report for Retention 08192026.xlsx', then pasted here as static values — per your instruction: check the output first, formalize into live formulas once the model is trusted. Every definition, threshold and the resolution script are documented on the tabs that follow.
A12: Term window: 201930–202610 (20 terms). Maturity threshold: ≥9 terms elapsed since a cohort's first term. Left-censoring: cohorts whose first term predates 201930 are excluded (no reliable Term 1 for them in this pull).
A13: Credit Hours to Degree is program-specific (not a single constant like the 40-CH Accounting pilot used) — sourced per program from Rev_Forecast_Model_final.xlsx, assumption tab, 'Required Credits' column (rows 107–147). Where that sheet notes a code renumbering (e.g. M013 formerly M002), the current code's value is used. It's shown on the Program List and Method A sheets for reference, but no longer enters the Returning Student Retention calculation itself — see the correction note below.
A15: Program identity
... A122: Once you've reviewed these graduate-program outputs and are confident in the approach, the same build extends to the 10 ADC programs. UG11 stays out until those programs accumulate real enrollment history.

Sheet Controls
A1: Persistence Model — Controls & Assumptions (shared across all 41 graduate programs)
A3: Data Window Start Term | B3: 201930 | C3: Cohorts whose First Term in Major predates this are left-censored and excluded from every program's Method A/B figures.
A5: Maturity Threshold (terms elapsed) | B5: 9 | C5: A cohort is 'mature' once at least this many terms have elapsed since its first term. Same threshold used in the Portfolio Persistence Screen for consistency across deliverables.
A7: Returning-Segment Floor (% of Segment Base) | B7: 0.2 | C7: Returning Student Retention accounting starts at Term 3 (the segment's own base, always 100% of itself) and stops accumulating once the cumulative count at a later term, as a share of the Term-3 base ('% of Segment Base'), falls below this rate — sticky once breached, so a later uptick doesn't resume accumulation. (Corrected twice in this version — see the Read Me correction notes: first, the floor test itself was fixed to compare against '% of Segment Base' instead of Term-over-Term Retention; then the accounting was moved to start at Term 3 instead of Term 4.)
A9: Thin-Sample Caution Threshold (students at T1) | B9: 30 | C9: Below this many mature-cohort students at Term 1, a program is flagged 'Thin sample' — matches the Revenue model's own 30-observation empirical-retention threshold.
A11: Last Term Order in Data | B11: 20 | C11: Shared term window: 201930–202610 (20 terms), same construction as the Portfolio Persistence Screen (excludes the MAX_TERM_CODE forward-registration sentinel and legacy GRADUATION_TERM_CODE contamination from the term sequence itself).
A13: Values here are Python-computed and pasted as static values, per your instruction to check the output before formalizing into live in-sheet formulas.

Sheet Term Index
A1: Term Code | B1: Sequential Order
A2: 201930 | B2: 1
A3: 202010 | B3: 2
A4: 202020 | B4: 3
A5: 202030 | B5: 4
A6: 202110 | B6: 5
A7: 202120 | B7: 6
A8: 202130 | B8: 7
A9: 202210 | B9: 8
A10: 202220 | B10: 9
A11: 202230 | B11: 10
A12: 202310 | B12: 11
A13: 202320 | B13: 12
... A21: 202610 | B21: 20

Sheet Program List
A1: Code | B1: Program Name | C1: Banner codes pooled | D1: Resolution note | E1: CH to Degree | F1: CH Source Note | G1: Raw rows (this program) | H1: Left-censored excluded | I1: Mature-cohort N @ T1 | J1: Sample Flag
A2: 1550C | B2: Certificate in Population Health | C2: 1550C | D2: not in PROGRAM_KEY; exact-code match only | E2: 12 | F2: OU: 12-cr certificate | G2: 0 | H2: 0 | I2: 0 | J2: No data
A3: D318 | B3: Ed.D. in Education Administration | C3: D318 | D3: pooled via PROGRAM_KEY siblings | E3: 54 | F3: OU: 54 billed doctoral credit hrs | G3: 955 | H3: 0 | I3: 0 | J3: No data
A4: M366 | B4: Executive MBA in Energy | C4: M366 | D4: pooled via PROGRAM_KEY siblings | EXCLUDED M824 ('Renewables (EMBA)-OL75') from this pool -- shares PROGRAM_KEY's 'EMBA' known-name with M366 ('Energy-OL60'), but the descriptions name different concentrations (Energy vs Renewables) AND different credit-hour formats (60 vs 75), which reads as two distinct EMBA tracks rather than one program under two codes. M824 carries 81 raw rows. Using exact-code-only (M366) until confirmed with the program owner whether these are meant to be combined. | E4: 36 | F4: Airtable BE validated vs OU | G4: 801 | H4: 0 | I4: 112 | J4: OK
A5: 1231EX | B5: Executive Masters in Health Administration | C5: 1231EX | D5: not in PROGRAM_KEY; exact-code match only | E5: 42 | F5: Airtable BE validated vs OU | G5: 0 | H5: 0 | I5: 0 | J5: No data
A6: M013 | B6: Master of Accountancy | C6: M002, M012, M013 | D6: pooled via PROGRAM_KEY siblings | E6: 40 | F6: Updated to 40 per instruction (code M013, formerly M002) | G6: 2036 | H6: 0 | I6: 272 | J6: OK
A7: M075 | B7: Master of Arts in Art and Technology | C7: M075 | D7: pooled via PROGRAM_KEY siblings | E7: 33 | F7: Airtable BE validated vs OU | G7: 864 | H7: 0 | I7: 146 | J7: OK
A8: M073 | B8: Master of Arts in Arts Management | C8: M073 | D8: pooled via PROGRAM_KEY siblings | E8: 30 | F8: Airtable BE validated vs OU | G8: 721 | H8: 0 | I8: 80 | J8: OK
A9: M494 | B9: Master of Arts in Global Affairs | C9: M494 | D9: pooled via PROGRAM_KEY siblings | E9: 33 | F9: Airtable BE validated vs OU | G9: 1852 | H9: 0 | I9: 248 | J9: OK
A10: M700 | B10: Master of Arts in Museum Studies | C10: M578, M700 | D10: pooled via PROGRAM_KEY siblings | E10: 33 | F10: Airtable BE validated vs OU | G10: 3652 | H10: 0 | I10: 474 | J10: OK
A11: M762 | B11: Master of Arts in Organizational Leadership | C11: M762 | D11: AMBIGUOUS: shares known-name 'Organizational Leadership' with target(s) ['B580', 'B755']; using exact code only | E11: 30 | F11: Airtable BE validated vs OU | G11: 3083 | H11: 0 | I11: 505 | J11: OK
A12: M859 | B12: Master of Arts in Strategic Communication and Digital Strategy | C12: M611, M859 | D12: pooled via PROGRAM_KEY siblings | RESOLVED via temporal-cutover check on the raw enrollment data: M611 ('Journalism & Mass Comm-OL') has 63 distinct students, first-terms 202020 (30) and 202030 (32), then drains to a single straggler at 202110. M859 ('Strat Comm & Digital Strat-OL') begins at exactly 202110 with a full new cohort of 75 students and continues every term through 202530 -- zero terms of concurrent admission under both codes. That is the rename signature (a clean one-term handoff), not two products running side by side, so M611 is pooled back in as the predecessor code for the same online program. The current registrar catalog listing both an online JMC MA (M611) and StratComm MA (M859) as separate active offerings reflects today's catalog, not the 2020-21 state when this enrollment data shows the actual cutover; M611's online section appears to have been discontinued and folded into M859 at that point. | E12: 33 | F12: Airtable BE validated vs OU | G12: 1687 | H12: 0 | I12: 256 | J12: OK
A13: M202 | B13: Master of Clinical Mental Health Counseling | C13: M202 | D13: pooled via PROGRAM_KEY siblings | E13: 60 | F13: Airtable BE validated vs OU | G13: 2180 | H13: 0 | I13: 240 | J13: OK
... A42: M592 | B42: Online LL.M. International Business | C42: M592 | D42: AMBIGUOUS: shares known-name 'International Business Law - Resident' with target(s) ['M589']; using exact code only | E42: 24 | F42: Airtable BE validated vs OU | G42: 16 | H42: 0 | I42: 2 | J42: Thin sample (<30)

Sheet Method A - Summary
A1: Code | B1: Program Name | C1: N @ T1 (mature) | D1: N @ T3 (mature) | E1: New Student Retention | F1: Sum CH Contribution | G1: Sum CH Weight (included terms) | H1: CH to Degree (reference only) | I1: Returning Student Retention | J1: LTR Factor (New x Returning) | K1: Floor Breach Term | L1: Sample Flag
A2: 1550C | B2: Certificate in Population Health | F2: 0 | G2: 0 | H2: 12 | K2: Not reached in observed data | L2: No data
A3: D318 | B3: Ed.D. in Education Administration | F3: 0 | G3: 0 | H3: 54 | K3: 3 | L3: No data
A4: M366 | B4: Executive MBA in Energy | C4: 112 | D4: 109 | E4: 0.97321429 | F4: 20.706422 | G4: 22.768408 | H4: 36 | I4: 0.90943653 | J4: 0.88507662 | K4: 6 | L4: OK
A5: 1231EX | B5: Executive Masters in Health Administration | F5: 0 | G5: 0 | H5: 42 | K5: Not reached in observed data | L5: No data
A6: M013 | B6: Master of Accountancy | C6: 272 | D6: 188 | E6: 0.69117647 | F6: 20.319149 | G6: 32.563817 | H6: 40 | I6: 0.62397934 | J6: 0.43127984 | K6: 9 | L6: OK
A7: M075 | B7: Master of Arts in Art and Technology | C7: 146 | D7: 101 | E7: 0.69178082 | F7: 18.059406 | G7: 19.104455 | H7: 33 | I7: 0.94529815 | J7: 0.65393913 | K7: 6 | L7: OK
A8: M073 | B8: Master of Arts in Arts Management | C8: 80 | D8: 62 | E8: 0.775 | F8: 13.112903 | G8: 13.207298 | H8: 30 | I8: 0.99285285 | J8: 0.76946096 | K8: 5 | L8: OK
A9: M494 | B9: Master of Arts in Global Affairs | C9: 248 | D9: 132 | E9: 0.53225806 | F9: 25.765152 | G9: 30.809568 | H9: 33 | I9: 0.8362711 | J9: 0.44511204 | K9: 9 | L9: OK
A10: M700 | B10: Master of Arts in Museum Studies | C10: 474 | D10: 310 | E10: 0.65400844 | F10: 21.674194 | G10: 29.339279 | H10: 33 | I10: 0.73874322 | J10: 0.4831443 | K10: 9 | L10: OK
A11: M762 | B11: Master of Arts in Organizational Leadership | C11: 505 | D11: 288 | E11: 0.57029703 | F11: 21.53125 | G11: 31.088749 | H11: 30 | I11: 0.6925737 | J11: 0.39497272 | K11: 9 | L11: OK
A12: M859 | B12: Master of Arts in Strategic Communication and Digital Strategy | C12: 256 | D12: 208 | E12: 0.8125 | F12: 19.5 | G12: 19.654322 | H12: 33 | I12: 0.99214821 | J12: 0.80612042 | K12: 6 | L12: OK
A13: M202 | B13: Master of Clinical Mental Health Counseling | C13: 240 | D13: 189 | E13: 0.7875 | F13: 39.243386 | G13: 43.138141 | H13: 60 | I13: 0.90971437 | J13: 0.71640006 | K13: 9 | L13: OK
A14: M246 | B14: Master of Construction Business | C14: 115 | D14: 100 | E14: 0.86956522 | F14: 16.14 | G14: 23.575662 | H14: 32 | I14: 0.68460432 | J14: 0.59530811 | K14: 7 | L14: OK
A15: M297 | B15: Master of Econometrics | F15: 0 | G15: 0 | H15: 30 | K15: 3 | L15: No data
A16: M383 | B16: Master of Entrepreneurship & Innovation | F16: 0 | G16: 0 | H16: 30 | K16: 3 | L16: No data
A17: M518 | B17: Master of Environmental Science: Hydrology and Water Security | C17: 254 | D17: 184 | E17: 0.72440945 | F17: 19.271739 | G17: 25.855814 | H17: 30 | I17: 0.74535418 | J17: 0.53994161 | K17: 8 | L17: OK
A18: M368 | B18: Master of Legal Studies - Energy | C18: 82 | D18: 58 | E18: 0.70731707 | F18: 15.137931 | G18: 15.406404 | H18: 32 | I18: 0.98257394 | J18: 0.69499132 | K18: 5 | L18: OK
A19: M636 | B19: Master of Legal Studies - General | F19: 0 | G19: 0 | H19: 32 | K19: 3 | L19: No data
A20: M503 | B20: Master of Legal Studies - Healthcare Law | C20: 428 | D20: 314 | E20: 0.73364486 | F20: 16.146497 | G20: 20.405562 | H20: 32 | I20: 0.79127921 | J20: 0.58051792 | K20: 6 | L20: OK
A21: M522 | B21: Master of Legal Studies - Indigenous Peoples Law | C21: 566 | D21: 384 | E21: 0.67844523 | F21: 18.567708 | G21: 23.73046 | H21: 33 | I21: 0.78244199 | J21: 0.53084403 | K21: 6 | L21: OK
A22: M589 | B22: Master of Legal Studies - International Business | C22: 68 | D22: 48 | E22: 0.70588235 | F22: 15.770833 | G22: 18.714015 | H22: 32 | I22: 0.84272847 | J22: 0.59486715 | K22: 6 | L22: OK
A23: M029 | B23: Master of Science in Applied Computing | F23: 0 | G23: 0 | H23: 30 | K23: 3 | L23: No data
A24: M035 | B24: Master of Science in Applied Statistics | C24: 49 | D24: 21 | E24: 0.42857143 | F24: 16.714286 | G24: 23.266917 | H24: 30 | I24: 0.7183713 | J24: 0.30787342 | K24: 8 | L24: OK
A25: M145 | B25: Master of Science in Business Analytics | C25: 77 | D25: 47 | E25: 0.61038961 | F25: 16.765957 | G25: 20.559003 | H25: 32 | I25: 0.81550439 | J25: 0.49777541 | K25: 6 | L25: OK
A26: M191 | B26: Master of Science in Civil Engineering | C26: 145 | D26: 121 | E26: 0.83448276 | F26: 16.644628 | G26: 22.489827 | H26: 30 | I26: 0.74009588 | J26: 0.61759725 | K26: 7 | L26: OK
A27: M260 | B27: Master of Science in Criminal Justice | C27: 218 | D27: 121 | E27: 0.55504587 | F27: 21.22314 | G27: 27.408921 | H27: 30 | I27: 0.77431506 | J27: 0.42978038 | K27: 8 | L27: OK
A28: M264 | B28: Master of Science in Cybersecurity Leadership | F28: 0 | G28: 0 | H28: 30 | K28: 3 | L28: No data
A29: M374 | B29: Master of Science in Engineering Leadership and Management | C29: 24 | D29: 19 | E29: 0.79166667 | F29: 16.578947 | G29: 21.092105 | H29: 30 | I29: 0.7860262 | J29: 0.62227074 | K29: 6 | L29: Thin sample (<30)
A30: M435 | B30: Master of Science in Finance | C30: 262 | D30: 195 | E30: 0.74427481 | F30: 15.374359 | G30: 20.275 | H30: 32 | I30: 0.75829144 | J30: 0.56437722 | K30: 6 | L30: OK
A31: M464 | B31: Master of Science in Geospatial Technology | C31: 103 | D31: 72 | E31: 0.69902913 | F31: 20.458333 | G31: 24.342857 | H31: 33 | I31: 0.84042449 | J31: 0.5874812 | K31: 7 | L31: OK
A32: M527 | B32: Master of Science in Industrial and Systems Engineering | C32: 91 | D32: 54 | E32: 0.59340659 | F32: 18.444444 | G32: 24.621275 | H32: 30 | I32: 0.74912631 | J32: 0.44453649 | K32: 8 | L32: OK
A33: M746 | B33: Master of Science in Natural Gas Engineering and Management | C33: 82 | D33: 54 | E33: 0.65853659 | F33: 19.407407 | G33: 24.129618 | H33: 30 | I33: 0.80429818 | J33: 0.52965977 | K33: 8 | L33: OK
A34: M861 | B34: Master of Science in Supply Chain Management | C34: 88 | D34: 72 | E34: 0.81818182 | F34: 15 | G34: 15.104851 | H34: 32 | I34: 0.99305843 | J34: 0.81250235 | K34: 5 | L34: OK
A35: M869 | B35: Master of Science in Sustainability - Energy and Materials Mgmt | C35: 26 | D35: 16 | E35: 0.61538462 | F35: 15.5625 | G35: 17.008929 | H35: 30 | I35: 0.91496063 | J35: 0.5630527 | K35: 6 | L35: Thin sample (<30)
A36: M867 | B36: Master of Science in Sustainable Architecture | C36: 20 | D36: 15 | E36: 0.75 | F36: 13.733333 | G36: 14.142857 | H36: 30 | I36: 0.97104377 | J36: 0.72828283 | K36: 5 | L36: Thin sample (<30)
A37: M844 | B37: Master of Social Work | C37: 771 | D37: 595 | E37: 0.77172503 | F37: 40.811765 | G37: 51.007984 | H37: 60 | I37: 0.80010543 | J37: 0.61746139 | K37: 10 | L37: OK
A38: 1237Q | B38: Masters in Public Health | F38: 0 | G38: 0 | H38: 42 | K38: Not reached in observed data | L38: No data
A39: M355 | B39: Online LL.M. Energy and Natural Resources | C39: 9 | D39: 4 | E39: 0.44444444 | F39: 12.5 | G39: 12.5 | H39: 24 | I39: 1 | J39: 0.44444444 | K39: Not reached in observed data | L39: Thin sample (<30)
A40: M504 | B40: Online LL.M. Healthcare Law | C40: 9 | D40: 3 | E40: 0.33333333 | F40: 11.333333 | G40: 11.333333 | H40: 24 | I40: 1 | J40: 0.33333333 | K40: Not reached in observed data | L40: Thin sample (<30)
A41: M526 | B41: Online LL.M. Indigenous Peoples Law | C41: 19 | D41: 7 | E41: 0.36842105 | F41: 15 | G41: 17 | H41: 25 | I41: 0.88235294 | J41: 0.3250774 | K41: 6 | L41: Thin sample (<30)
A42: M592 | B42: Online LL.M. International Business | C42: 2 | D42: 1 | E42: 0.5 | F42: 5 | G42: 5 | H42: 24 | I42: 1 | J42: 0.5 | K42: 4 | L42: Thin sample (<30)

Sheet Method B - Summary
A1: Code | B1: Program Name | C1: # Cohorts | D1: # Mature Cohorts | E1: Pooled S(T3) | F1: Simple-Avg S(T3) | G1: Difference (Pooled - Simple Avg) | H1: Cross-check vs Method A | I1: Sample Flag
A2: 1550C | B2: Certificate in Population Health | C2: 0 | D2: 0 | H2: n/a | I2: No data
A3: D318 | B3: Ed.D. in Education Administration | C3: 4 | D3: 0 | H3: n/a | I3: No data
A4: M366 | B4: Executive MBA in Energy | C4: 14 | D4: 8 | E4: 0.97321429 | F4: 0.96780303 | G4: 0.0054112554 | H4: Matches | I4: OK
A5: 1231EX | B5: Executive Masters in Health Administration | C5: 0 | D5: 0 | H5: n/a | I5: No data
A6: M013 | B6: Master of Accountancy | C6: 20 | D6: 12 | E6: 0.69117647 | F6: 0.69644281 | G6: -0.0052663373 | H6: Matches | I6: OK
A7: M075 | B7: Master of Arts in Art and Technology | C7: 11 | D7: 6 | E7: 0.69178082 | F7: 0.71072091 | G7: -0.018940088 | H7: Matches | I7: OK
A8: M073 | B8: Master of Arts in Arts Management | C8: 9 | D8: 4 | E8: 0.775 | F8: 0.8780722 | G8: -0.1030722 | H8: Matches | I8: OK
A9: M494 | B9: Master of Arts in Global Affairs | C9: 20 | D9: 12 | E9: 0.53225806 | F9: 0.54563272 | G9: -0.013374652 | H9: Matches | I9: OK
A10: M700 | B10: Master of Arts in Museum Studies | C10: 20 | D10: 12 | E10: 0.65400844 | F10: 0.63771837 | G10: 0.016290073 | H10: Matches | I10: OK
A11: M762 | B11: Master of Arts in Organizational Leadership | C11: 20 | D11: 12 | E11: 0.57029703 | F11: 0.57736759 | G11: -0.0070705596 | H11: Matches | I11: OK
A12: M859 | B12: Master of Arts in Strategic Communication and Digital Strategy | C12: 18 | D12: 10 | E12: 0.8125 | F12: 0.8097506 | G12: 0.0027494026 | H12: Matches | I12: OK
A13: M202 | B13: Master of Clinical Mental Health Counseling | C13: 15 | D13: 8 | E13: 0.7875 | F13: 0.79731129 | G13: -0.0098112923 | H13: Matches | I13: OK
A14: M246 | B14: Master of Construction Business | C14: 11 | D14: 6 | E14: 0.86956522 | F14: 0.87434605 | G14: -0.0047808366 | H14: Matches | I14: OK
A15: M297 | B15: Master of Econometrics | C15: 4 | D15: 0 | H15: n/a | I15: No data
A16: M383 | B16: Master of Entrepreneurship & Innovation | C16: 5 | D16: 0 | H16: n/a | I16: No data
A17: M518 | B17: Master of Environmental Science: Hydrology and Water Security | C17: 16 | D17: 11 | E17: 0.72440945 | F17: 0.70742494 | G17: 0.016984505 | H17: Matches | I17: OK
A18: M368 | B18: Master of Legal Studies - Energy | C18: 12 | D18: 7 | E18: 0.70731707 | F18: 0.72367306 | G18: -0.016355986 | H18: Matches | I18: OK
A19: M636 | B19: Master of Legal Studies - General | C19: 3 | D19: 0 | H19: n/a | I19: No data
A20: M503 | B20: Master of Legal Studies - Healthcare Law | C20: 20 | D20: 12 | E20: 0.73364486 | F20: 0.74187156 | G20: -0.0082266983 | H20: Matches | I20: OK
A21: M522 | B21: Master of Legal Studies - Indigenous Peoples Law | C21: 20 | D21: 12 | E21: 0.67844523 | F21: 0.67878777 | G21: -0.0003425449 | H21: Matches | I21: OK
A22: M589 | B22: Master of Legal Studies - International Business | C22: 11 | D22: 8 | E22: 0.70588235 | F22: 0.70757576 | G22: -0.0016934046 | H22: Matches | I22: OK
A23: M029 | B23: Master of Science in Applied Computing | C23: 6 | D23: 0 | H23: n/a | I23: No data
A24: M035 | B24: Master of Science in Applied Statistics | C24: 9 | D24: 2 | E24: 0.42857143 | F24: 0.42676768 | G24: 0.0018037518 | H24: Matches | I24: OK
A25: M145 | B25: Master of Science in Business Analytics | C25: 10 | D25: 5 | E25: 0.61038961 | F25: 0.68135621 | G25: -0.070966599 | H25: Matches | I25: OK
A26: M191 | B26: Master of Science in Civil Engineering | C26: 14 | D26: 9 | E26: 0.83448276 | F26: 0.85161364 | G26: -0.017130878 | H26: Matches | I26: OK
A27: M260 | B27: Master of Science in Criminal Justice | C27: 20 | D27: 12 | E27: 0.55504587 | F27: 0.60966448 | G27: -0.054618606 | H27: Matches | I27: OK
A28: M264 | B28: Master of Science in Cybersecurity Leadership | C28: 2 | D28: 0 | H28: n/a | I28: No data
A29: M374 | B29: Master of Science in Engineering Leadership and Management | C29: 6 | D29: 1 | E29: 0.79166667 | F29: 0.79166667 | G29: 0 | H29: Matches | I29: Thin sample (<30)
A30: M435 | B30: Master of Science in Finance | C30: 20 | D30: 12 | E30: 0.74427481 | F30: 0.76522752 | G30: -0.020952706 | H30: Matches | I30: OK
A31: M464 | B31: Master of Science in Geospatial Technology | C31: 13 | D31: 8 | E31: 0.69902913 | F31: 0.67661648 | G31: 0.022412646 | H31: Matches | I31: OK
A32: M527 | B32: Master of Science in Industrial and Systems Engineering | C32: 11 | D32: 6 | E32: 0.59340659 | F32: 0.57954545 | G32: 0.013861139 | H32: Matches | I32: OK
A33: M746 | B33: Master of Science in Natural Gas Engineering and Management | C33: 15 | D33: 9 | E33: 0.65853659 | F33: 0.69423786 | G33: -0.035701276 | H33: Matches | I33: OK
A34: M861 | B34: Master of Science in Supply Chain Management | C34: 13 | D34: 5 | E34: 0.81818182 | F34: 0.844 | G34: -0.025818182 | H34: Matches | I34: OK
A35: M869 | B35: Master of Science in Sustainability - Energy and Materials Mgmt | C35: 7 | D35: 2 | E35: 0.61538462 | F35: 0.60714286 | G35: 0.0082417582 | H35: Matches | I35: Thin sample (<30)
A36: M867 | B36: Master of Science in Sustainable Architecture | C36: 6 | D36: 1 | E36: 0.75 | F36: 0.75 | G36: 0 | H36: Matches | I36: Thin sample (<30)
A37: M844 | B37: Master of Social Work | C37: 17 | D37: 11 | E37: 0.77172503 | F37: 0.74614845 | G37: 0.025576579 | H37: Matches | I37: OK
A38: 1237Q | B38: Masters in Public Health | C38: 0 | D38: 0 | H38: n/a | I38: No data
A39: M355 | B39: Online LL.M. Energy and Natural Resources | C39: 9 | D39: 5 | E39: 0.44444444 | F39: 0.43333333 | G39: 0.011111111 | H39: Matches | I39: Thin sample (<30)
A40: M504 | B40: Online LL.M. Healthcare Law | C40: 12 | D40: 7 | E40: 0.33333333 | F40: 0.35714286 | G40: -0.023809524 | H40: Matches | I40: Thin sample (<30)
A41: M526 | B41: Online LL.M. Indigenous Peoples Law | C41: 12 | D41: 7 | E41: 0.36842105 | F41: 0.45714286 | G41: -0.088721805 | H41: Matches | I41: Thin sample (<30)
A42: M592 | B42: Online LL.M. International Business | C42: 4 | D42: 2 | E42: 0.5 | F42: 0.5 | G42: 0 | H42: Matches | I42: Thin sample (<30)

Sheet Method A - Detail
A1: 1550C — Certificate in Population Health
A2: No mature-cohort data available for this program in the current pull.
A4: D318 — Ed.D. in Education Administration
A5: No mature-cohort data available for this program in the current pull.
A7: M366 — Executive MBA in Energy
A8: Relative Term | B8: N (mature-cohort rows) | C8: Avg Credit Hours | D8: Term-over-Term Retention | E8: Ratio vs Term 3 | F8: Above Floor? | G8: CH Contribution
A9: 1 | B9: 112 | C9: 6.93 | D9: — | E9: 1.0275229 | F9: — | G9: 0
A10: 2 | B10: 112 | C10: 7.81 | D10: 1 | E10: 1.0275229 | F10: — | G10: 0
A11: 3 | B11: 109 | C11: 7.31 | D11: 0.97321429 | E11: 1 | F11: Yes | G11: 7.312
A12: 4 | B12: 108 | C12: 7.98 | D12: 0.99082569 | E12: 0.99082569 | F12: Yes | G12: 7.908
A13: 5 | B13: 80 | C13: 7.47 | D13: 0.74074074 | E13: 0.73394495 | F13: Yes | G13: 5.486
A14: 6 | B14: 5 | C14: 4.2 | D14: 0.0625 | E14: 0.04587156 | F14: No | G14: 0
A15: 7 | B15: 2 | C15: 3 | D15: 0.4 | E15: 0.018348624 | F15: No | G15: 0
A16: 8 | B16: 0 | C16: 0 | D16: 0 | E16: 0 | F16: No | G16: 0
A17: 9 | B17: 1 | C17: 2 | D17: — | E17: 0.0091743119 | F17: No | G17: 0
A18: 10 | B18: 1 | C18: 8 | D18: 1 | E18: 0.0091743119 | F18: No | G18: 0
A19: 11 | B19: 1 | C19: 7 | D19: 1 | E19: 0.0091743119 | F19: No | G19: 0
A20: New Student Retention (Term 3 ÷ Term 1) | B20: 0.97321429
A21: Sum of CH Contributions (term 3 through cutoff, while above floor) | B21: 20.706
A22: Sum of Avg CH, included terms (averaging denominator) | B22: 22.768
A23: Credit Hours to Degree (reference only — not used below) | B23: 36
A24: Returning Student Retention (= CH Contributions ÷ Avg CH, included terms) | B24: 0.90943653
A25: LTR Factor (New x Returning) | B25: 0.88507662
A26: First term floor was breached | B26: 6
A28: 1231EX — Executive Masters in Health Administration
A29: No mature-cohort data available for this program in the current pull.
A31: M013 — Master of Accountancy
A32: Relative Term | B32: N (mature-cohort rows) | C32: Avg Credit Hours | D32: Term-over-Term Retention | E32: Ratio vs Term 3 | F32: Above Floor? | G32: CH Contribution
A33: 1 | B33: 272 | C33: 6.13 | D33: — | E33: 1.4468085 | F33: — | G33: 0
A34: 2 | B34: 215 | C34: 6.18 | D34: 0.79044118 | E34: 1.143617 | F34: — | G34: 0
A35: 3 | B35: 188 | C35: 6.24 | D35: 0.8744186 | E35: 1 | F35: Yes | G35: 6.245
A36: 4 | B36: 160 | C36: 5.91 | D36: 0.85106383 | E36: 0.85106383 | F36: Yes | G36: 5.032
A37: 5 | B37: 120 | C37: 5.6 | D37: 0.75 | E37: 0.63829787 | F37: Yes | G37: 3.574
A38: 6 | B38: 95 | C38: 5.06 | D38: 0.79166667 | E38: 0.50531915 | F38: Yes | G38: 2.559
A39: 7 | B39: 65 | C39: 5.2 | D39: 0.68421053 | E39: 0.34574468 | F39: Yes | G39: 1.798
A40: 8 | B40: 46 | C40: 4.54 | D40: 0.70769231 | E40: 0.24468085 | F40: Yes | G40: 1.112
A41: 9 | B41: 27 | C41: 4.15 | D41: 0.58695652 | E41: 0.14361702 | F41: No | G41: 0
A42: 10 | B42: 24 | C42: 4.29 | D42: 0.88888889 | E42: 0.12765957 | F42: No | G42: 0
A43: 11 | B43: 11 | C43: 4.18 | D43: 0.45833333 | E43: 0.058510638 | F43: No | G43: 0
A44: 12 | B44: 6 | C44: 4 | D44: 0.54545455 | E44: 0.031914894 | F44: No | G44: 0
A45: 13 | B45: 6 | C45: 3.67 | D45: 1 | E45: 0.031914894 | F45: No | G45: 0
... A47: 15 | B47: 0 | C47: 0 | D47: 0 | E47: 0 | F47: No | G47: 0
A48: 16 | B48: 1 | C48: 3 | D48: — | E48: 0.0053191489 | F48: No | G48: 0
A49: New Student Retention (Term 3 ÷ Term 1) | B49: 0.69117647
A50: Sum of CH Contributions (term 3 through cutoff, while above floor) | B50: 20.319
A51: Sum of Avg CH, included terms (averaging denominator) | B51: 32.564
A52: Credit Hours to Degree (reference only — not used below) | B52: 40
A53: Returning Student Retention (= CH Contributions ÷ Avg CH, included terms) | B53: 0.62397934
A54: LTR Factor (New x Returning) | B54: 0.43127984
A55: First term floor was breached | B55: 9
A57: M075 — Master of Arts in Art and Technology
A58: Relative Term | B58: N (mature-cohort rows) | C58: Avg Credit Hours | D58: Term-over-Term Retention | E58: Ratio vs Term 3 | F58: Above Floor? | G58: CH Contribution
A59: 1 | B59: 146 | C59: 5.51 | D59: — | E59: 1.4455446 | F59: — | G59: 0
A60: 2 | B60: 118 | C60: 6.81 | D60: 0.80821918 | E60: 1.1683168 | F60: — | G60: 0
A61: 3 | B61: 101 | C61: 7.54 | D61: 0.8559322 | E61: 1 | F61: Yes | G61: 7.545
A62: 4 | B62: 97 | C62: 5.63 | D62: 0.96039604 | E62: 0.96039604 | F62: Yes | G62: 5.406
A63: 5 | B63: 87 | C63: 5.93 | D63: 0.89690722 | E63: 0.86138614 | F63: Yes | G63: 5.109
A64: 6 | B64: 9 | C64: 5.67 | D64: 0.10344828 | E64: 0.089108911 | F64: No | G64: 0
A65: 7 | B65: 7 | C65: 5.57 | D65: 0.77777778 | E65: 0.069306931 | F65: No | G65: 0
A66: 8 | B66: 2 | C66: 6 | D66: 0.28571429 | E66: 0.01980198 | F66: No | G66: 0
A67: 9 | B67: 4 | C67: 6 | D67: 2 | E67: 0.03960396 | F67: No | G67: 0
A68: 10 | B68: 3 | C68: 5 | D68: 0.75 | E68: 0.02970297 | F68: No | G68: 0
A69: 11 | B69: 2 | C69: 6 | D69: 0.66666667 | E69: 0.01980198 | F69: No | G69: 0
A70: 12 | B70: 1 | C70: 6 | D70: 0.5 | E70: 0.0099009901 | F70: No | G70: 0
A71: 13 | B71: 1 | C71: 6 | D71: 1 | E71: 0.0099009901 | F71: No | G71: 0
A72: New Student Retention (Term 3 ÷ Term 1) | B72: 0.69178082
A73: Sum of CH Contributions (term 3 through cutoff, while above floor) | B73: 18.059
A74: Sum of Avg CH, included terms (averaging denominator) | B74: 19.104
A75: Credit Hours to Degree (reference only — not used below) | B75: 33
A76: Returning Student Retention (= CH Contributions ÷ Avg CH, included terms) | B76: 0.94529815
A77: LTR Factor (New x Returning) | B77: 0.65393913
A78: First term floor was breached | B78: 6
A80: M073 — Master of Arts in Arts Management
A81: Relative Term | B81: N (mature-cohort rows) | C81: Avg Credit Hours | D81: Term-over-Term Retention | E81: Ratio vs Term 3 | F81: Above Floor? | G81: CH Contribution
A82: 1 | B82: 80 | C82: 8.51 | D82: — | E82: 1.2903226 | F82: — | G82: 0
A83: 2 | B83: 68 | C83: 6.53 | D83: 0.85 | E83: 1.0967742 | F83: — | G83: 0
A84: 3 | B84: 62 | C84: 7.35 | D84: 0.91176471 | E84: 1 | F84: Yes | G84: 7.355
A85: 4 | B85: 61 | C85: 5.85 | D85: 0.98387097 | E85: 0.98387097 | F85: Yes | G85: 5.758
A86: 5 | B86: 12 | C86: 4.25 | D86: 0.19672131 | E86: 0.19354839 | F86: No | G86: 0
A87: 6 | B87: 7 | C87: 4.71 | D87: 0.58333333 | E87: 0.11290323 | F87: No | G87: 0
A88: 7 | B88: 7 | C88: 4.29 | D88: 1 | E88: 0.11290323 | F88: No | G88: 0
A89: 8 | B89: 0 | C89: 0 | D89: 0 | E89: 0 | F89: No | G89: 0
A90: 9 | B90: 2 | C90: 3 | D90: — | E90: 0.032258065 | F90: No | G90: 0
A91: New Student Retention (Term 3 ÷ Term 1) | B91: 0.775
A92: Sum of CH Contributions (term 3 through cutoff, while above floor) | B92: 13.113
A93: Sum of Avg CH, included terms (averaging denominator) | B93: 13.207
A94: Credit Hours to Degree (reference only — not used below) | B94: 30
A95: Returning Student Retention (= CH Contributions ÷ Avg CH, included terms) | B95: 0.99285285
A96: LTR Factor (New x Returning) | B96: 0.76946096
A97: First term floor was breached | B97: 5
A99: M494 — Master of Arts in Global Affairs
A100: Relative Term | B100: N (mature-cohort rows) | C100: Avg Credit Hours | D100: Term-over-Term Retention | E100: Ratio vs Term 3 | F100: Above Floor? | G100: CH Contribution
A101: 1 | B101: 248 | C101: 5.58 | D101: — | E101: 1.8787879 | F101: — | G101: 0
A102: 2 | B102: 167 | C102: 5.37 | D102: 0.6733871 | E102: 1.2651515 | F102: — | G102: 0
A103: 3 | B103: 132 | C103: 5.5 | D103: 0.79041916 | E103: 1 | F103: Yes | G103: 5.5
A104: 4 | B104: 154 | C104: 5.68 | D104: 1.1666667 | E104: 1.1666667 | F104: Yes | G104: 6.621
A105: 5 | B105: 133 | C105: 5.15 | D105: 0.86363636 | E105: 1.0075758 | F105: Yes | G105: 5.189
A106: 6 | B106: 111 | C106: 4.95 | D106: 0.83458647 | E106: 0.84090909 | F106: Yes | G106: 4.167
A107: 7 | B107: 74 | C107: 5.04 | D107: 0.66666667 | E107: 0.56060606 | F107: Yes | G107: 2.826
A108: 8 | B108: 43 | C108: 4.49 | D108: 0.58108108 | E108: 0.32575758 | F108: Yes | G108: 1.462
...

Sheet Method B - Detail
A1: 1550C — Certificate in Population Health
A2: No cohort data available for this program in the current pull.
A4: D318 — Ed.D. in Education Administration
A5: Cohort | B5: Order | C5: Mature? | D5: N @ T1 | E5: 1 | F5: 2 | G5: 3 | H5: 4 | I5: 5 | J5: 6 | K5: 7 | L5: 8
A6: 202330 | B6: 13 | C6: N | D6: 64 | E6: 1 | F6: 0.953125 | G6: 0.90625 | H6: 0.859375 | I6: 0.875 | J6: 0.890625 | K6: 0.90625 | L6: 0.84375
A7: 202410 | B7: 14 | C7: N | D7: 8 | E7: 1 | F7: 1 | G7: 1 | H7: 1 | I7: 1 | J7: 1 | K7: 0.875
A8: 202430 | B8: 16 | C8: N | D8: 67 | E8: 1 | F8: 0.92537313 | G8: 0.89552239 | H8: 0.86567164 | I8: 0.85074627
A9: 202530 | B9: 19 | C9: N | D9: 69 | E9: 1 | F9: 0.92753623
A10: Pooled S(t) — student-weighted (mature)
A11: Simple Average S(t) — cohort-weighted (mature)
A12: Cross-check @ Term 3: Pooled=n/a | n/a
A14: M366 — Executive MBA in Energy
A15: Cohort | B15: Order | C15: Mature? | D15: N @ T1 | E15: 1 | F15: 2 | G15: 3 | H15: 4 | I15: 5 | J15: 6 | K15: 7 | L15: 8 | M15: 9 | N15: 10 | O15: 11
A16: 202010 | B16: 2 | C16: Y | D16: 17 | E16: 1 | F16: 1 | G16: 1 | H16: 1 | I16: 0 | J16: 0.058823529 | K16: 0 | L16: 0 | M16: 0 | N16: 0 | O16: 0
A17: 202020 | B17: 3 | C17: Y | D17: 10 | E17: 1 | F17: 1 | G17: 1 | H17: 1 | I17: 0 | J17: 0 | K17: 0 | L17: 0 | M17: 0 | N17: 0 | O17: 0
A18: 202030 | B18: 4 | C18: Y | D18: 11 | E18: 1 | F18: 1 | G18: 0.90909091 | H18: 0.90909091 | I18: 0.81818182 | J18: 0 | K18: 0.090909091 | L18: 0 | M18: 0 | N18: 0 | O18: 0
A19: 202110 | B19: 5 | C19: Y | D19: 9 | E19: 1 | F19: 1 | G19: 0.88888889 | H19: 0.88888889 | I19: 0.88888889 | J19: 0 | K19: 0 | L19: 0 | M19: 0 | N19: 0 | O19: 0
A20: 202130 | B20: 7 | C20: Y | D20: 20 | E20: 1 | F20: 1 | G20: 1 | H20: 0.95 | I20: 0.95 | J20: 0 | K20: 0 | L20: 0 | M20: 0 | N20: 0 | O20: 0
A21: 202210 | B21: 8 | C21: Y | D21: 18 | E21: 1 | F21: 1 | G21: 0.94444444 | H21: 0.94444444 | I21: 0.94444444 | J21: 0.055555556 | K21: 0.055555556 | L21: 0 | M21: 0.055555556 | N21: 0.055555556 | O21: 0.055555556
A22: 202230 | B22: 10 | C22: Y | D22: 12 | E22: 1 | F22: 1 | G22: 1 | H22: 1 | I22: 1 | J22: 0.083333333 | K22: 0 | L22: 0 | M22: 0 | N22: 0 | O22: 0
A23: 202310 | B23: 11 | C23: Y | D23: 15 | E23: 1 | F23: 1 | G23: 1 | H23: 1 | I23: 1 | J23: 0.13333333 | K23: 0 | L23: 0 | M23: 0 | N23: 0
A24: 202330 | B24: 13 | C24: N | D24: 12 | E24: 1 | F24: 1 | G24: 1 | H24: 1 | I24: 1 | J24: 0.083333333 | K24: 0 | L24: 0
A25: 202410 | B25: 14 | C25: N | D25: 12 | E25: 1 | F25: 0.91666667 | G25: 0.91666667 | H25: 0.91666667 | I25: 0.91666667 | J25: 0 | K25: 0
A26: 202430 | B26: 16 | C26: N | D26: 6 | E26: 1 | F26: 1 | G26: 1 | H26: 1 | I26: 1
A27: 202510 | B27: 17 | C27: N | D27: 9 | E27: 1 | F27: 1 | G27: 0.88888889 | H27: 1
A28: 202520 | B28: 18 | C28: N | D28: 1 | E28: 1 | F28: 1 | G28: 1
A29: 202530 | B29: 19 | C29: N | D29: 5 | E29: 1 | F29: 1
A30: Pooled S(t) — student-weighted (mature) | E30: 1 | F30: 1 | G30: 0.97321429 | H30: 0.96428571 | I30: 0.71428571 | J30: 0.044642857 | K30: 0.017857143 | L30: 0 | M30: 0.0089285714 | N30: 0.0089285714 | O30: 0.0089285714
A31: Simple Average S(t) — cohort-weighted (mature) | E31: 1 | F31: 1 | G31: 0.96780303 | H31: 0.96155303 | I31: 0.70018939 | J31: 0.041380719 | K31: 0.018308081 | L31: 0 | M31: 0.0069444444 | N31: 0.0069444444 | O31: 0.0079365079
A32: Cross-check @ Term 3: Pooled=97.3% | Matches Method A
A34: 1231EX — Executive Masters in Health Administration
A35: No cohort data available for this program in the current pull.
A37: M013 — Master of Accountancy
A38: Cohort | B38: Order | C38: Mature? | D38: N @ T1 | E38: 1 | F38: 2 | G38: 3 | H38: 4 | I38: 5 | J38: 6 | K38: 7 | L38: 8 | M38: 9 | N38: 10 | O38: 11 | P38: 12 | Q38: 13 | R38: 14 | S38: 15 | T38: 16
A39: 201930 | B39: 1 | C39: Y | D39: 8 | E39: 1 | F39: 0.875 | G39: 0.75 | H39: 0.125 | I39: 0.375 | J39: 0.25 | K39: 0 | L39: 0.125 | M39: 0 | N39: 0 | O39: 0 | P39: 0 | Q39: 0 | R39: 0 | S39: 0 | T39: 0
A40: 202010 | B40: 2 | C40: Y | D40: 31 | E40: 1 | F40: 0.87096774 | G40: 0.70967742 | H40: 0.64516129 | I40: 0.58064516 | J40: 0.32258065 | K40: 0.29032258 | L40: 0.25806452 | M40: 0.096774194 | N40: 0.12903226 | O40: 0.064516129 | P40: 0.032258065 | Q40: 0.064516129 | R40: 0.032258065 | S40: 0 | T40: 0
A41: 202020 | B41: 3 | C41: Y | D41: 41 | E41: 1 | F41: 0.75609756 | G41: 0.73170732 | H41: 0.70731707 | I41: 0.29268293 | J41: 0.41463415 | K41: 0.26829268 | L41: 0.12195122 | M41: 0.14634146 | N41: 0.12195122 | O41: 0.024390244 | P41: 0.024390244 | Q41: 0.024390244 | R41: 0 | S41: 0 | T41: 0
A42: 202030 | B42: 4 | C42: Y | D42: 12 | E42: 1 | F42: 0.75 | G42: 0.75 | H42: 0.5 | I42: 0.5 | J42: 0.25 | K42: 0.083333333 | L42: 0.083333333 | M42: 0.083333333 | N42: 0.083333333 | O42: 0.083333333 | P42: 0 | Q42: 0 | R42: 0 | S42: 0 | T42: 0
A43: 202110 | B43: 5 | C43: Y | D43: 28 | E43: 1 | F43: 0.92857143 | G43: 0.67857143 | H43: 0.75 | I43: 0.60714286 | J43: 0.32142857 | K43: 0.32142857 | L43: 0.21428571 | M43: 0.10714286 | N43: 0.10714286 | O43: 0.071428571 | P43: 0 | Q43: 0.035714286 | R43: 0.035714286 | S43: 0 | T43: 0.035714286
A44: 202120 | B44: 6 | C44: Y | D44: 29 | E44: 1 | F44: 0.75862069 | G44: 0.75862069 | H44: 0.68965517 | I44: 0.4137931 | J44: 0.51724138 | K44: 0.34482759 | L44: 0.20689655 | M44: 0.20689655 | N44: 0.10344828 | O44: 0.034482759 | P44: 0.10344828 | Q44: 0.034482759 | R44: 0 | S44: 0
A45: 202130 | B45: 7 | C45: Y | D45: 7 | E45: 1 | F45: 1 | G45: 0.85714286 | H45: 0.42857143 | I45: 0.71428571 | J45: 0.42857143 | K45: 0.28571429 | L45: 0.28571429 | M45: 0.14285714 | N45: 0 | O45: 0 | P45: 0 | Q45: 0 | R45: 0
A46: 202210 | B46: 8 | C46: Y | D46: 29 | E46: 1 | F46: 0.89655172 | G46: 0.65517241 | H46: 0.5862069 | I46: 0.48275862 | J46: 0.27586207 | K46: 0.13793103 | L46: 0.13793103 | M46: 0.034482759 | N46: 0.068965517 | O46: 0.034482759 | P46: 0.034482759 | Q46: 0.034482759
A47: 202220 | B47: 9 | C47: Y | D47: 16 | E47: 1 | F47: 0.625 | G47: 0.5625 | H47: 0.4375 | I47: 0.3125 | J47: 0.375 | K47: 0.25 | L47: 0.125 | M47: 0.1875 | N47: 0.0625 | O47: 0.125 | P47: 0
A48: 202230 | B48: 10 | C48: Y | D48: 17 | E48: 1 | F48: 0.58823529 | G48: 0.47058824 | H48: 0.35294118 | I48: 0.41176471 | J48: 0.35294118 | K48: 0.058823529 | L48: 0.11764706 | M48: 0.058823529 | N48: 0.058823529 | O48: 0.058823529
A49: 202310 | B49: 11 | C49: Y | D49: 30 | E49: 1 | F49: 0.8 | G49: 0.6 | H49: 0.56666667 | I49: 0.5 | J49: 0.26666667 | K49: 0.33333333 | L49: 0.16666667 | M49: 0.066666667 | N49: 0.13333333
A50: 202320 | B50: 12 | C50: Y | D50: 24 | E50: 1 | F50: 0.66666667 | G50: 0.83333333 | H50: 0.54166667 | I50: 0.25 | J50: 0.33333333 | K50: 0.16666667 | L50: 0.16666667 | M50: 0
A51: 202330 | B51: 13 | C51: N | D51: 9 | E51: 1 | F51: 1 | G51: 0.66666667 | H51: 0.55555556 | I51: 0.66666667 | J51: 0.33333333 | K51: 0 | L51: 0.11111111
A52: 202410 | B52: 14 | C52: N | D52: 30 | E52: 1 | F52: 0.83333333 | G52: 0.76666667 | H52: 0.8 | I52: 0.66666667 | J52: 0.33333333 | K52: 0.16666667
A53: 202420 | B53: 15 | C53: N | D53: 15 | E53: 1 | F53: 0.6 | G53: 0.86666667 | H53: 0.6 | I53: 0.46666667 | J53: 0.4
A54: 202430 | B54: 16 | C54: N | D54: 14 | E54: 1 | F54: 1 | G54: 0.85714286 | H54: 0.71428571 | I54: 0.71428571
A55: 202510 | B55: 17 | C55: N | D55: 29 | E55: 1 | F55: 0.86206897 | G55: 0.51724138 | H55: 0.62068966
A56: 202520 | B56: 18 | C56: N | D56: 23 | E56: 1 | F56: 0.7826087 | G56: 0.69565217
A57: 202530 | B57: 19 | C57: N | D57: 10 | E57: 1 | F57: 0.9
A58: 202610 | B58: 20 | C58: N | D58: 24 | E58: 1
A59: Pooled S(t) — student-weighted (mature) | E59: 1 | F59: 0.79044118 | G59: 0.69117647 | H59: 0.58823529 | I59: 0.44117647 | J59: 0.34926471 | K59: 0.23897059 | L59: 0.16911765 | M59: 0.099264706 | N59: 0.088235294 | O59: 0.040441176 | P59: 0.022058824 | Q59: 0.022058824 | R59: 0.0073529412 | S59: 0 | T59: 0.0036764706
A60: Simple Average S(t) — cohort-weighted (mature) | E60: 1 | F60: 0.79297593 | G60: 0.69644281 | H60: 0.5275572 | I60: 0.45338109 | J60: 0.34235495 | K60: 0.2117228 | L60: 0.16742975 | M60: 0.094234875 | N60: 0.078957302 | O60: 0.049645732 | P60: 0.021619927 | Q60: 0.024198272 | R60: 0.0097103357 | S60: 0 | T60: 0.0071428571
A61: Cross-check @ Term 3: Pooled=69.1% | Matches Method A
A63: M075 — Master of Arts in Art and Technology
A64: Cohort | B64: Order | C64: Mature? | D64: N @ T1 | E64: 1 | F64: 2 | G64: 3 | H64: 4 | I64: 5 | J64: 6 | K64: 7 | L64: 8 | M64: 9 | N64: 10 | O64: 11 | P64: 12 | Q64: 13
A65: 202110 | B65: 5 | C65: Y | D65: 23 | E65: 1 | F65: 0.86956522 | G65: 0.73913043 | H65: 0.82608696 | I65: 0.69565217 | J65: 0.086956522 | K65: 0 | L65: 0 | M65: 0 | N65: 0 | O65: 0 | P65: 0 | Q65: 0
A66: 202120 | B66: 6 | C66: Y | D66: 27 | E66: 1 | F66: 0.55555556 | G66: 0.55555556 | H66: 0.48148148 | I66: 0.40740741 | J66: 0.037037037 | K66: 0.11111111 | L66: 0 | M66: 0 | N66: 0 | O66: 0 | P66: 0 | Q66: 0
A67: 202210 | B67: 8 | C67: Y | D67: 31 | E67: 1 | F67: 0.87096774 | G67: 0.70967742 | H67: 0.64516129 | I67: 0.64516129 | J67: 0.064516129 | K67: 0.032258065 | L67: 0.032258065 | M67: 0 | N67: 0 | O67: 0.032258065 | P67: 0.032258065 | Q67: 0.032258065
A68: 202220 | B68: 9 | C68: Y | D68: 17 | E68: 1 | F68: 0.94117647 | G68: 0.94117647 | H68: 0.82352941 | I68: 0.70588235 | J68: 0.058823529 | K68: 0.058823529 | L68: 0 | M68: 0.11764706 | N68: 0.11764706 | O68: 0.058823529 | P68: 0
A69: 202310 | B69: 11 | C69: Y | D69: 31 | E69: 1 | F69: 0.83870968 | G69: 0.61290323 | H69: 0.58064516 | I69: 0.5483871 | J69: 0.096774194 | K69: 0.064516129 | L69: 0.032258065 | M69: 0.064516129 | N69: 0.032258065
A70: 202320 | B70: 12 | C70: Y | D70: 17 | E70: 1 | F70: 0.82352941 | G70: 0.70588235 | H70: 0.76470588 | I70: 0.64705882 | J70: 0 | K70: 0 | L70: 0 | M70: 0
A71: 202410 | B71: 14 | C71: N | D71: 30 | E71: 1 | F71: 0.83333333 | G71: 0.7 | H71: 0.6 | I71: 0.53333333 | J71: 0.23333333 | K71: 0.13333333
A72: 202420 | B72: 15 | C72: N | D72: 15 | E72: 1 | F72: 0.66666667 | G72: 0.66666667 | H72: 0.6 | I72: 0.6 | J72: 0.26666667
A73: 202510 | B73: 17 | C73: N | D73: 18 | E73: 1 | F73: 1 | G73: 0.55555556 | H73: 0.61111111
A74: 202520 | B74: 18 | C74: N | D74: 15 | E74: 1 | F74: 0.93333333 | G74: 0.73333333
A75: 202610 | B75: 20 | C75: N | D75: 11 | E75: 1
A76: Pooled S(t) — student-weighted (mature) | E76: 1 | F76: 0.80821918 | G76: 0.69178082 | H76: 0.66438356 | I76: 0.59589041 | J76: 0.061643836 | K76: 0.047945205 | L76: 0.01369863 | M76: 0.02739726 | N76: 0.020547945 | O76: 0.01369863 | P76: 0.0068493151 | Q76: 0.0068493151
A77: Simple Average S(t) — cohort-weighted (mature) | E77: 1 | F77: 0.81658401 | G77: 0.71072091 | H77: 0.68693503 | I77: 0.60825819 | J77: 0.057351235 | K77: 0.044451472 | L77: 0.010752688 | M77: 0.030360531 | N77: 0.029981025 | O77: 0.022770398 | P77: 0.0080645161 | Q77: 0.010752688
A78: Cross-check @ Term 3: Pooled=69.2% | Matches Method A
A80: M073 — Master of Arts in Arts Management
A81: Cohort | B81: Order | C81: Mature? | D81: N @ T1 | E81: 1 | F81: 2 | G81: 3 | H81: 4 | I81: 5 | J81: 6 | K81: 7 | L81: 8 | M81: 9
A82: 202220 | B82: 9 | C82: Y | D82: 6 | E82: 1 | F82: 1 | G82: 1 | H82: 0.83333333 | I82: 0.16666667 | J82: 0.33333333 | K82: 0.16666667 | L82: 0 | M82: 0
A83: 202230 | B83: 10 | C83: Y | D83: 1 | E83: 1 | F83: 1 | G83: 1 | H83: 1 | I83: 1 | J83: 0 | K83: 0 | L83: 0 | M83: 0
A84: 202310 | B84: 11 | C84: Y | D84: 31 | E84: 1 | F84: 0.87096774 | G84: 0.77419355 | H84: 0.80645161 | I84: 0.19354839 | J84: 0.064516129 | K84: 0.032258065 | L84: 0 | M84: 0
A85: 202320 | B85: 12 | C85: Y | D85: 42 | E85: 1 | F85: 0.80952381 | G85: 0.73809524 | H85: 0.71428571 | I85: 0.095238095 | J85: 0.071428571 | K85: 0.11904762 | L85: 0 | M85: 0.047619048
A86: 202410 | B86: 14 | C86: N | D86: 28 | E86: 1 | F86: 0.89285714 | G86: 0.82142857 | H86: 0.75 | I86: 0.25 | J86: 0.21428571 | K86: 0.17857143
A87: 202420 | B87: 15 | C87: N | D87: 31 | E87: 1 | F87: 0.77419355 | G87: 0.87096774 | H87: 0.83870968 | I87: 0.22580645 | J87: 0.12903226
A88: 202510 | B88: 17 | C88: N | D88: 39 | E88: 1 | F88: 0.84615385 | G88: 0.74358974 | H88: 0.61538462
A89: 202520 | B89: 18 | C89: N | D89: 16 | E89: 1 | F89: 0.6875 | G89: 0.8125
A90: 202610 | B90: 20 | C90: N | D90: 23 | E90: 1
A91: Pooled S(t) — student-weighted (mature) | E91: 1 | F91: 0.85 | G91: 0.775 | H91: 0.7625 | I91: 0.15 | J91: 0.0875 | K91: 0.0875 | L91: 0 | M91: 0.025
A92: Simple Average S(t) — cohort-weighted (mature) | E92: 1 | F92: 0.92012289 | G92: 0.8780722 | H92: 0.83851767 | I92: 0.36386329 | J92: 0.11731951 | K92: 0.079493088 | L92: 0 | M92: 0.011904762
A93: Cross-check @ Term 3: Pooled=77.5% | Matches Method A
A95: M494 — Master of Arts in Global Affairs
A96: Cohort | B96: Order | C96: Mature? | D96: N @ T1 | E96: 1 | F96: 2 | G96: 3 | H96: 4 | I96: 5 | J96: 6 | K96: 7 | L96: 8 | M96: 9 | N96: 10 | O96: 11 | P96: 12 | Q96: 13 | R96: 14 | S96: 15 | T96: 16 | U96: 17
A97: 201930 | B97: 1 | C97: Y | D97: 4 | E97: 1 | F97: 0.5 | G97: 0.5 | H97: 0.25 | I97: 0.5 | J97: 0.5 | K97: 0.25 | L97: 0.25 | M97: 0.25 | N97: 0 | O97: 0 | P97: 0 | Q97: 0 | R97: 0 | S97: 0 | T97: 0 | U97: 0
A98: 202010 | B98: 2 | C98: Y | D98: 27 | E98: 1 | F98: 0.74074074 | G98: 0.22222222 | H98: 0.59259259 | I98: 0.44444444 | J98: 0.37037037 | K98: 0.22222222 | L98: 0.11111111 | M98: 0.11111111 | N98: 0.037037037 | O98: 0 | P98: 0 | Q98: 0 | R98: 0 | S98: 0 | T98: 0 | U98: 0
A99: 202020 | B99: 3 | C99: Y | D99: 25 | E99: 1 | F99: 0.36 | G99: 0.72 | H99: 0.68 | I99: 0.44 | J99: 0.52 | K99: 0.4 | L99: 0.08 | M99: 0.04 | N99: 0.08 | O99: 0 | P99: 0.08 | Q99: 0.04 | R99: 0 | S99: 0 | T99: 0 | U99: 0
A100: 202030 | B100: 4 | C100: Y | D100: 10 | E100: 1 | F100: 0.9 | G100: 0.6 | H100: 0.5 | I100: 0.5 | J100: 0.3 | K100: 0.2 | L100: 0.2 | M100: 0 | N100: 0 | O100: 0 | P100: 0 | Q100: 0.1 | R100: 0.2 | S100: 0.2 | T100: 0.1 | U100: 0.1
A101: 202110 | B101: 5 | C101: Y | D101: 21 | E101: 1 | F101: 0.85714286 | G101: 0.23809524 | H101: 0.76190476 | I101: 0.71428571 | J101: 0.66666667 | K101: 0.42857143 | L101: 0.33333333 | M101: 0.095238095 | N101: 0.095238095 | O101: 0 | P101: 0 | Q101: 0 | R101: 0 | S101: 0 | T101: 0
A102: 202120 | B102: 6 | C102: Y | D102: 15 | E102: 1 | F102: 0.46666667 | G102: 0.8 | H102: 0.66666667 | I102: 0.53333333 | J102: 0.46666667 | K102: 0.33333333 | L102: 0.13333333 | M102: 0.13333333 | N102: 0.066666667 | O102: 0 | P102: 0.13333333 | Q102: 0.066666667 | R102: 0.066666667 | S102: 0
A103: 202130 | B103: 7 | C103: Y | D103: 5 | E103: 1 | F103: 1 | G103: 0.6 | H103: 0.4 | I103: 0.6 | J103: 0.4 | K103: 0 | L103: 0.2 | M103: 0 | N103: 0 | O103: 0 | P103: 0 | Q103: 0 | R103: 0
A104: 202210 | B104: 8 | C104: Y | D104: 32 | E104: 1 | F104: 0.8125 | G104: 0.375 | H104: 0.65625 | I104: 0.53125 | J104: 0.1875 | K104: 0.25 | L104: 0.1875 | M104: 0.0625 | N104: 0.09375 | O104: 0.0625 | P104: 0 | Q104: 0.03125
A105: 202220 | B105: 9 | C105: Y | D105: 25 | E105: 1 | F105: 0.4 | G105: 0.56 | H105: 0.6 | I105: 0.44 | J105: 0.48 | K105: 0.28 | L105: 0.12 | M105: 0.08 | N105: 0.04 | O105: 0.08 | P105: 0.12
A106: 202230 | B106: 10 | C106: Y | D106: 15 | E106: 1 | F106: 0.8 | G106: 0.8 | H106: 0.53333333 | I106: 0.66666667 | J106: 0.46666667 | K106: 0.33333333 | L106: 0.26666667 | M106: 0.13333333 | N106: 0 | O106: 0.066666667
A107: 202310 | B107: 11 | C107: Y | D107: 27 | E107: 1 | F107: 0.85185185 | G107: 0.37037037 | H107: 0.7037037 | I107: 0.74074074 | J107: 0.51851852 | K107: 0.44444444 | L107: 0.25925926 | M107: 0.18518519 | N107: 0.037037037
...

Sheet Current-Year Tracker
A1: Current-Year Tracker — leading indicator, layered on top of the historical view above
A2: Method A/B (previous sheets) can only judge a cohort once it's mature (≥9 terms elapsed) — by nature, a lagging view. This sheet tracks whatever a program's newest cohorts have shown so far, against that program's own historical benchmark, to flag deterioration before it would show up as a bad Early Persistence number two terms from now.
A4: Current-year terms tracked | B4: 202520, 202530, 202610
A5: Deterioration flag threshold | B5: 0.1 | C5: Flag fires when a current cohort's step ratio runs this many points or more below the historical mature-cohort benchmark for that same step.
A6: Thin-sample threshold (students at T1) | B6: 30
A8: Watch List — flagged current-cohort steps this run
A9: Code | B9: Program | C9: Historical Quadrant | D9: Cohort (Entry Term) | E9: Flagged Step | F9: Current Value | G9: Historical Benchmark | H9: Δ (pp) | I9: Thin Sample?
A10: M464 | B10: Master of Science in Geospatial Technology | C10: Early Risk | D10: 202520 | E10: T1→T2 | F10: 0.6 | G10: 0.83495146 | H10: -0.23495146 | I10: Yes
A11: M073 | B11: Master of Arts in Arts Management | C11: Not screened (below viability threshold) | D11: 202520 | E11: T1→T2 | F11: 0.6875 | G11: 0.85 | H11: -0.1625 | I11: Yes
A12: M700 | B12: Master of Arts in Museum Studies | C12: Double Risk | D12: 202520 | E12: T1→T2 | F12: 0.62790698 | G12: 0.7721519 | H12: -0.14424492 | I12: No
A13: M522 | B13: Master of Legal Studies - Indigenous Peoples Law | C13: Healthy | D13: 202520 | E13: T1→T2 | F13: 0.65217391 | G13: 0.79151943 | H13: -0.13934552 | I13: Yes
A14: M435 | B14: Master of Science in Finance | C14: Healthy | D14: 202520 | E14: T2→T3 | F14: 0.77777778 | G14: 0.91121495 | H14: -0.13343718 | I14: Yes
A15: M260 | B15: Master of Science in Criminal Justice | C15: Early Risk | D15: 202530 | E15: T1→T2 | F15: 0.57142857 | G15: 0.70183486 | H15: -0.13040629 | I15: Yes
A16: M260 | B16: Master of Science in Criminal Justice | C16: Early Risk | D16: 202520 | E16: T1→T2 | F16: 0.58333333 | G16: 0.70183486 | H16: -0.11850153 | I16: Yes
A17: M527 | B17: Master of Science in Industrial and Systems Engineering | C17: Double Risk | D17: 202520 | E17: T1→T2 | F17: 0.56666667 | G17: 0.67032967 | H17: -0.103663 | I17: No
A18: 3 additional program(s) showed a flagged step this run but are left off this Watch List because their own historical benchmark rests on fewer than 30 mature-cohort students — comparing a new cohort against a benchmark that thin is noise, not signal. They're still shown, fully transparently, in the per-program detail below.
A20: Per-program detail — last three entering cohorts
A22: 1550C — Certificate in Population Health | Historical quadrant: Not screened (below viability threshold)
A23: No current-year cohort data available (no new entrants tracked in the last 3 terms for this program).
A25: D318 — Ed.D. in Education Administration | Historical quadrant: Not screened (below viability threshold)
A26: Historical benchmark (pooled mature cohorts) | I26: Benchmark thin (<30)
A27: Entry Term | B27: N @ T1 | C27: T1→T2 | D27: Δ vs Hist. (pp) | E27: T2→T3 | F27: Δ vs Hist. (pp) | G27: T1→T3 (Early Persistence) | H27: Δ vs Hist. (pp) | I27: Sample Flag
A28: 202530 | B28: 69 | C28: 0.92753623 | D28: — | E28: — | F28: — | G28: — | H28: — | I28: OK
A30: M366 — Executive MBA in Energy | Historical quadrant: Healthy
A31: Historical benchmark (pooled mature cohorts) | B31: 112 | C31: 1 | E31: 0.97321429 | G31: 0.97321429
A32: Entry Term | B32: N @ T1 | C32: T1→T2 | D32: Δ vs Hist. (pp) | E32: T2→T3 | F32: Δ vs Hist. (pp) | G32: T1→T3 (Early Persistence) | H32: Δ vs Hist. (pp) | I32: Sample Flag
A33: 202520 | B33: 1 | C33: 1 | D33: 0 | E33: 1 | F33: 0.026785714 | G33: 1 | H33: 0.026785714 | I33: Thin (<30)
A34: 202530 | B34: 5 | C34: 1 | D34: 0 | E34: — | F34: — | G34: — | H34: — | I34: Thin (<30)
A36: 1231EX — Executive Masters in Health Administration | Historical quadrant: Not screened (below viability threshold)
A37: No current-year cohort data available (no new entrants tracked in the last 3 terms for this program).
A39: M013 — Master of Accountancy | Historical quadrant: Double Risk
A40: Historical benchmark (pooled mature cohorts) | B40: 272 | C40: 0.79044118 | E40: 0.8744186 | G40: 0.69117647
A41: Entry Term | B41: N @ T1 | C41: T1→T2 | D41: Δ vs Hist. (pp) | E41: T2→T3 | F41: Δ vs Hist. (pp) | G41: T1→T3 (Early Persistence) | H41: Δ vs Hist. (pp) | I41: Sample Flag
A42: 202520 | B42: 23 | C42: 0.7826087 | D42: -0.0078324808 | E42: 0.88888889 | F42: 0.014470284 | G42: 0.69565217 | H42: 0.0044757033 | I42: Thin (<30)
A43: 202530 | B43: 10 | C43: 0.9 | D43: 0.10955882 | E43: — | F43: — | G43: — | H43: — | I43: Thin (<30)
A44: 202610 | B44: 24 | C44: — | D44: — | E44: — | F44: — | G44: — | H44: — | I44: Thin (<30)
A46: M075 — Master of Arts in Art and Technology | Historical quadrant: Double Risk
A47: Historical benchmark (pooled mature cohorts) | B47: 146 | C47: 0.80821918 | E47: 0.8559322 | G47: 0.69178082
A48: Entry Term | B48: N @ T1 | C48: T1→T2 | D48: Δ vs Hist. (pp) | E48: T2→T3 | F48: Δ vs Hist. (pp) | G48: T1→T3 (Early Persistence) | H48: Δ vs Hist. (pp) | I48: Sample Flag
A49: 202520 | B49: 15 | C49: 0.93333333 | D49: 0.12511416 | E49: 0.78571429 | F49: -0.070217918 | G49: 0.73333333 | H49: 0.041552511 | I49: Thin (<30)
A50: 202610 | B50: 11 | C50: — | D50: — | E50: — | F50: — | G50: — | H50: — | I50: Thin (<30)
A52: M073 — Master of Arts in Arts Management | Historical quadrant: Not screened (below viability threshold)
A53: Historical benchmark (pooled mature cohorts) | B53: 80 | C53: 0.85 | E53: 0.91176471 | G53: 0.775
A54: Entry Term | B54: N @ T1 | C54: T1→T2 | D54: Δ vs Hist. (pp) | E54: T2→T3 | F54: Δ vs Hist. (pp) | G54: T1→T3 (Early Persistence) | H54: Δ vs Hist. (pp) | I54: Sample Flag
A55: 202520 | B55: 16 | C55: 0.6875 | D55: -0.1625 | E55: 1.1818182 | F55: 0.27005348 | G55: 0.8125 | H55: 0.0375 | I55: Thin (<30)
A56: 202610 | B56: 23 | C56: — | D56: — | E56: — | F56: — | G56: — | H56: — | I56: Thin (<30)
A58: M494 — Master of Arts in Global Affairs | Historical quadrant: Double Risk
A59: Historical benchmark (pooled mature cohorts) | B59: 248 | C59: 0.6733871 | E59: 0.79041916 | G59: 0.53225806
A60: Entry Term | B60: N @ T1 | C60: T1→T2 | D60: Δ vs Hist. (pp) | E60: T2→T3 | F60: Δ vs Hist. (pp) | G60: T1→T3 (Early Persistence) | H60: Δ vs Hist. (pp) | I60: Sample Flag
A61: 202520 | B61: 21 | C61: 0.61904762 | D61: -0.054339478 | E61: 1.1538462 | F61: 0.36342699 | G61: 0.71428571 | H61: 0.18202765 | I61: Thin (<30)
A62: 202530 | B62: 9 | C62: 1 | D62: 0.3266129 | E62: — | F62: — | G62: — | H62: — | I62: Thin (<30)
A63: 202610 | B63: 13 | C63: — | D63: — | E63: — | F63: — | G63: — | H63: — | I63: Thin (<30)
A65: M700 — Master of Arts in Museum Studies | Historical quadrant: Double Risk
A66: Historical benchmark (pooled mature cohorts) | B66: 474 | C66: 0.7721519 | E66: 0.84699454 | G66: 0.65400844
A67: Entry Term | B67: N @ T1 | C67: T1→T2 | D67: Δ vs Hist. (pp) | E67: T2→T3 | F67: Δ vs Hist. (pp) | G67: T1→T3 (Early Persistence) | H67: Δ vs Hist. (pp) | I67: Sample Flag
A68: 202520 | B68: 43 | C68: 0.62790698 | D68: -0.14424492 | E68: 1 | F68: 0.15300546 | G68: 0.62790698 | H68: -0.026101462 | I68: OK
A69: 202530 | B69: 22 | C69: 0.81818182 | D69: 0.046029919 | E69: — | F69: — | G69: — | H69: — | I69: Thin (<30)
A70: 202610 | B70: 51 | C70: — | D70: — | E70: — | F70: — | G70: — | H70: — | I70: OK
A72: M762 — Master of Arts in Organizational Leadership | Historical quadrant: Double Risk
A73: Historical benchmark (pooled mature cohorts) | B73: 505 | C73: 0.68514851 | E73: 0.83236994 | G73: 0.57029703
A74: Entry Term | B74: N @ T1 | C74: T1→T2 | D74: Δ vs Hist. (pp) | E74: T2→T3 | F74: Δ vs Hist. (pp) | G74: T1→T3 (Early Persistence) | H74: Δ vs Hist. (pp) | I74: Sample Flag
A75: 202520 | B75: 34 | C75: 0.76470588 | D75: 0.079557368 | E75: 0.88461538 | F75: 0.052245442 | G75: 0.67647059 | H75: 0.10617356 | I75: OK
A76: 202530 | B76: 22 | C76: 0.72727273 | D76: 0.042124212 | E76: — | F76: — | G76: — | H76: — | I76: Thin (<30)
A77: 202610 | B77: 48 | C77: — | D77: — | E77: — | F77: — | G77: — | H77: — | I77: OK
A79: M859 — Master of Arts in Strategic Communication and Digital Strategy | Historical quadrant: Healthy
A80: Historical benchmark (pooled mature cohorts) | B80: 256 | C80: 0.8515625 | E80: 0.95412844 | G80: 0.8125
A81: Entry Term | B81: N @ T1 | C81: T1→T2 | D81: Δ vs Hist. (pp) | E81: T2→T3 | F81: Δ vs Hist. (pp) | G81: T1→T3 (Early Persistence) | H81: Δ vs Hist. (pp) | I81: Sample Flag
A82: 202520 | B82: 16 | C82: 0.8125 | D82: -0.0390625 | E82: 1.1538462 | F82: 0.19971771 | G82: 0.9375 | H82: 0.125 | I82: Thin (<30)
A83: 202530 | B83: 10 | C83: 1 | D83: 0.1484375 | E83: — | F83: — | G83: — | H83: — | I83: Thin (<30)
A84: 202610 | B84: 13 | C84: — | D84: — | E84: — | F84: — | G84: — | H84: — | I84: Thin (<30)
A86: M202 — Master of Clinical Mental Health Counseling | Historical quadrant: Post-T3 Risk
A87: Historical benchmark (pooled mature cohorts) | B87: 240 | C87: 0.8375 | E87: 0.94029851 | G87: 0.7875
A88: Entry Term | B88: N @ T1 | C88: T1→T2 | D88: Δ vs Hist. (pp) | E88: T2→T3 | F88: Δ vs Hist. (pp) | G88: T1→T3 (Early Persistence) | H88: Δ vs Hist. (pp) | I88: Sample Flag
A89: 202520 | B89: 43 | C89: 0.88372093 | D89: 0.04622093 | E89: 0.86842105 | F89: -0.071877455 | G89: 0.76744186 | H89: -0.02005814 | I89: OK
A90: 202530 | B90: 10 | C90: 0.9 | D90: 0.0625 | E90: — | F90: — | G90: — | H90: — | I90: Thin (<30)
A91: 202610 | B91: 51 | C91: — | D91: — | E91: — | F91: — | G91: — | H91: — | I91: OK
A93: M246 — Master of Construction Business | Historical quadrant: Healthy
A94: Historical benchmark (pooled mature cohorts) | B94: 115 | C94: 0.88695652 | E94: 0.98039216 | G94: 0.86956522
A95: Entry Term | B95: N @ T1 | C95: T1→T2 | D95: Δ vs Hist. (pp) | E95: T2→T3 | F95: Δ vs Hist. (pp) | G95: T1→T3 (Early Persistence) | H95: Δ vs Hist. (pp) | I95: Sample Flag
A96: 202520 | B96: 13 | C96: 0.92307692 | D96: 0.036120401 | E96: 1 | F96: 0.019607843 | G96: 0.92307692 | H96: 0.053511706 | I96: Thin (<30)
A97: 202610 | B97: 14 | C97: — | D97: — | E97: — | F97: — | G97: — | H97: — | I97: Thin (<30)
A99: M297 — Master of Econometrics | Historical quadrant: Not screened (below viability threshold)
A100: Historical benchmark (pooled mature cohorts) | I100: Benchmark thin (<30)
A101: Entry Term | B101: N @ T1 | C101: T1→T2 | D101: Δ vs Hist. (pp) | E101: T2→T3 | F101: Δ vs Hist. (pp) | G101: T1→T3 (Early Persistence) | H101: Δ vs Hist. (pp) | I101: Sample Flag
A102: 202520 | B102: 10 | C102: 0.8 | D102: — | E102: 1 | F102: — | G102: 0.8 | H102: — | I102: Thin (<30)
A103: 202610 | B103: 7 | C103: — | D103: — | E103: — | F103: — | G103: — | H103: — | I103: Thin (<30)
A105: M383 — Master of Entrepreneurship & Innovation | Historical quadrant: Not screened (below viability threshold)
A106: Historical benchmark (pooled mature cohorts) | I106: Benchmark thin (<30)
A107: Entry Term | B107: N @ T1 | C107: T1→T2 | D107: Δ vs Hist. (pp) | E107: T2→T3 | F107: Δ vs Hist. (pp) | G107: T1→T3 (Early Persistence) | H107: Δ vs Hist. (pp) | I107: Sample Flag
A108: 202520 | B108: 7 | C108: 0.71428571 | D108: — | E108: 1 | F108: — | G108: 0.71428571 | H108: — | I108: Thin (<30)
A109: 202610 | B109: 6 | C109: — | D109: — | E109: — | F109: — | G109: — | H109: — | I109: Thin (<30)
A111: M518 — Master of Environmental Science: Hydrology and Water Security | Historical quadrant: Healthy
A112: Historical benchmark (pooled mature cohorts) | B112: 254 | C112: 0.79133858 | E112: 0.91542289 | G112: 0.72440945
A113: Entry Term | B113: N @ T1 | C113: T1→T2 | D113: Δ vs Hist. (pp) | E113: T2→T3 | F113: Δ vs Hist. (pp) | G113: T1→T3 (Early Persistence) | H113: Δ vs Hist. (pp) | I113: Sample Flag
A114: 202520 | B114: 18 | C114: 0.88888889 | D114: 0.097550306 | E114: 0.875 | F114: -0.040422886 | G114: 0.77777778 | H114: 0.053368329 | I114: Thin (<30)
A115: 202610 | B115: 32 | C115: — | D115: — | E115: — | F115: — | G115: — | H115: — | I115: OK
A117: M368 — Master of Legal Studies - Energy | Historical quadrant: Early Risk
A118: Historical benchmark (pooled mature cohorts) | B118: 82 | C118: 0.76829268 | E118: 0.92063492 | G118: 0.70731707
A119: Entry Term | B119: N @ T1 | C119: T1→T2 | D119: Δ vs Hist. (pp) | E119: T2→T3 | F119: Δ vs Hist. (pp) | G119: T1→T3 (Early Persistence) | H119: Δ vs Hist. (pp) | I119: Sample Flag
A120: 202520 | B120: 7 | C120: 0.71428571 | D120: -0.054006969 | E120: 1.2 | F120: 0.27936508 | G120: 0.85714286 | H120: 0.14982578 | I120: Thin (<30)
...

Sheet Headcount Waterfall
A1: Headcount Waterfall — mature-cohort population, Term 1 through the last term reached
A2: Real observed counts, not a re-derived curve — this is the same pooled mature-cohort term-by-term count that both Method A's New Student Retention and Method B's Pooled S(t) are built from. Shaded rows mark where a program first drops below 20% of its own Term-3 base.
A4: All 41 Graduate Programs — Combined
A5: Caveat: this combined curve pools relative terms across all 41 programs regardless of length or credit-hours-to-degree, so "relative term 5" blends a program built to finish in 30 credit hours with one built to take 60 -- they are at very different points in their own lifecycle at the same relative term. Treat this as a rough portfolio-wide shape only; the real, decision-grade signal is in the per-program curves below, not this aggregate.
A6: Relative Term | B6: Headcount (N) | C6: Change from Prior Term | D6: Term-over-Term Retention | E6: % of Term 1 Remaining | F6: Above 20% Floor?
A7: 1 | B7: 5841 | E7: 1 | F7: —
A8: 2 | B8: 4638 | C8: -1203 | D8: 0.79404212 | E8: 0.79404212 | F8: —
A9: 3 | B9: 4092 | C9: -546 | D9: 0.88227684 | E9: 0.70056497 | F9: Yes
A10: 4 | B10: 4022 | C10: -70 | D10: 0.98289345 | E10: 0.68858072 | F10: Yes
A11: 5 | B11: 2755 | C11: -1267 | D11: 0.6849826 | E11: 0.47166581 | F11: Yes
A12: 6 | B12: 1774 | C12: -981 | D12: 0.64392015 | E12: 0.30371512 | F12: Yes
A13: 7 | B13: 1355 | C13: -419 | D13: 0.7638106 | E13: 0.23198083 | F13: Yes
A14: 8 | B14: 822 | C14: -533 | D14: 0.60664207 | E14: 0.14072933 | F14: Yes
A15: 9 | B15: 463 | C15: -359 | D15: 0.56326034 | E15: 0.079267249 | F15: Yes
A16: 10 | B16: 262 | C16: -201 | D16: 0.56587473 | E16: 0.044855333 | F16: Yes
A17: 11 | B17: 140 | C17: -122 | D17: 0.53435115 | E17: 0.023968499 | F17: Yes
A18: 12 | B18: 75 | C18: -65 | D18: 0.53571429 | E18: 0.012840267 | F18: Yes
A19: 13 | B19: 51 | C19: -24 | D19: 0.68 | E19: 0.0087313816 | F19: Yes
... A24: 18 | B24: 3 | C24: -3 | D24: 0.5 | E24: 0.00051361068 | F24: Yes
A25: Summary | B25: T1=5841 → T18=3 | C25: -5838 | E25: 0.00051361068
A27: 1550C — Certificate in Population Health | Historical quadrant: Not screened (below viability threshold)
A28: No mature-cohort data available for this program in the current pull.
A30: D318 — Ed.D. in Education Administration | Historical quadrant: Not screened (below viability threshold)
A31: No mature-cohort data available for this program in the current pull.
A33: M366 — Executive MBA in Energy | Historical quadrant: Healthy
A34: Relative Term | B34: Headcount (N) | C34: Change from Prior Term | D34: Term-over-Term Retention | E34: % of Term 1 Remaining | F34: Above 20% Floor?
A35: 1 | B35: 112 | E35: 1 | F35: —
A36: 2 | B36: 112 | C36: 0 | D36: 1 | E36: 1 | F36: —
A37: 3 | B37: 109 | C37: -3 | D37: 0.97321429 | E37: 0.97321429 | F37: Yes
A38: 4 | B38: 108 | C38: -1 | D38: 0.99082569 | E38: 0.96428571 | F38: Yes
A39: 5 | B39: 80 | C39: -28 | D39: 0.74074074 | E39: 0.71428571 | F39: Yes
A40: 6 | B40: 5 | C40: -75 | D40: 0.0625 | E40: 0.044642857 | F40: No
A41: 7 | B41: 2 | C41: -3 | D41: 0.4 | E41: 0.017857143 | F41: No
A42: 8 | B42: 0 | C42: -2 | D42: 0 | E42: 0 | F42: No
A43: 9 | B43: 1 | C43: 1 | E43: 0.0089285714 | F43: No
A44: 10 | B44: 1 | C44: 0 | D44: 1 | E44: 0.0089285714 | F44: No
A45: 11 | B45: 1 | C45: 0 | D45: 1 | E45: 0.0089285714 | F45: No
A46: Summary | B46: T1=112 → T11=1 | C46: -111 | E46: 0.0089285714
A48: 1231EX — Executive Masters in Health Administration | Historical quadrant: Not screened (below viability threshold)
A49: No mature-cohort data available for this program in the current pull.
A51: M013 — Master of Accountancy | Historical quadrant: Double Risk
A52: Relative Term | B52: Headcount (N) | C52: Change from Prior Term | D52: Term-over-Term Retention | E52: % of Term 1 Remaining | F52: Above 20% Floor?
A53: 1 | B53: 272 | E53: 1 | F53: —
A54: 2 | B54: 215 | C54: -57 | D54: 0.79044118 | E54: 0.79044118 | F54: —
A55: 3 | B55: 188 | C55: -27 | D55: 0.8744186 | E55: 0.69117647 | F55: Yes
A56: 4 | B56: 160 | C56: -28 | D56: 0.85106383 | E56: 0.58823529 | F56: Yes
A57: 5 | B57: 120 | C57: -40 | D57: 0.75 | E57: 0.44117647 | F57: Yes
A58: 6 | B58: 95 | C58: -25 | D58: 0.79166667 | E58: 0.34926471 | F58: Yes
A59: 7 | B59: 65 | C59: -30 | D59: 0.68421053 | E59: 0.23897059 | F59: Yes
A60: 8 | B60: 46 | C60: -19 | D60: 0.70769231 | E60: 0.16911765 | F60: Yes
A61: 9 | B61: 27 | C61: -19 | D61: 0.58695652 | E61: 0.099264706 | F61: No
A62: 10 | B62: 24 | C62: -3 | D62: 0.88888889 | E62: 0.088235294 | F62: No
A63: 11 | B63: 11 | C63: -13 | D63: 0.45833333 | E63: 0.040441176 | F63: No
A64: 12 | B64: 6 | C64: -5 | D64: 0.54545455 | E64: 0.022058824 | F64: No
A65: 13 | B65: 6 | C65: 0 | D65: 1 | E65: 0.022058824 | F65: No
... A67: 15 | B67: 0 | C67: -2 | D67: 0 | E67: 0 | F67: No
A68: 16 | B68: 1 | C68: 1 | E68: 0.0036764706 | F68: No
A69: Summary | B69: T1=272 → T16=1 | C69: -271 | E69: 0.0036764706
A71: M075 — Master of Arts in Art and Technology | Historical quadrant: Double Risk
A72: Relative Term | B72: Headcount (N) | C72: Change from Prior Term | D72: Term-over-Term Retention | E72: % of Term 1 Remaining | F72: Above 20% Floor?
A73: 1 | B73: 146 | E73: 1 | F73: —
A74: 2 | B74: 118 | C74: -28 | D74: 0.80821918 | E74: 0.80821918 | F74: —
A75: 3 | B75: 101 | C75: -17 | D75: 0.8559322 | E75: 0.69178082 | F75: Yes
A76: 4 | B76: 97 | C76: -4 | D76: 0.96039604 | E76: 0.66438356 | F76: Yes
A77: 5 | B77: 87 | C77: -10 | D77: 0.89690722 | E77: 0.59589041 | F77: Yes
A78: 6 | B78: 9 | C78: -78 | D78: 0.10344828 | E78: 0.061643836 | F78: No
A79: 7 | B79: 7 | C79: -2 | D79: 0.77777778 | E79: 0.047945205 | F79: No
A80: 8 | B80: 2 | C80: -5 | D80: 0.28571429 | E80: 0.01369863 | F80: No
A81: 9 | B81: 4 | C81: 2 | D81: 2 | E81: 0.02739726 | F81: No
A82: 10 | B82: 3 | C82: -1 | D82: 0.75 | E82: 0.020547945 | F82: No
A83: 11 | B83: 2 | C83: -1 | D83: 0.66666667 | E83: 0.01369863 | F83: No
A84: 12 | B84: 1 | C84: -1 | D84: 0.5 | E84: 0.0068493151 | F84: No
A85: 13 | B85: 1 | C85: 0 | D85: 1 | E85: 0.0068493151 | F85: No
A86: Summary | B86: T1=146 → T13=1 | C86: -145 | E86: 0.0068493151
A88: M073 — Master of Arts in Arts Management | Historical quadrant: Not screened (below viability threshold)
A89: Relative Term | B89: Headcount (N) | C89: Change from Prior Term | D89: Term-over-Term Retention | E89: % of Term 1 Remaining | F89: Above 20% Floor?
A90: 1 | B90: 80 | E90: 1 | F90: —
A91: 2 | B91: 68 | C91: -12 | D91: 0.85 | E91: 0.85 | F91: —
A92: 3 | B92: 62 | C92: -6 | D92: 0.91176471 | E92: 0.775 | F92: Yes
A93: 4 | B93: 61 | C93: -1 | D93: 0.98387097 | E93: 0.7625 | F93: Yes
A94: 5 | B94: 12 | C94: -49 | D94: 0.19672131 | E94: 0.15 | F94: No
A95: 6 | B95: 7 | C95: -5 | D95: 0.58333333 | E95: 0.0875 | F95: No
A96: 7 | B96: 7 | C96: 0 | D96: 1 | E96: 0.0875 | F96: No
A97: 8 | B97: 0 | C97: -7 | D97: 0 | E97: 0 | F97: No
A98: 9 | B98: 2 | C98: 2 | E98: 0.025 | F98: No
A99: Summary | B99: T1=80 → T9=2 | C99: -78 | E99: 0.025
A101: M494 — Master of Arts in Global Affairs | Historical quadrant: Double Risk
A102: Relative Term | B102: Headcount (N) | C102: Change from Prior Term | D102: Term-over-Term Retention | E102: % of Term 1 Remaining | F102: Above 20% Floor?
A103: 1 | B103: 248 | E103: 1 | F103: —
A104: 2 | B104: 167 | C104: -81 | D104: 0.6733871 | E104: 0.6733871 | F104: —
A105: 3 | B105: 132 | C105: -35 | D105: 0.79041916 | E105: 0.53225806 | F105: Yes
A106: 4 | B106: 154 | C106: 22 | D106: 1.1666667 | E106: 0.62096774 | F106: Yes
A107: 5 | B107: 133 | C107: -21 | D107: 0.86363636 | E107: 0.53629032 | F107: Yes
A108: 6 | B108: 111 | C108: -22 | D108: 0.83458647 | E108: 0.44758065 | F108: Yes
A109: 7 | B109: 74 | C109: -37 | D109: 0.66666667 | E109: 0.2983871 | F109: Yes
A110: 8 | B110: 43 | C110: -31 | D110: 0.58108108 | E110: 0.1733871 | F110: Yes
A111: 9 | B111: 24 | C111: -19 | D111: 0.55813953 | E111: 0.096774194 | F111: No
A112: 10 | B112: 11 | C112: -13 | D112: 0.45833333 | E112: 0.044354839 | F112: No
A113: 11 | B113: 5 | C113: -6 | D113: 0.45454545 | E113: 0.02016129 | F113: No
A114: 12 | B114: 7 | C114: 2 | D114: 1.4 | E114: 0.028225806 | F114: No
...

Sheet LTR Waterfall (New-Return)
A1: LTR Waterfall — New Student (T1→T3) vs Returning Student (T4→last term, anchored at T3)
A2: Same headcount curve as Method A / the Headcount Waterfall sheet, split at the exact boundary the LTR formula uses: New Student Retention runs Term 1 to Term 3. Returning Student Retention is re-based to the population at Term 3 (not Term 1) — and, per the Read Me correction, its floor test and credit-hour weighting now start counting AT Term 3 itself, not Term 4; see 'Above 20% Floor?' below, which now starts one column earlier.
A4: All 41 Graduate Programs — Combined
A5: Caveat: this combined curve pools relative terms across all 41 programs regardless of length or credit-hours-to-degree, so "relative term 5" blends a program built to finish in 30 credit hours with one built to take 60 -- they are at very different points in their own lifecycle at the same relative term. Treat this as a rough portfolio-wide shape only; the real, decision-grade signal is in the per-program curves below, not this aggregate.
B6: New Student (T1 → T3) | E6: Returning Student (T4 → T18 — population anchored at T3)
A8: Relative Term | B8: 1 | C8: 2 | D8: 3 | E8: 4 | F8: 5 | G8: 6 | H8: 7 | I8: 8 | J8: 9 | K8: 10 | L8: 11 | M8: 12 | N8: 13 | O8: 14 | P8: 15 | Q8: 16 | R8: 17 | S8: 18
A9: Headcount (N) | B9: 5841 | C9: 4638 | D9: 4092 | E9: 4022 | F9: 2755 | G9: 1774 | H9: 1355 | I9: 822 | J9: 463 | K9: 262 | L9: 140 | M9: 75 | N9: 51 | O9: 25 | P9: 18 | Q9: 12 | R9: 6 | S9: 3
A10: % of Segment Base (T1 for New, T3 for Returning) | B10: 1 | C10: 0.79404212 | D10: 0.70056497 | E10: 0.98289345 | F10: 0.67326491 | G10: 0.43352884 | H10: 0.33113392 | I10: 0.20087977 | J10: 0.11314761 | K10: 0.06402737 | L10: 0.034213099 | M10: 0.018328446 | N10: 0.012463343 | O10: 0.0061094819 | P10: 0.004398827 | Q10: 0.0029325513 | R10: 0.0014662757 | S10: 0.00073313783
A11: New Student Retention (T3÷T1) | B11: 0.70056497
A12: Returning Student Retention (credit-hour weighted) | B12: n/a — aggregate; credit hours to degree differ by program
A13: LTR Factor (New × Returning) | B13: n/a — aggregate
A15: 1550C — Certificate in Population Health | Historical quadrant: Not screened (below viability threshold)
A16: No mature-cohort data available for this program in the current pull.
A18: D318 — Ed.D. in Education Administration | Historical quadrant: Not screened (below viability threshold)
A19: No mature-cohort data available for this program in the current pull.
A21: M366 — Executive MBA in Energy | Historical quadrant: Healthy
B22: New Student (T1 → T3) | E22: Returning Student (T4 → T11 — population anchored at T3)
A24: Relative Term | B24: 1 | C24: 2 | D24: 3 | E24: 4 | F24: 5 | G24: 6 | H24: 7 | I24: 8 | J24: 9 | K24: 10 | L24: 11
A25: Headcount (N) | B25: 112 | C25: 112 | D25: 109 | E25: 108 | F25: 80 | G25: 5 | H25: 2 | I25: 0 | J25: 1 | K25: 1 | L25: 1
A26: % of Segment Base (T1 for New, T3 for Returning) | B26: 1 | C26: 1 | D26: 0.97321429 | E26: 0.99082569 | F26: 0.73394495 | G26: 0.04587156 | H26: 0.018348624 | I26: 0 | J26: 0.0091743119 | K26: 0.0091743119 | L26: 0.0091743119
A27: Above 20% Floor? (Returning basis, starts at T3) | D27: Yes | E27: Yes | F27: Yes | G27: No | H27: No | I27: No | J27: No | K27: No | L27: No
A28: New Student Retention (T3÷T1) | B28: 0.97321429
A29: Returning Student Retention (credit-hour weighted) | B29: 0.90943653
A30: LTR Factor (New × Returning) | B30: 0.88507662
A32: 1231EX — Executive Masters in Health Administration | Historical quadrant: Not screened (below viability threshold)
A33: No mature-cohort data available for this program in the current pull.
A35: M013 — Master of Accountancy | Historical quadrant: Double Risk
B36: New Student (T1 → T3) | E36: Returning Student (T4 → T16 — population anchored at T3)
A38: Relative Term | B38: 1 | C38: 2 | D38: 3 | E38: 4 | F38: 5 | G38: 6 | H38: 7 | I38: 8 | J38: 9 | K38: 10 | L38: 11 | M38: 12 | N38: 13 | O38: 14 | P38: 15 | Q38: 16
A39: Headcount (N) | B39: 272 | C39: 215 | D39: 188 | E39: 160 | F39: 120 | G39: 95 | H39: 65 | I39: 46 | J39: 27 | K39: 24 | L39: 11 | M39: 6 | N39: 6 | O39: 2 | P39: 0 | Q39: 1
A40: % of Segment Base (T1 for New, T3 for Returning) | B40: 1 | C40: 0.79044118 | D40: 0.69117647 | E40: 0.85106383 | F40: 0.63829787 | G40: 0.50531915 | H40: 0.34574468 | I40: 0.24468085 | J40: 0.14361702 | K40: 0.12765957 | L40: 0.058510638 | M40: 0.031914894 | N40: 0.031914894 | O40: 0.010638298 | P40: 0 | Q40: 0.0053191489
A41: Above 20% Floor? (Returning basis, starts at T3) | D41: Yes | E41: Yes | F41: Yes | G41: Yes | H41: Yes | I41: Yes | J41: No | K41: No | L41: No | M41: No | N41: No | O41: No | P41: No | Q41: No
A42: New Student Retention (T3÷T1) | B42: 0.69117647
A43: Returning Student Retention (credit-hour weighted) | B43: 0.62397934
A44: LTR Factor (New × Returning) | B44: 0.43127984
A46: M075 — Master of Arts in Art and Technology | Historical quadrant: Double Risk
B47: New Student (T1 → T3) | E47: Returning Student (T4 → T13 — population anchored at T3)
A49: Relative Term | B49: 1 | C49: 2 | D49: 3 | E49: 4 | F49: 5 | G49: 6 | H49: 7 | I49: 8 | J49: 9 | K49: 10 | L49: 11 | M49: 12 | N49: 13
A50: Headcount (N) | B50: 146 | C50: 118 | D50: 101 | E50: 97 | F50: 87 | G50: 9 | H50: 7 | I50: 2 | J50: 4 | K50: 3 | L50: 2 | M50: 1 | N50: 1
A51: % of Segment Base (T1 for New, T3 for Returning) | B51: 1 | C51: 0.80821918 | D51: 0.69178082 | E51: 0.96039604 | F51: 0.86138614 | G51: 0.089108911 | H51: 0.069306931 | I51: 0.01980198 | J51: 0.03960396 | K51: 0.02970297 | L51: 0.01980198 | M51: 0.0099009901 | N51: 0.0099009901
A52: Above 20% Floor? (Returning basis, starts at T3) | D52: Yes | E52: Yes | F52: Yes | G52: No | H52: No | I52: No | J52: No | K52: No | L52: No | M52: No | N52: No
A53: New Student Retention (T3÷T1) | B53: 0.69178082
A54: Returning Student Retention (credit-hour weighted) | B54: 0.94529815
A55: LTR Factor (New × Returning) | B55: 0.65393913
A57: M073 — Master of Arts in Arts Management | Historical quadrant: Not screened (below viability threshold)
B58: New Student (T1 → T3) | E58: Returning Student (T4 → T9 — population anchored at T3)
A60: Relative Term | B60: 1 | C60: 2 | D60: 3 | E60: 4 | F60: 5 | G60: 6 | H60: 7 | I60: 8 | J60: 9
A61: Headcount (N) | B61: 80 | C61: 68 | D61: 62 | E61: 61 | F61: 12 | G61: 7 | H61: 7 | I61: 0 | J61: 2
A62: % of Segment Base (T1 for New, T3 for Returning) | B62: 1 | C62: 0.85 | D62: 0.775 | E62: 0.98387097 | F62: 0.19354839 | G62: 0.11290323 | H62: 0.11290323 | I62: 0 | J62: 0.032258065
A63: Above 20% Floor? (Returning basis, starts at T3) | D63: Yes | E63: Yes | F63: No | G63: No | H63: No | I63: No | J63: No
A64: New Student Retention (T3÷T1) | B64: 0.775
A65: Returning Student Retention (credit-hour weighted) | B65: 0.99285285
A66: LTR Factor (New × Returning) | B66: 0.76946096
A68: M494 — Master of Arts in Global Affairs | Historical quadrant: Double Risk
B69: New Student (T1 → T3) | E69: Returning Student (T4 → T17 — population anchored at T3)
A71: Relative Term | B71: 1 | C71: 2 | D71: 3 | E71: 4 | F71: 5 | G71: 6 | H71: 7 | I71: 8 | J71: 9 | K71: 10 | L71: 11 | M71: 12 | N71: 13 | O71: 14 | P71: 15 | Q71: 16 | R71: 17
A72: Headcount (N) | B72: 248 | C72: 167 | D72: 132 | E72: 154 | F72: 133 | G72: 111 | H72: 74 | I72: 43 | J72: 24 | K72: 11 | L72: 5 | M72: 7 | N72: 4 | O72: 3 | P72: 2 | Q72: 1 | R72: 1
A73: % of Segment Base (T1 for New, T3 for Returning) | B73: 1 | C73: 0.6733871 | D73: 0.53225806 | E73: 1.1666667 | F73: 1.0075758 | G73: 0.84090909 | H73: 0.56060606 | I73: 0.32575758 | J73: 0.18181818 | K73: 0.083333333 | L73: 0.037878788 | M73: 0.053030303 | N73: 0.03030303 | O73: 0.022727273 | P73: 0.015151515 | Q73: 0.0075757576 | R73: 0.0075757576
A74: Above 20% Floor? (Returning basis, starts at T3) | D74: Yes | E74: Yes | F74: Yes | G74: Yes | H74: Yes | I74: Yes | J74: No | K74: No | L74: No | M74: No | N74: No | O74: No | P74: No | Q74: No | R74: No
A75: New Student Retention (T3÷T1) | B75: 0.53225806
A76: Returning Student Retention (credit-hour weighted) | B76: 0.8362711
A77: LTR Factor (New × Returning) | B77: 0.44511204
A79: M700 — Master of Arts in Museum Studies | Historical quadrant: Double Risk
B80: New Student (T1 → T3) | E80: Returning Student (T4 → T15 — population anchored at T3)
A82: Relative Term | B82: 1 | C82: 2 | D82: 3 | E82: 4 | F82: 5 | G82: 6 | H82: 7 | I82: 8 | J82: 9 | K82: 10 | L82: 11 | M82: 12 | N82: 13 | O82: 14 | P82: 15
A83: Headcount (N) | B83: 474 | C83: 366 | D83: 310 | E83: 311 | F83: 276 | G83: 235 | H83: 105 | I83: 67 | J83: 32 | K83: 21 | L83: 15 | M83: 6 | N83: 6 | O83: 2 | P83: 1
A84: % of Segment Base (T1 for New, T3 for Returning) | B84: 1 | C84: 0.7721519 | D84: 0.65400844 | E84: 1.0032258 | F84: 0.89032258 | G84: 0.75806452 | H84: 0.33870968 | I84: 0.21612903 | J84: 0.10322581 | K84: 0.067741935 | L84: 0.048387097 | M84: 0.019354839 | N84: 0.019354839 | O84: 0.0064516129 | P84: 0.0032258065
A85: Above 20% Floor? (Returning basis, starts at T3) | D85: Yes | E85: Yes | F85: Yes | G85: Yes | H85: Yes | I85: Yes | J85: No | K85: No | L85: No | M85: No | N85: No | O85: No | P85: No
A86: New Student Retention (T3÷T1) | B86: 0.65400844
A87: Returning Student Retention (credit-hour weighted) | B87: 0.73874322
A88: LTR Factor (New × Returning) | B88: 0.4831443
A90: M762 — Master of Arts in Organizational Leadership | Historical quadrant: Double Risk
B91: New Student (T1 → T3) | E91: Returning Student (T4 → T17 — population anchored at T3)
A93: Relative Term | B93: 1 | C93: 2 | D93: 3 | E93: 4 | F93: 5 | G93: 6 | H93: 7 | I93: 8 | J93: 9 | K93: 10 | L93: 11 | M93: 12 | N93: 13 | O93: 14 | P93: 15 | Q93: 16 | R93: 17
A94: Headcount (N) | B94: 505 | C94: 346 | D94: 288 | E94: 277 | F94: 245 | G94: 171 | H94: 114 | I94: 64 | J94: 48 | K94: 33 | L94: 18 | M94: 11 | N94: 8 | O94: 5 | P94: 6 | Q94: 4 | R94: 1
A95: % of Segment Base (T1 for New, T3 for Returning) | B95: 1 | C95: 0.68514851 | D95: 0.57029703 | E95: 0.96180556 | F95: 0.85069444 | G95: 0.59375 | H95: 0.39583333 | I95: 0.22222222 | J95: 0.16666667 | K95: 0.11458333 | L95: 0.0625 | M95: 0.038194444 | N95: 0.027777778 | O95: 0.017361111 | P95: 0.020833333 | Q95: 0.013888889 | R95: 0.0034722222
A96: Above 20% Floor? (Returning basis, starts at T3) | D96: Yes | E96: Yes | F96: Yes | G96: Yes | H96: Yes | I96: Yes | J96: No | K96: No | L96: No | M96: No | N96: No | O96: No | P96: No | Q96: No | R96: No
A97: New Student Retention (T3÷T1) | B97: 0.57029703
A98: Returning Student Retention (credit-hour weighted) | B98: 0.6925737
A99: LTR Factor (New × Returning) | B99: 0.39497272
A101: M859 — Master of Arts in Strategic Communication and Digital Strategy | Historical quadrant: Healthy
B102: New Student (T1 → T3) | E102: Returning Student (T4 → T16 — population anchored at T3)
A104: Relative Term | B104: 1 | C104: 2 | D104: 3 | E104: 4 | F104: 5 | G104: 6 | H104: 7 | I104: 8 | J104: 9 | K104: 10 | L104: 11 | M104: 12 | N104: 13 | O104: 14 | P104: 15 | Q104: 16
A105: Headcount (N) | B105: 256 | C105: 218 | D105: 208 | E105: 207 | F105: 204 | G105: 35 | H105: 16 | I105: 16 | J105: 11 | K105: 6 | L105: 3 | M105: 2 | N105: 3 | O105: 3 | P105: 1 | Q105: 1
A106: % of Segment Base (T1 for New, T3 for Returning) | B106: 1 | C106: 0.8515625 | D106: 0.8125 | E106: 0.99519231 | F106: 0.98076923 | G106: 0.16826923 | H106: 0.076923077 | I106: 0.076923077 | J106: 0.052884615 | K106: 0.028846154 | L106: 0.014423077 | M106: 0.0096153846 | N106: 0.014423077 | O106: 0.014423077 | P106: 0.0048076923 | Q106: 0.0048076923
A107: Above 20% Floor? (Returning basis, starts at T3) | D107: Yes | E107: Yes | F107: Yes | G107: No | H107: No | I107: No | J107: No | K107: No | L107: No | M107: No | N107: No | O107: No | P107: No | Q107: No
A108: New Student Retention (T3÷T1) | B108: 0.8125
A109: Returning Student Retention (credit-hour weighted) | B109: 0.99214821
A110: LTR Factor (New × Returning) | B110: 0.80612042
A112: M202 — Master of Clinical Mental Health Counseling | Historical quadrant: Post-T3 Risk
B113: New Student (T1 → T3) | E113: Returning Student (T4 → T12 — population anchored at T3)
A115: Relative Term | B115: 1 | C115: 2 | D115: 3 | E115: 4 | F115: 5 | G115: 6 | H115: 7 | I115: 8 | J115: 9 | K115: 10 | L115: 11 | M115: 12
A116: Headcount (N) | B116: 240 | C116: 201 | D116: 189 | E116: 179 | F116: 175 | G116: 164 | H116: 158 | I116: 161 | J116: 35 | K116: 19 | L116: 7 | M116: 1
A117: % of Segment Base (T1 for New, T3 for Returning) | B117: 1 | C117: 0.8375 | D117: 0.7875 | E117: 0.94708995 | F117: 0.92592593 | G117: 0.86772487 | H117: 0.83597884 | I117: 0.85185185 | J117: 0.18518519 | K117: 0.1005291 | L117: 0.037037037 | M117: 0.0052910053
A118: Above 20% Floor? (Returning basis, starts at T3) | D118: Yes | E118: Yes | F118: Yes | G118: Yes | H118: Yes | I118: Yes | J118: No | K118: No | L118: No | M118: No
A119: New Student Retention (T3÷T1) | B119: 0.7875
A120: Returning Student Retention (credit-hour weighted) | B120: 0.90971437
A121: LTR Factor (New × Returning) | B121: 0.71640006
A123: M246 — Master of Construction Business | Historical quadrant: Healthy
B124: New Student (T1 → T3) | E124: Returning Student (T4 → T15 — population anchored at T3)
...

Sheet Term-to-Term Waterfall
A1: Term-to-Term Waterfall — New Student LTR Retention Lifecycle, T1 through the last term reached
A2: Same headcount curve as Method A / the Headcount Waterfall sheet, shown as one continuous lifecycle rather than split into New/Returning segments — each term's retention is measured against the term immediately before it (T2÷T1, T3÷T2, T4÷T3, etc.). Note: Method A's 20% floor test runs on a different ratio — the cumulative count vs. the Term-3 base, shown on the LTR Waterfall sheet — not on this term-over-term figure.
A4: All 41 Graduate Programs — Combined
A5: Caveat: this combined curve pools relative terms across all 41 programs regardless of length or credit-hours-to-degree, so "relative term 5" blends a program built to finish in 30 credit hours with one built to take 60 -- they are at very different points in their own lifecycle at the same relative term. Treat this as a rough portfolio-wide shape only; the real, decision-grade signal is in the per-program curves below, not this aggregate.
B6: Term to Term Retention by Program (T2÷T1, T3÷T2, T4÷T3, etc.)
A8: Relative Term | B8: 1 | C8: 2 | D8: 3 | E8: 4 | F8: 5 | G8: 6 | H8: 7 | I8: 8 | J8: 9 | K8: 10 | L8: 11 | M8: 12 | N8: 13 | O8: 14 | P8: 15 | Q8: 16 | R8: 17 | S8: 18
A9: Headcount (N) | B9: 5841 | C9: 4638 | D9: 4092 | E9: 4022 | F9: 2755 | G9: 1774 | H9: 1355 | I9: 822 | J9: 463 | K9: 262 | L9: 140 | M9: 75 | N9: 51 | O9: 25 | P9: 18 | Q9: 12 | R9: 6 | S9: 3
A10: Term-to-Term Retention | C10: 0.79404212 | D10: 0.88227684 | E10: 0.98289345 | F10: 0.6849826 | G10: 0.64392015 | H10: 0.7638106 | I10: 0.60664207 | J10: 0.56326034 | K10: 0.56587473 | L10: 0.53435115 | M10: 0.53571429 | N10: 0.68 | O10: 0.49019608 | P10: 0.72 | Q10: 0.66666667 | R10: 0.5 | S10: 0.5
A11: % of Term 1 Remaining | B11: 1 | C11: 0.79404212 | D11: 0.70056497 | E11: 0.68858072 | F11: 0.47166581 | G11: 0.30371512 | H11: 0.23198083 | I11: 0.14072933 | J11: 0.079267249 | K11: 0.044855333 | L11: 0.023968499 | M11: 0.012840267 | N11: 0.0087313816 | O11: 0.004280089 | P11: 0.0030816641 | Q11: 0.0020544427 | R11: 0.0010272214 | S11: 0.00051361068
A13: 1550C — Certificate in Population Health | Historical quadrant: Not screened (below viability threshold)
A14: No mature-cohort data available for this program in the current pull.
A16: D318 — Ed.D. in Education Administration | Historical quadrant: Not screened (below viability threshold)
A17: No mature-cohort data available for this program in the current pull.
A19: M366 — Executive MBA in Energy | Historical quadrant: Healthy
B20: Term to Term Retention by Program (T2÷T1, T3÷T2, T4÷T3, etc.)
A22: Relative Term | B22: 1 | C22: 2 | D22: 3 | E22: 4 | F22: 5 | G22: 6 | H22: 7 | I22: 8 | J22: 9 | K22: 10 | L22: 11
A23: Headcount (N) | B23: 112 | C23: 112 | D23: 109 | E23: 108 | F23: 80 | G23: 5 | H23: 2 | I23: 0 | J23: 1 | K23: 1 | L23: 1
A24: Term-to-Term Retention | C24: 1 | D24: 0.97321429 | E24: 0.99082569 | F24: 0.74074074 | G24: 0.0625 | H24: 0.4 | I24: 0 | K24: 1 | L24: 1
A25: % of Term 1 Remaining | B25: 1 | C25: 1 | D25: 0.97321429 | E25: 0.96428571 | F25: 0.71428571 | G25: 0.044642857 | H25: 0.017857143 | I25: 0 | J25: 0.0089285714 | K25: 0.0089285714 | L25: 0.0089285714
A27: 1231EX — Executive Masters in Health Administration | Historical quadrant: Not screened (below viability threshold)
A28: No mature-cohort data available for this program in the current pull.
A30: M013 — Master of Accountancy | Historical quadrant: Double Risk
B31: Term to Term Retention by Program (T2÷T1, T3÷T2, T4÷T3, etc.)
A33: Relative Term | B33: 1 | C33: 2 | D33: 3 | E33: 4 | F33: 5 | G33: 6 | H33: 7 | I33: 8 | J33: 9 | K33: 10 | L33: 11 | M33: 12 | N33: 13 | O33: 14 | P33: 15 | Q33: 16
A34: Headcount (N) | B34: 272 | C34: 215 | D34: 188 | E34: 160 | F34: 120 | G34: 95 | H34: 65 | I34: 46 | J34: 27 | K34: 24 | L34: 11 | M34: 6 | N34: 6 | O34: 2 | P34: 0 | Q34: 1
A35: Term-to-Term Retention | C35: 0.79044118 | D35: 0.8744186 | E35: 0.85106383 | F35: 0.75 | G35: 0.79166667 | H35: 0.68421053 | I35: 0.70769231 | J35: 0.58695652 | K35: 0.88888889 | L35: 0.45833333 | M35: 0.54545455 | N35: 1 | O35: 0.33333333 | P35: 0
A36: % of Term 1 Remaining | B36: 1 | C36: 0.79044118 | D36: 0.69117647 | E36: 0.58823529 | F36: 0.44117647 | G36: 0.34926471 | H36: 0.23897059 | I36: 0.16911765 | J36: 0.099264706 | K36: 0.088235294 | L36: 0.040441176 | M36: 0.022058824 | N36: 0.022058824 | O36: 0.0073529412 | P36: 0 | Q36: 0.0036764706
A38: M075 — Master of Arts in Art and Technology | Historical quadrant: Double Risk
B39: Term to Term Retention by Program (T2÷T1, T3÷T2, T4÷T3, etc.)
A41: Relative Term | B41: 1 | C41: 2 | D41: 3 | E41: 4 | F41: 5 | G41: 6 | H41: 7 | I41: 8 | J41: 9 | K41: 10 | L41: 11 | M41: 12 | N41: 13
A42: Headcount (N) | B42: 146 | C42: 118 | D42: 101 | E42: 97 | F42: 87 | G42: 9 | H42: 7 | I42: 2 | J42: 4 | K42: 3 | L42: 2 | M42: 1 | N42: 1
A43: Term-to-Term Retention | C43: 0.80821918 | D43: 0.8559322 | E43: 0.96039604 | F43: 0.89690722 | G43: 0.10344828 | H43: 0.77777778 | I43: 0.28571429 | J43: 2 | K43: 0.75 | L43: 0.66666667 | M43: 0.5 | N43: 1
A44: % of Term 1 Remaining | B44: 1 | C44: 0.80821918 | D44: 0.69178082 | E44: 0.66438356 | F44: 0.59589041 | G44: 0.061643836 | H44: 0.047945205 | I44: 0.01369863 | J44: 0.02739726 | K44: 0.020547945 | L44: 0.01369863 | M44: 0.0068493151 | N44: 0.0068493151
A46: M073 — Master of Arts in Arts Management | Historical quadrant: Not screened (below viability threshold)
B47: Term to Term Retention by Program (T2÷T1, T3÷T2, T4÷T3, etc.)
A49: Relative Term | B49: 1 | C49: 2 | D49: 3 | E49: 4 | F49: 5 | G49: 6 | H49: 7 | I49: 8 | J49: 9
A50: Headcount (N) | B50: 80 | C50: 68 | D50: 62 | E50: 61 | F50: 12 | G50: 7 | H50: 7 | I50: 0 | J50: 2
A51: Term-to-Term Retention | C51: 0.85 | D51: 0.91176471 | E51: 0.98387097 | F51: 0.19672131 | G51: 0.58333333 | H51: 1 | I51: 0
A52: % of Term 1 Remaining | B52: 1 | C52: 0.85 | D52: 0.775 | E52: 0.7625 | F52: 0.15 | G52: 0.0875 | H52: 0.0875 | I52: 0 | J52: 0.025
A54: M494 — Master of Arts in Global Affairs | Historical quadrant: Double Risk
B55: Term to Term Retention by Program (T2÷T1, T3÷T2, T4÷T3, etc.)
A57: Relative Term | B57: 1 | C57: 2 | D57: 3 | E57: 4 | F57: 5 | G57: 6 | H57: 7 | I57: 8 | J57: 9 | K57: 10 | L57: 11 | M57: 12 | N57: 13 | O57: 14 | P57: 15 | Q57: 16 | R57: 17
A58: Headcount (N) | B58: 248 | C58: 167 | D58: 132 | E58: 154 | F58: 133 | G58: 111 | H58: 74 | I58: 43 | J58: 24 | K58: 11 | L58: 5 | M58: 7 | N58: 4 | O58: 3 | P58: 2 | Q58: 1 | R58: 1
A59: Term-to-Term Retention | C59: 0.6733871 | D59: 0.79041916 | E59: 1.1666667 | F59: 0.86363636 | G59: 0.83458647 | H59: 0.66666667 | I59: 0.58108108 | J59: 0.55813953 | K59: 0.45833333 | L59: 0.45454545 | M59: 1.4 | N59: 0.57142857 | O59: 0.75 | P59: 0.66666667 | Q59: 0.5 | R59: 1
A60: % of Term 1 Remaining | B60: 1 | C60: 0.6733871 | D60: 0.53225806 | E60: 0.62096774 | F60: 0.53629032 | G60: 0.44758065 | H60: 0.2983871 | I60: 0.1733871 | J60: 0.096774194 | K60: 0.044354839 | L60: 0.02016129 | M60: 0.028225806 | N60: 0.016129032 | O60: 0.012096774 | P60: 0.0080645161 | Q60: 0.0040322581 | R60: 0.0040322581
A62: M700 — Master of Arts in Museum Studies | Historical quadrant: Double Risk
B63: Term to Term Retention by Program (T2÷T1, T3÷T2, T4÷T3, etc.)
A65: Relative Term | B65: 1 | C65: 2 | D65: 3 | E65: 4 | F65: 5 | G65: 6 | H65: 7 | I65: 8 | J65: 9 | K65: 10 | L65: 11 | M65: 12 | N65: 13 | O65: 14 | P65: 15
A66: Headcount (N) | B66: 474 | C66: 366 | D66: 310 | E66: 311 | F66: 276 | G66: 235 | H66: 105 | I66: 67 | J66: 32 | K66: 21 | L66: 15 | M66: 6 | N66: 6 | O66: 2 | P66: 1
A67: Term-to-Term Retention | C67: 0.7721519 | D67: 0.84699454 | E67: 1.0032258 | F67: 0.88745981 | G67: 0.85144928 | H67: 0.44680851 | I67: 0.63809524 | J67: 0.47761194 | K67: 0.65625 | L67: 0.71428571 | M67: 0.4 | N67: 1 | O67: 0.33333333 | P67: 0.5
A68: % of Term 1 Remaining | B68: 1 | C68: 0.7721519 | D68: 0.65400844 | E68: 0.65611814 | F68: 0.58227848 | G68: 0.49578059 | H68: 0.22151899 | I68: 0.14135021 | J68: 0.067510549 | K68: 0.044303797 | L68: 0.03164557 | M68: 0.012658228 | N68: 0.012658228 | O68: 0.0042194093 | P68: 0.0021097046
A70: M762 — Master of Arts in Organizational Leadership | Historical quadrant: Double Risk
B71: Term to Term Retention by Program (T2÷T1, T3÷T2, T4÷T3, etc.)
A73: Relative Term | B73: 1 | C73: 2 | D73: 3 | E73: 4 | F73: 5 | G73: 6 | H73: 7 | I73: 8 | J73: 9 | K73: 10 | L73: 11 | M73: 12 | N73: 13 | O73: 14 | P73: 15 | Q73: 16 | R73: 17
A74: Headcount (N) | B74: 505 | C74: 346 | D74: 288 | E74: 277 | F74: 245 | G74: 171 | H74: 114 | I74: 64 | J74: 48 | K74: 33 | L74: 18 | M74: 11 | N74: 8 | O74: 5 | P74: 6 | Q74: 4 | R74: 1
A75: Term-to-Term Retention | C75: 0.68514851 | D75: 0.83236994 | E75: 0.96180556 | F75: 0.88447653 | G75: 0.69795918 | H75: 0.66666667 | I75: 0.56140351 | J75: 0.75 | K75: 0.6875 | L75: 0.54545455 | M75: 0.61111111 | N75: 0.72727273 | O75: 0.625 | P75: 1.2 | Q75: 0.66666667 | R75: 0.25
A76: % of Term 1 Remaining | B76: 1 | C76: 0.68514851 | D76: 0.57029703 | E76: 0.54851485 | F76: 0.48514851 | G76: 0.33861386 | H76: 0.22574257 | I76: 0.12673267 | J76: 0.095049505 | K76: 0.065346535 | L76: 0.035643564 | M76: 0.021782178 | N76: 0.015841584 | O76: 0.0099009901 | P76: 0.011881188 | Q76: 0.0079207921 | R76: 0.001980198
A78: M859 — Master of Arts in Strategic Communication and Digital Strategy | Historical quadrant: Healthy
B79: Term to Term Retention by Program (T2÷T1, T3÷T2, T4÷T3, etc.)
A81: Relative Term | B81: 1 | C81: 2 | D81: 3 | E81: 4 | F81: 5 | G81: 6 | H81: 7 | I81: 8 | J81: 9 | K81: 10 | L81: 11 | M81: 12 | N81: 13 | O81: 14 | P81: 15 | Q81: 16
A82: Headcount (N) | B82: 256 | C82: 218 | D82: 208 | E82: 207 | F82: 204 | G82: 35 | H82: 16 | I82: 16 | J82: 11 | K82: 6 | L82: 3 | M82: 2 | N82: 3 | O82: 3 | P82: 1 | Q82: 1
A83: Term-to-Term Retention | C83: 0.8515625 | D83: 0.95412844 | E83: 0.99519231 | F83: 0.98550725 | G83: 0.17156863 | H83: 0.45714286 | I83: 1 | J83: 0.6875 | K83: 0.54545455 | L83: 0.5 | M83: 0.66666667 | N83: 1.5 | O83: 1 | P83: 0.33333333 | Q83: 1
A84: % of Term 1 Remaining | B84: 1 | C84: 0.8515625 | D84: 0.8125 | E84: 0.80859375 | F84: 0.796875 | G84: 0.13671875 | H84: 0.0625 | I84: 0.0625 | J84: 0.04296875 | K84: 0.0234375 | L84: 0.01171875 | M84: 0.0078125 | N84: 0.01171875 | O84: 0.01171875 | P84: 0.00390625 | Q84: 0.00390625
A86: M202 — Master of Clinical Mental Health Counseling | Historical quadrant: Post-T3 Risk
B87: Term to Term Retention by Program (T2÷T1, T3÷T2, T4÷T3, etc.)
A89: Relative Term | B89: 1 | C89: 2 | D89: 3 | E89: 4 | F89: 5 | G89: 6 | H89: 7 | I89: 8 | J89: 9 | K89: 10 | L89: 11 | M89: 12
A90: Headcount (N) | B90: 240 | C90: 201 | D90: 189 | E90: 179 | F90: 175 | G90: 164 | H90: 158 | I90: 161 | J90: 35 | K90: 19 | L90: 7 | M90: 1
A91: Term-to-Term Retention | C91: 0.8375 | D91: 0.94029851 | E91: 0.94708995 | F91: 0.97765363 | G91: 0.93714286 | H91: 0.96341463 | I91: 1.0189873 | J91: 0.2173913 | K91: 0.54285714 | L91: 0.36842105 | M91: 0.14285714
A92: % of Term 1 Remaining | B92: 1 | C92: 0.8375 | D92: 0.7875 | E92: 0.74583333 | F92: 0.72916667 | G92: 0.68333333 | H92: 0.65833333 | I92: 0.67083333 | J92: 0.14583333 | K92: 0.079166667 | L92: 0.029166667 | M92: 0.0041666667
A94: M246 — Master of Construction Business | Historical quadrant: Healthy
B95: Term to Term Retention by Program (T2÷T1, T3÷T2, T4÷T3, etc.)
A97: Relative Term | B97: 1 | C97: 2 | D97: 3 | E97: 4 | F97: 5 | G97: 6 | H97: 7 | I97: 8 | J97: 9 | K97: 10 | L97: 11 | M97: 12 | N97: 13 | O97: 14 | P97: 15
A98: Headcount (N) | B98: 115 | C98: 102 | D98: 100 | E98: 95 | F98: 33 | G98: 22 | H98: 17 | I98: 2 | J98: 2 | K98: 1 | L98: 0 | M98: 1 | N98: 2 | O98: 1 | P98: 1
A99: Term-to-Term Retention | C99: 0.88695652 | D99: 0.98039216 | E99: 0.95 | F99: 0.34736842 | G99: 0.66666667 | H99: 0.77272727 | I99: 0.11764706 | J99: 1 | K99: 0.5 | L99: 0 | N99: 2 | O99: 0.5 | P99: 1
A100: % of Term 1 Remaining | B100: 1 | C100: 0.88695652 | D100: 0.86956522 | E100: 0.82608696 | F100: 0.28695652 | G100: 0.19130435 | H100: 0.14782609 | I100: 0.017391304 | J100: 0.017391304 | K100: 0.0086956522 | L100: 0 | M100: 0.0086956522 | N100: 0.017391304 | O100: 0.0086956522 | P100: 0.0086956522
A102: M297 — Master of Econometrics | Historical quadrant: Not screened (below viability threshold)
A103: No mature-cohort data available for this program in the current pull.
A105: M383 — Master of Entrepreneurship & Innovation | Historical quadrant: Not screened (below viability threshold)
A106: No mature-cohort data available for this program in the current pull.
A108: M518 — Master of Environmental Science: Hydrology and Water Security | Historical quadrant: Healthy
B109: Term to Term Retention by Program (T2÷T1, T3÷T2, T4÷T3, etc.)
A111: Relative Term | B111: 1 | C111: 2 | D111: 3 | E111: 4 | F111: 5 | G111: 6 | H111: 7 | I111: 8 | J111: 9 | K111: 10 | L111: 11 | M111: 12 | N111: 13 | O111: 14 | P111: 15 | Q111: 16
A112: Headcount (N) | B112: 254 | C112: 201 | D112: 184 | E112: 181 | F112: 183 | G112: 48 | H112: 41 | I112: 31 | J112: 12 | K112: 11 | L112: 9 | M112: 2 | N112: 1 | O112: 1 | P112: 0 | Q112: 1
A113: Term-to-Term Retention | C113: 0.79133858 | D113: 0.91542289 | E113: 0.98369565 | F113: 1.0110497 | G113: 0.26229508 | H113: 0.85416667 | I113: 0.75609756 | J113: 0.38709677 | K113: 0.91666667 | L113: 0.81818182 | M113: 0.22222222 | N113: 0.5 | O113: 1 | P113: 0
A114: % of Term 1 Remaining | B114: 1 | C114: 0.79133858 | D114: 0.72440945 | E114: 0.71259843 | F114: 0.72047244 | G114: 0.18897638 | H114: 0.16141732 | I114: 0.12204724 | J114: 0.047244094 | K114: 0.043307087 | L114: 0.035433071 | M114: 0.0078740157 | N114: 0.0039370079 | O114: 0.0039370079 | P114: 0 | Q114: 0.0039370079
A116: M368 — Master of Legal Studies - Energy | Historical quadrant: Early Risk
B117: Term to Term Retention by Program (T2÷T1, T3÷T2, T4÷T3, etc.)
A119: Relative Term | B119: 1 | C119: 2 | D119: 3 | E119: 4 | F119: 5 | G119: 6 | H119: 7 | I119: 8 | J119: 9 | K119: 10 | L119: 11 | M119: 12 | N119: 13
A120: Headcount (N) | B120: 82 | C120: 63 | D120: 58 | E120: 56 | F120: 4 | G120: 6 | H120: 6 | I120: 3 | J120: 3 | K120: 1 | L120: 2 | M120: 1 | N120: 1
A121: Term-to-Term Retention | C121: 0.76829268 | D121: 0.92063492 | E121: 0.96551724 | F121: 0.071428571 | G121: 1.5 | H121: 1 | I121: 0.5 | J121: 1 | K121: 0.33333333 | L121: 2 | M121: 0.5 | N121: 1
A122: % of Term 1 Remaining | B122: 1 | C122: 0.76829268 | D122: 0.70731707 | E122: 0.68292683 | F122: 0.048780488 | G122: 0.073170732 | H122: 0.073170732 | I122: 0.036585366 | J122: 0.036585366 | K122: 0.012195122 | L122: 0.024390244 | M122: 0.012195122 | N122: 0.012195122
A124: M636 — Master of Legal Studies - General | Historical quadrant: Not screened (below viability threshold)
A125: No mature-cohort data available for this program in the current pull.
A127: M503 — Master of Legal Studies - Healthcare Law | Historical quadrant: Healthy
B128: Term to Term Retention by Program (T2÷T1, T3÷T2, T4÷T3, etc.)
A130: Relative Term | B130: 1 | C130: 2 | D130: 3 | E130: 4 | F130: 5 | G130: 6 | H130: 7 | I130: 8 | J130: 9 | K130: 10 | L130: 11 | M130: 12 | N130: 13
A131: Headcount (N) | B131: 428 | C131: 351 | D131: 314 | E131: 319 | F131: 74 | G131: 32 | H131: 21 | I131: 16 | J131: 7 | K131: 6 | L131: 2 | M131: 1 | N131: 1
A132: Term-to-Term Retention | C132: 0.82009346 | D132: 0.89458689 | E132: 1.0159236 | F132: 0.23197492 | G132: 0.43243243 | H132: 0.65625 | I132: 0.76190476 | J132: 0.4375 | K132: 0.85714286 | L132: 0.33333333 | M132: 0.5 | N132: 1
A133: % of Term 1 Remaining | B133: 1 | C133: 0.82009346 | D133: 0.73364486 | E133: 0.7453271 | F133: 0.1728972 | G133: 0.074766355 | H133: 0.049065421 | I133: 0.037383178 | J133: 0.01635514 | K133: 0.014018692 | L133: 0.0046728972 | M133: 0.0023364486 | N133: 0.0023364486
A135: M522 — Master of Legal Studies - Indigenous Peoples Law | Historical quadrant: Healthy
...

Sheet Program LTR Retention
A1: Program LTR Retention — cohort vintage triangle, observed data only (201930–202530)
A2: Same layout as the example you shared: calendar terms across the columns, one row per entering cohort starting on its own diagonal. Every cell here is a real observed count, reconstructed from that cohort's own survival curve on Method B - Detail — nothing projected, nothing assumed.
A4: 1550C — Certificate in Population Health | Historical quadrant: Not screened (below viability threshold)
A5: No mature-cohort data available for this program in the current pull.
A7: D318 — Ed.D. in Education Administration | Historical quadrant: Not screened (below viability threshold)
A8: No mature-cohort data available for this program in the current pull.
A10: M366 — Executive MBA in Energy | Historical quadrant: Healthy
A11: Vintage ↓ / Calendar Term → | B11: 201930 | C11: 202010 | D11: 202020 | E11: 202030 | F11: 202110 | G11: 202120 | H11: 202130 | I11: 202210 | J11: 202220 | K11: 202230 | L11: 202310 | M11: 202320 | N11: 202330 | O11: 202410 | P11: 202420 | Q11: 202430 | R11: 202510 | S11: 202520 | T11: 202530 | U11: 202610
A12: 202010 | C12: 17 | D12: 17 | E12: 17 | F12: 17 | G12: 0 | H12: 1 | I12: 0 | J12: 0 | K12: 0 | L12: 0 | M12: 0 | N12: 0 | O12: 0 | P12: 0 | Q12: 0 | R12: 0 | S12: 0 | T12: 0 | U12: 0
A13: 202020 | D13: 10 | E13: 10 | F13: 10 | G13: 10 | H13: 0 | I13: 0 | J13: 0 | K13: 0 | L13: 0 | M13: 0 | N13: 0 | O13: 0 | P13: 0 | Q13: 0 | R13: 0 | S13: 0 | T13: 0 | U13: 0
A14: 202030 | E14: 11 | F14: 11 | G14: 10 | H14: 10 | I14: 9 | J14: 0 | K14: 1 | L14: 0 | M14: 0 | N14: 0 | O14: 0 | P14: 0 | Q14: 0 | R14: 0 | S14: 0 | T14: 0 | U14: 0
A15: 202110 | F15: 9 | G15: 9 | H15: 8 | I15: 8 | J15: 8 | K15: 0 | L15: 0 | M15: 0 | N15: 0 | O15: 0 | P15: 0 | Q15: 0 | R15: 0 | S15: 0 | T15: 0 | U15: 0
A16: 202130 | H16: 20 | I16: 20 | J16: 20 | K16: 19 | L16: 19 | M16: 0 | N16: 0 | O16: 0 | P16: 0 | Q16: 0 | R16: 0 | S16: 0 | T16: 0 | U16: 0
A17: 202210 | I17: 18 | J17: 18 | K17: 17 | L17: 17 | M17: 17 | N17: 1 | O17: 1 | P17: 0 | Q17: 1 | R17: 1 | S17: 1 | T17: 0 | U17: 0
A18: 202230 | K18: 12 | L18: 12 | M18: 12 | N18: 12 | O18: 12 | P18: 1 | Q18: 0 | R18: 0 | S18: 0 | T18: 0 | U18: 0
A19: 202310 | L19: 15 | M19: 15 | N19: 15 | O19: 15 | P19: 15 | Q19: 2 | R19: 0 | S19: 0 | T19: 0 | U19: 0
A20: 202330 | N20: 12 | O20: 12 | P20: 12 | Q20: 12 | R20: 12 | S20: 1 | T20: 0 | U20: 0
A21: 202410 | O21: 12 | P21: 11 | Q21: 11 | R21: 11 | S21: 11 | T21: 0 | U21: 0
A22: 202430 | Q22: 6 | R22: 6 | S22: 6 | T22: 6 | U22: 6
A23: 202510 | R23: 9 | S23: 9 | T23: 8 | U23: 9
A24: 202520 | S24: 1 | T24: 1 | U24: 1
A25: 202530 | T25: 5 | U25: 5
A26: Total Enrolled (all cohorts) | C26: 17 | D26: 27 | E26: 38 | F26: 47 | G26: 29 | H26: 39 | I26: 55 | J26: 46 | K26: 49 | L26: 63 | M26: 44 | N26: 40 | O26: 52 | P26: 39 | Q26: 32 | R26: 39 | S26: 29 | T26: 20 | U26: 21
A28: 1231EX — Executive Masters in Health Administration | Historical quadrant: Not screened (below viability threshold)
A29: No mature-cohort data available for this program in the current pull.
A31: M013 — Master of Accountancy | Historical quadrant: Double Risk
A32: Vintage ↓ / Calendar Term → | B32: 201930 | C32: 202010 | D32: 202020 | E32: 202030 | F32: 202110 | G32: 202120 | H32: 202130 | I32: 202210 | J32: 202220 | K32: 202230 | L32: 202310 | M32: 202320 | N32: 202330 | O32: 202410 | P32: 202420 | Q32: 202430 | R32: 202510 | S32: 202520 | T32: 202530 | U32: 202610
A33: 201930 | B33: 8 | C33: 7 | D33: 6 | E33: 1 | F33: 3 | G33: 2 | H33: 0 | I33: 1 | J33: 0 | K33: 0 | L33: 0 | M33: 0 | N33: 0 | O33: 0 | P33: 0 | Q33: 0 | R33: 0 | S33: 0 | T33: 0 | U33: 0
A34: 202010 | C34: 31 | D34: 27 | E34: 22 | F34: 20 | G34: 18 | H34: 10 | I34: 9 | J34: 8 | K34: 3 | L34: 4 | M34: 2 | N34: 1 | O34: 2 | P34: 1 | Q34: 0 | R34: 0 | S34: 0 | T34: 0 | U34: 0
A35: 202020 | D35: 41 | E35: 31 | F35: 30 | G35: 29 | H35: 12 | I35: 17 | J35: 11 | K35: 5 | L35: 6 | M35: 5 | N35: 1 | O35: 1 | P35: 1 | Q35: 0 | R35: 0 | S35: 0 | T35: 0 | U35: 0
A36: 202030 | E36: 12 | F36: 9 | G36: 9 | H36: 6 | I36: 6 | J36: 3 | K36: 1 | L36: 1 | M36: 1 | N36: 1 | O36: 1 | P36: 0 | Q36: 0 | R36: 0 | S36: 0 | T36: 0 | U36: 0
A37: 202110 | F37: 28 | G37: 26 | H37: 19 | I37: 21 | J37: 17 | K37: 9 | L37: 9 | M37: 6 | N37: 3 | O37: 3 | P37: 2 | Q37: 0 | R37: 1 | S37: 1 | T37: 0 | U37: 1
A38: 202120 | G38: 29 | H38: 22 | I38: 22 | J38: 20 | K38: 12 | L38: 15 | M38: 10 | N38: 6 | O38: 6 | P38: 3 | Q38: 1 | R38: 3 | S38: 1 | T38: 0 | U38: 0
A39: 202130 | H39: 7 | I39: 7 | J39: 6 | K39: 3 | L39: 5 | M39: 3 | N39: 2 | O39: 2 | P39: 1 | Q39: 0 | R39: 0 | S39: 0 | T39: 0 | U39: 0
A40: 202210 | I40: 29 | J40: 26 | K40: 19 | L40: 17 | M40: 14 | N40: 8 | O40: 4 | P40: 4 | Q40: 1 | R40: 2 | S40: 1 | T40: 1 | U40: 1
A41: 202220 | J41: 16 | K41: 10 | L41: 9 | M41: 7 | N41: 5 | O41: 6 | P41: 4 | Q41: 2 | R41: 3 | S41: 1 | T41: 2 | U41: 0
A42: 202230 | K42: 17 | L42: 10 | M42: 8 | N42: 6 | O42: 7 | P42: 6 | Q42: 1 | R42: 2 | S42: 1 | T42: 1 | U42: 1
A43: 202310 | L43: 30 | M43: 24 | N43: 18 | O43: 17 | P43: 15 | Q43: 8 | R43: 10 | S43: 5 | T43: 2 | U43: 4
A44: 202320 | M44: 24 | N44: 16 | O44: 20 | P44: 13 | Q44: 6 | R44: 8 | S44: 4 | T44: 4 | U44: 0
A45: 202330 | N45: 9 | O45: 9 | P45: 6 | Q45: 5 | R45: 6 | S45: 3 | T45: 0 | U45: 1
A46: 202410 | O46: 30 | P46: 25 | Q46: 23 | R46: 24 | S46: 20 | T46: 10 | U46: 5
A47: 202420 | P47: 15 | Q47: 9 | R47: 13 | S47: 9 | T47: 7 | U47: 6
A48: 202430 | Q48: 14 | R48: 14 | S48: 12 | T48: 10 | U48: 10
A49: 202510 | R49: 29 | S49: 25 | T49: 15 | U49: 18
A50: 202520 | S50: 23 | T50: 18 | U50: 16
A51: 202530 | T51: 10 | U51: 9
A52: 202610 | U52: 24
A53: Total Enrolled (all cohorts) | B53: 8 | C53: 38 | D53: 74 | E53: 66 | F53: 90 | G53: 113 | H53: 76 | I53: 112 | J53: 107 | K53: 79 | L53: 106 | M53: 104 | N53: 76 | O53: 108 | P53: 96 | Q53: 70 | R53: 115 | S53: 106 | T53: 80 | U53: 96
A55: M075 — Master of Arts in Art and Technology | Historical quadrant: Double Risk
A56: Vintage ↓ / Calendar Term → | B56: 201930 | C56: 202010 | D56: 202020 | E56: 202030 | F56: 202110 | G56: 202120 | H56: 202130 | I56: 202210 | J56: 202220 | K56: 202230 | L56: 202310 | M56: 202320 | N56: 202330 | O56: 202410 | P56: 202420 | Q56: 202430 | R56: 202510 | S56: 202520 | T56: 202530 | U56: 202610
A57: 202110 | F57: 23 | G57: 20 | H57: 17 | I57: 19 | J57: 16 | K57: 2 | L57: 0 | M57: 0 | N57: 0 | O57: 0 | P57: 0 | Q57: 0 | R57: 0 | S57: 0 | T57: 0 | U57: 0
A58: 202120 | G58: 27 | H58: 15 | I58: 15 | J58: 13 | K58: 11 | L58: 1 | M58: 3 | N58: 0 | O58: 0 | P58: 0 | Q58: 0 | R58: 0 | S58: 0 | T58: 0 | U58: 0
A59: 202210 | I59: 31 | J59: 27 | K59: 22 | L59: 20 | M59: 20 | N59: 2 | O59: 1 | P59: 1 | Q59: 0 | R59: 0 | S59: 1 | T59: 1 | U59: 1
A60: 202220 | J60: 17 | K60: 16 | L60: 16 | M60: 14 | N60: 12 | O60: 1 | P60: 1 | Q60: 0 | R60: 2 | S60: 2 | T60: 1 | U60: 0
A61: 202310 | L61: 31 | M61: 26 | N61: 19 | O61: 18 | P61: 17 | Q61: 3 | R61: 2 | S61: 1 | T61: 2 | U61: 1
A62: 202320 | M62: 17 | N62: 14 | O62: 12 | P62: 13 | Q62: 11 | R62: 0 | S62: 0 | T62: 0 | U62: 0
A63: 202410 | O63: 30 | P63: 25 | Q63: 21 | R63: 18 | S63: 16 | T63: 7 | U63: 4
A64: 202420 | P64: 15 | Q64: 10 | R64: 10 | S64: 9 | T64: 9 | U64: 4
A65: 202510 | R65: 18 | S65: 18 | T65: 10 | U65: 11
A66: 202520 | S66: 15 | T66: 14 | U66: 11
A67: 202610 | U67: 11
A68: Total Enrolled (all cohorts) | F68: 23 | G68: 47 | H68: 32 | I68: 65 | J68: 73 | K68: 51 | L68: 68 | M68: 80 | N68: 47 | O68: 62 | P68: 72 | Q68: 45 | R68: 50 | S68: 62 | T68: 44 | U68: 43
A70: M073 — Master of Arts in Arts Management | Historical quadrant: Not screened (below viability threshold)
A71: Vintage ↓ / Calendar Term → | B71: 201930 | C71: 202010 | D71: 202020 | E71: 202030 | F71: 202110 | G71: 202120 | H71: 202130 | I71: 202210 | J71: 202220 | K71: 202230 | L71: 202310 | M71: 202320 | N71: 202330 | O71: 202410 | P71: 202420 | Q71: 202430 | R71: 202510 | S71: 202520 | T71: 202530 | U71: 202610
A72: 202220 | J72: 6 | K72: 6 | L72: 6 | M72: 5 | N72: 1 | O72: 2 | P72: 1 | Q72: 0 | R72: 0 | S72: 0 | T72: 0 | U72: 0
A73: 202230 | K73: 1 | L73: 1 | M73: 1 | N73: 1 | O73: 1 | P73: 0 | Q73: 0 | R73: 0 | S73: 0 | T73: 0 | U73: 0
A74: 202310 | L74: 31 | M74: 27 | N74: 24 | O74: 25 | P74: 6 | Q74: 2 | R74: 1 | S74: 0 | T74: 0 | U74: 0
A75: 202320 | M75: 42 | N75: 34 | O75: 31 | P75: 30 | Q75: 4 | R75: 3 | S75: 5 | T75: 0 | U75: 2
A76: 202410 | O76: 28 | P76: 25 | Q76: 23 | R76: 21 | S76: 7 | T76: 6 | U76: 5
A77: 202420 | P77: 31 | Q77: 24 | R77: 27 | S77: 26 | T77: 7 | U77: 4
A78: 202510 | R78: 39 | S78: 33 | T78: 29 | U78: 24
A79: 202520 | S79: 16 | T79: 11 | U79: 13
A80: 202610 | U80: 23
A81: Total Enrolled (all cohorts) | J81: 6 | K81: 7 | L81: 38 | M81: 75 | N81: 60 | O81: 87 | P81: 93 | Q81: 53 | R81: 91 | S81: 87 | T81: 53 | U81: 71
A83: M494 — Master of Arts in Global Affairs | Historical quadrant: Double Risk
A84: Vintage ↓ / Calendar Term → | B84: 201930 | C84: 202010 | D84: 202020 | E84: 202030 | F84: 202110 | G84: 202120 | H84: 202130 | I84: 202210 | J84: 202220 | K84: 202230 | L84: 202310 | M84: 202320 | N84: 202330 | O84: 202410 | P84: 202420 | Q84: 202430 | R84: 202510 | S84: 202520 | T84: 202530 | U84: 202610
A85: 201930 | B85: 4 | C85: 2 | D85: 2 | E85: 1 | F85: 2 | G85: 2 | H85: 1 | I85: 1 | J85: 1 | K85: 0 | L85: 0 | M85: 0 | N85: 0 | O85: 0 | P85: 0 | Q85: 0 | R85: 0 | S85: 0 | T85: 0 | U85: 0
A86: 202010 | C86: 27 | D86: 20 | E86: 6 | F86: 16 | G86: 12 | H86: 10 | I86: 6 | J86: 3 | K86: 3 | L86: 1 | M86: 0 | N86: 0 | O86: 0 | P86: 0 | Q86: 0 | R86: 0 | S86: 0 | T86: 0 | U86: 0
A87: 202020 | D87: 25 | E87: 9 | F87: 18 | G87: 17 | H87: 11 | I87: 13 | J87: 10 | K87: 2 | L87: 1 | M87: 2 | N87: 0 | O87: 2 | P87: 1 | Q87: 0 | R87: 0 | S87: 0 | T87: 0 | U87: 0
A88: 202030 | E88: 10 | F88: 9 | G88: 6 | H88: 5 | I88: 5 | J88: 3 | K88: 2 | L88: 2 | M88: 0 | N88: 0 | O88: 0 | P88: 0 | Q88: 1 | R88: 2 | S88: 2 | T88: 1 | U88: 1
A89: 202110 | F89: 21 | G89: 18 | H89: 5 | I89: 16 | J89: 15 | K89: 14 | L89: 9 | M89: 7 | N89: 2 | O89: 2 | P89: 0 | Q89: 0 | R89: 0 | S89: 0 | T89: 0 | U89: 0
A90: 202120 | G90: 15 | H90: 7 | I90: 12 | J90: 10 | K90: 8 | L90: 7 | M90: 5 | N90: 2 | O90: 2 | P90: 1 | Q90: 0 | R90: 2 | S90: 1 | T90: 1 | U90: 0
A91: 202130 | H91: 5 | I91: 5 | J91: 3 | K91: 2 | L91: 3 | M91: 2 | N91: 0 | O91: 1 | P91: 0 | Q91: 0 | R91: 0 | S91: 0 | T91: 0 | U91: 0
A92: 202210 | I92: 32 | J92: 26 | K92: 12 | L92: 21 | M92: 17 | N92: 6 | O92: 8 | P92: 6 | Q92: 2 | R92: 3 | S92: 2 | T92: 0 | U92: 1
A93: 202220 | J93: 25 | K93: 10 | L93: 14 | M93: 15 | N93: 11 | O93: 12 | P93: 7 | Q93: 3 | R93: 2 | S93: 1 | T93: 2 | U93: 3
A94: 202230 | K94: 15 | L94: 12 | M94: 12 | N94: 8 | O94: 10 | P94: 7 | Q94: 5 | R94: 4 | S94: 2 | T94: 0 | U94: 1
A95: 202310 | L95: 27 | M95: 23 | N95: 10 | O95: 19 | P95: 20 | Q95: 14 | R95: 12 | S95: 7 | T95: 5 | U95: 1
A96: 202320 | M96: 42 | N96: 26 | O96: 32 | P96: 24 | Q96: 19 | R96: 21 | S96: 9 | T96: 5 | U96: 4
A97: 202330 | N97: 11 | O97: 10 | P97: 6 | Q97: 7 | R97: 9 | S97: 3 | T97: 2 | U97: 2
A98: 202410 | O98: 38 | P98: 24 | Q98: 11 | R98: 20 | S98: 18 | T98: 10 | U98: 10
A99: 202420 | P99: 35 | Q99: 12 | R99: 30 | S99: 24 | T99: 17 | U99: 14
A100: 202430 | Q100: 8 | R100: 6 | S100: 3 | T100: 3 | U100: 5
A101: 202510 | R101: 29 | S101: 20 | T101: 10 | U101: 21
A102: 202520 | S102: 21 | T102: 13 | U102: 15
A103: 202530 | T103: 9 | U103: 9
A104: 202610 | U104: 13
A105: Total Enrolled (all cohorts) | B105: 4 | C105: 29 | D105: 47 | E105: 26 | F105: 66 | G105: 70 | H105: 44 | I105: 90 | J105: 96 | K105: 68 | L105: 97 | M105: 125 | N105: 76 | O105: 136 | P105: 131 | Q105: 82 | R105: 140 | S105: 113 | T105: 78 | U105: 100
A107: M700 — Master of Arts in Museum Studies | Historical quadrant: Double Risk
A108: Vintage ↓ / Calendar Term → | B108: 201930 | C108: 202010 | D108: 202020 | E108: 202030 | F108: 202110 | G108: 202120 | H108: 202130 | I108: 202210 | J108: 202220 | K108: 202230 | L108: 202310 | M108: 202320 | N108: 202330 | O108: 202410 | P108: 202420 | Q108: 202430 | R108: 202510 | S108: 202520 | T108: 202530 | U108: 202610
A109: 201930 | B109: 7 | C109: 6 | D109: 6 | E109: 3 | F109: 5 | G109: 5 | H109: 4 | I109: 3 | J109: 2 | K109: 0 | L109: 1 | M109: 1 | N109: 1 | O109: 1 | P109: 0 | Q109: 0 | R109: 0 | S109: 0 | T109: 0 | U109: 0
...

Sheet LTR Lifecycle (Proforma)
A1: LTR Lifecycle (Proforma) — same triangle, extended 6 terms into the future as a stated-assumption forecast
A2: Shaded, italic cells (and 'assumed' vintage rows) are projected, not observed — everything else is the same real data as Program LTR Retention. Existing cohorts are projected forward using this program's own validated term-over-term retention curve (holding the last observed rate flat once a projection runs past any cohort's actual history); new cohorts are assumed to keep entering each future term, sized at the recent actual average shown per program below. Treat this sheet as a forecast to stress-test, not a committed number.
A4: 1550C — Certificate in Population Health | Historical quadrant: Not screened (below viability threshold)
A5: No mature-cohort data available for this program in the current pull.
A7: D318 — Ed.D. in Education Administration | Historical quadrant: Not screened (below viability threshold)
A8: No mature-cohort data available for this program in the current pull.
A10: M366 — Executive MBA in Energy | Historical quadrant: Healthy
A11: Assumed future intake per new cohort: 5 students (avg. of last 3 actual entering classes)
A12: Vintage ↓ / Calendar Term → | B12: 201930 | C12: 202010 | D12: 202020 | E12: 202030 | F12: 202110 | G12: 202120 | H12: 202130 | I12: 202210 | J12: 202220 | K12: 202230 | L12: 202310 | M12: 202320 | N12: 202330 | O12: 202410 | P12: 202420 | Q12: 202430 | R12: 202510 | S12: 202520 | T12: 202530 | U12: 202610 | V12: 202620 | W12: 202630 | X12: 202710 | Y12: 202720 | Z12: 202730 | AA12: 202810
A13: 202010 | C13: 17 | D13: 17 | E13: 17 | F13: 17 | G13: 0 | H13: 1 | I13: 0 | J13: 0 | K13: 0 | L13: 0 | M13: 0 | N13: 0 | O13: 0 | P13: 0 | Q13: 0 | R13: 0 | S13: 0 | T13: 0 | U13: 0 | V13: 0 | W13: 0 | X13: 0 | Y13: 0 | Z13: 0 | AA13: 0
A14: 202020 | D14: 10 | E14: 10 | F14: 10 | G14: 10 | H14: 0 | I14: 0 | J14: 0 | K14: 0 | L14: 0 | M14: 0 | N14: 0 | O14: 0 | P14: 0 | Q14: 0 | R14: 0 | S14: 0 | T14: 0 | U14: 0 | V14: 0 | W14: 0 | X14: 0 | Y14: 0 | Z14: 0 | AA14: 0
A15: 202030 | E15: 11 | F15: 11 | G15: 10 | H15: 10 | I15: 9 | J15: 0 | K15: 1 | L15: 0 | M15: 0 | N15: 0 | O15: 0 | P15: 0 | Q15: 0 | R15: 0 | S15: 0 | T15: 0 | U15: 0 | V15: 0 | W15: 0 | X15: 0 | Y15: 0 | Z15: 0 | AA15: 0
A16: 202110 | F16: 9 | G16: 9 | H16: 8 | I16: 8 | J16: 8 | K16: 0 | L16: 0 | M16: 0 | N16: 0 | O16: 0 | P16: 0 | Q16: 0 | R16: 0 | S16: 0 | T16: 0 | U16: 0 | V16: 0 | W16: 0 | X16: 0 | Y16: 0 | Z16: 0 | AA16: 0
A17: 202130 | H17: 20 | I17: 20 | J17: 20 | K17: 19 | L17: 19 | M17: 0 | N17: 0 | O17: 0 | P17: 0 | Q17: 0 | R17: 0 | S17: 0 | T17: 0 | U17: 0 | V17: 0 | W17: 0 | X17: 0 | Y17: 0 | Z17: 0 | AA17: 0
A18: 202210 | I18: 18 | J18: 18 | K18: 17 | L18: 17 | M18: 17 | N18: 1 | O18: 1 | P18: 0 | Q18: 1 | R18: 1 | S18: 1 | T18: 0 | U18: 0 | V18: 0 | W18: 0 | X18: 0 | Y18: 0 | Z18: 0 | AA18: 0
A19: 202230 | K19: 12 | L19: 12 | M19: 12 | N19: 12 | O19: 12 | P19: 1 | Q19: 0 | R19: 0 | S19: 0 | T19: 0 | U19: 0 | V19: 0 | W19: 0 | X19: 0 | Y19: 0 | Z19: 0 | AA19: 0
A20: 202310 | L20: 15 | M20: 15 | N20: 15 | O20: 15 | P20: 15 | Q20: 2 | R20: 0 | S20: 0 | T20: 0 | U20: 0 | V20: 0 | W20: 0 | X20: 0 | Y20: 0 | Z20: 0 | AA20: 0
A21: 202330 | N21: 12 | O21: 12 | P21: 12 | Q21: 12 | R21: 12 | S21: 1 | T21: 0 | U21: 0 | V21: 0 | W21: 0 | X21: 0 | Y21: 0 | Z21: 0 | AA21: 0
A22: 202410 | O22: 12 | P22: 11 | Q22: 11 | R22: 11 | S22: 11 | T22: 0 | U22: 0 | V22: 0 | W22: 0 | X22: 0 | Y22: 0 | Z22: 0 | AA22: 0
A23: 202430 | Q23: 6 | R23: 6 | S23: 6 | T23: 6 | U23: 6 | V23: 0 | W23: 0 | X23: 0 | Y23: 0 | Z23: 0 | AA23: 0
A24: 202510 | R24: 9 | S24: 9 | T24: 8 | U24: 9 | V24: 7 | W24: 0 | X24: 0 | Y24: 0 | Z24: 0 | AA24: 0
A25: 202520 | S25: 1 | T25: 1 | U25: 1 | V25: 1 | W25: 1 | X25: 0 | Y25: 0 | Z25: 0 | AA25: 0
A26: 202530 | T26: 5 | U26: 5 | V26: 5 | W26: 5 | X26: 4 | Y26: 0 | Z26: 0 | AA26: 0
A27: 202620 (assumed) | V27: 5 | W27: 5 | X27: 5 | Y27: 5 | Z27: 4 | AA27: 0
A28: 202630 (assumed) | W28: 5 | X28: 5 | Y28: 5 | Z28: 5 | AA28: 4
A29: 202710 (assumed) | X29: 5 | Y29: 5 | Z29: 5 | AA29: 5
A30: 202720 (assumed) | Y30: 5 | Z30: 5 | AA30: 5
A31: 202730 (assumed) | Z31: 5 | AA31: 5
A32: 202810 (assumed) | AA32: 5
A33: Total Enrolled (all cohorts) | C33: 17 | D33: 27 | E33: 38 | F33: 47 | G33: 29 | H33: 39 | I33: 55 | J33: 46 | K33: 49 | L33: 63 | M33: 44 | N33: 40 | O33: 52 | P33: 39 | Q33: 32 | R33: 39 | S33: 29 | T33: 20 | U33: 21 | V33: 18 | W33: 16 | X33: 19 | Y33: 20 | Z33: 23 | AA33: 23
A35: 1231EX — Executive Masters in Health Administration | Historical quadrant: Not screened (below viability threshold)
A36: No mature-cohort data available for this program in the current pull.
A38: M013 — Master of Accountancy | Historical quadrant: Double Risk
A39: Assumed future intake per new cohort: 19 students (avg. of last 3 actual entering classes)
A40: Vintage ↓ / Calendar Term → | B40: 201930 | C40: 202010 | D40: 202020 | E40: 202030 | F40: 202110 | G40: 202120 | H40: 202130 | I40: 202210 | J40: 202220 | K40: 202230 | L40: 202310 | M40: 202320 | N40: 202330 | O40: 202410 | P40: 202420 | Q40: 202430 | R40: 202510 | S40: 202520 | T40: 202530 | U40: 202610 | V40: 202620 | W40: 202630 | X40: 202710 | Y40: 202720 | Z40: 202730 | AA40: 202810
A41: 201930 | B41: 8 | C41: 7 | D41: 6 | E41: 1 | F41: 3 | G41: 2 | H41: 0 | I41: 1 | J41: 0 | K41: 0 | L41: 0 | M41: 0 | N41: 0 | O41: 0 | P41: 0 | Q41: 0 | R41: 0 | S41: 0 | T41: 0 | U41: 0 | V41: 0 | W41: 0 | X41: 0 | Y41: 0 | Z41: 0 | AA41: 0
A42: 202010 | C42: 31 | D42: 27 | E42: 22 | F42: 20 | G42: 18 | H42: 10 | I42: 9 | J42: 8 | K42: 3 | L42: 4 | M42: 2 | N42: 1 | O42: 2 | P42: 1 | Q42: 0 | R42: 0 | S42: 0 | T42: 0 | U42: 0 | V42: 0 | W42: 0 | X42: 0 | Y42: 0 | Z42: 0 | AA42: 0
A43: 202020 | D43: 41 | E43: 31 | F43: 30 | G43: 29 | H43: 12 | I43: 17 | J43: 11 | K43: 5 | L43: 6 | M43: 5 | N43: 1 | O43: 1 | P43: 1 | Q43: 0 | R43: 0 | S43: 0 | T43: 0 | U43: 0 | V43: 0 | W43: 0 | X43: 0 | Y43: 0 | Z43: 0 | AA43: 0
A44: 202030 | E44: 12 | F44: 9 | G44: 9 | H44: 6 | I44: 6 | J44: 3 | K44: 1 | L44: 1 | M44: 1 | N44: 1 | O44: 1 | P44: 0 | Q44: 0 | R44: 0 | S44: 0 | T44: 0 | U44: 0 | V44: 0 | W44: 0 | X44: 0 | Y44: 0 | Z44: 0 | AA44: 0
A45: 202110 | F45: 28 | G45: 26 | H45: 19 | I45: 21 | J45: 17 | K45: 9 | L45: 9 | M45: 6 | N45: 3 | O45: 3 | P45: 2 | Q45: 0 | R45: 1 | S45: 1 | T45: 0 | U45: 1 | V45: 0 | W45: 0 | X45: 0 | Y45: 0 | Z45: 0 | AA45: 0
A46: 202120 | G46: 29 | H46: 22 | I46: 22 | J46: 20 | K46: 12 | L46: 15 | M46: 10 | N46: 6 | O46: 6 | P46: 3 | Q46: 1 | R46: 3 | S46: 1 | T46: 0 | U46: 0 | V46: 0 | W46: 0 | X46: 0 | Y46: 0 | Z46: 0 | AA46: 0
A47: 202130 | H47: 7 | I47: 7 | J47: 6 | K47: 3 | L47: 5 | M47: 3 | N47: 2 | O47: 2 | P47: 1 | Q47: 0 | R47: 0 | S47: 0 | T47: 0 | U47: 0 | V47: 0 | W47: 0 | X47: 0 | Y47: 0 | Z47: 0 | AA47: 0
A48: 202210 | I48: 29 | J48: 26 | K48: 19 | L48: 17 | M48: 14 | N48: 8 | O48: 4 | P48: 4 | Q48: 1 | R48: 2 | S48: 1 | T48: 1 | U48: 1 | V48: 0 | W48: 0 | X48: 0 | Y48: 0 | Z48: 0 | AA48: 0
A49: 202220 | J49: 16 | K49: 10 | L49: 9 | M49: 7 | N49: 5 | O49: 6 | P49: 4 | Q49: 2 | R49: 3 | S49: 1 | T49: 2 | U49: 0 | V49: 0 | W49: 0 | X49: 0 | Y49: 0 | Z49: 0 | AA49: 0
A50: 202230 | K50: 17 | L50: 10 | M50: 8 | N50: 6 | O50: 7 | P50: 6 | Q50: 1 | R50: 2 | S50: 1 | T50: 1 | U50: 1 | V50: 1 | W50: 1 | X50: 0 | Y50: 0 | Z50: 0 | AA50: 0
A51: 202310 | L51: 30 | M51: 24 | N51: 18 | O51: 17 | P51: 15 | Q51: 8 | R51: 10 | S51: 5 | T51: 2 | U51: 4 | V51: 2 | W51: 1 | X51: 1 | Y51: 0 | Z51: 0 | AA51: 0
A52: 202320 | M52: 24 | N52: 16 | O52: 20 | P52: 13 | Q52: 6 | R52: 8 | S52: 4 | T52: 4 | U52: 0 | V52: 0 | W52: 0 | X52: 0 | Y52: 0 | Z52: 0 | AA52: 0
A53: 202330 | N53: 9 | O53: 9 | P53: 6 | Q53: 5 | R53: 6 | S53: 3 | T53: 0 | U53: 1 | V53: 1 | W53: 1 | X53: 0 | Y53: 0 | Z53: 0 | AA53: 0
A54: 202410 | O54: 30 | P54: 25 | Q54: 23 | R54: 24 | S54: 20 | T54: 10 | U54: 5 | V54: 4 | W54: 2 | X54: 2 | Y54: 1 | Z54: 0 | AA54: 0
A55: 202420 | P55: 15 | Q55: 9 | R55: 13 | S55: 9 | T55: 7 | U55: 6 | V55: 4 | W55: 3 | X55: 2 | Y55: 2 | Z55: 1 | AA55: 0
A56: 202430 | Q56: 14 | R56: 14 | S56: 12 | T56: 10 | U56: 10 | V56: 8 | W56: 5 | X56: 4 | Y56: 2 | Z56: 2 | AA56: 1
A57: 202510 | R57: 29 | S57: 25 | T57: 15 | U57: 18 | V57: 14 | W57: 11 | X57: 7 | Y57: 5 | Z57: 3 | AA57: 3
A58: 202520 | S58: 23 | T58: 18 | U58: 16 | V58: 14 | W58: 10 | X58: 8 | Y58: 6 | Z58: 4 | AA58: 2
A59: 202530 | T59: 10 | U59: 9 | V59: 8 | W59: 7 | X59: 5 | Y59: 4 | Z59: 3 | AA59: 2
A60: 202610 | U60: 24 | V60: 19 | W60: 17 | X60: 14 | Y60: 11 | Z60: 8 | AA60: 6
A61: 202620 (assumed) | V61: 19 | W61: 15 | X61: 13 | Y61: 11 | Z61: 8 | AA61: 7
A62: 202630 (assumed) | W62: 19 | X62: 15 | Y62: 13 | Z62: 11 | AA62: 8
A63: 202710 (assumed) | X63: 19 | Y63: 15 | Z63: 13 | AA63: 11
A64: 202720 (assumed) | Y64: 19 | Z64: 15 | AA64: 13
A65: 202730 (assumed) | Z65: 19 | AA65: 15
A66: 202810 (assumed) | AA66: 19
A67: Total Enrolled (all cohorts) | B67: 8 | C67: 38 | D67: 74 | E67: 66 | F67: 90 | G67: 113 | H67: 76 | I67: 112 | J67: 107 | K67: 79 | L67: 106 | M67: 104 | N67: 76 | O67: 108 | P67: 96 | Q67: 70 | R67: 115 | S67: 106 | T67: 80 | U67: 96 | V67: 92 | W67: 91 | X67: 90 | Y67: 89 | Z67: 88 | AA67: 88
A69: M075 — Master of Arts in Art and Technology | Historical quadrant: Double Risk
A70: Assumed future intake per new cohort: 15 students (avg. of last 3 actual entering classes)
A71: Vintage ↓ / Calendar Term → | B71: 201930 | C71: 202010 | D71: 202020 | E71: 202030 | F71: 202110 | G71: 202120 | H71: 202130 | I71: 202210 | J71: 202220 | K71: 202230 | L71: 202310 | M71: 202320 | N71: 202330 | O71: 202410 | P71: 202420 | Q71: 202430 | R71: 202510 | S71: 202520 | T71: 202530 | U71: 202610 | V71: 202620 | W71: 202630 | X71: 202710 | Y71: 202720 | Z71: 202730 | AA71: 202810
A72: 202110 | F72: 23 | G72: 20 | H72: 17 | I72: 19 | J72: 16 | K72: 2 | L72: 0 | M72: 0 | N72: 0 | O72: 0 | P72: 0 | Q72: 0 | R72: 0 | S72: 0 | T72: 0 | U72: 0 | V72: 0 | W72: 0 | X72: 0 | Y72: 0 | Z72: 0 | AA72: 0
A73: 202120 | G73: 27 | H73: 15 | I73: 15 | J73: 13 | K73: 11 | L73: 1 | M73: 3 | N73: 0 | O73: 0 | P73: 0 | Q73: 0 | R73: 0 | S73: 0 | T73: 0 | U73: 0 | V73: 0 | W73: 0 | X73: 0 | Y73: 0 | Z73: 0 | AA73: 0
A74: 202210 | I74: 31 | J74: 27 | K74: 22 | L74: 20 | M74: 20 | N74: 2 | O74: 1 | P74: 1 | Q74: 0 | R74: 0 | S74: 1 | T74: 1 | U74: 1 | V74: 1 | W74: 1 | X74: 1 | Y74: 1 | Z74: 1 | AA74: 1
A75: 202220 | J75: 17 | K75: 16 | L75: 16 | M75: 14 | N75: 12 | O75: 1 | P75: 1 | Q75: 0 | R75: 2 | S75: 2 | T75: 1 | U75: 0 | V75: 0 | W75: 0 | X75: 0 | Y75: 0 | Z75: 0 | AA75: 0
A76: 202310 | L76: 31 | M76: 26 | N76: 19 | O76: 18 | P76: 17 | Q76: 3 | R76: 2 | S76: 1 | T76: 2 | U76: 1 | V76: 1 | W76: 0 | X76: 0 | Y76: 0 | Z76: 0 | AA76: 0
A77: 202320 | M77: 17 | N77: 14 | O77: 12 | P77: 13 | Q77: 11 | R77: 0 | S77: 0 | T77: 0 | U77: 0 | V77: 0 | W77: 0 | X77: 0 | Y77: 0 | Z77: 0 | AA77: 0
A78: 202410 | O78: 30 | P78: 25 | Q78: 21 | R78: 18 | S78: 16 | T78: 7 | U78: 4 | V78: 1 | W78: 2 | X78: 2 | Y78: 1 | Z78: 1 | AA78: 1
A79: 202420 | P79: 15 | Q79: 10 | R79: 10 | S79: 9 | T79: 9 | U79: 4 | V79: 3 | W79: 1 | X79: 2 | Y79: 1 | Z79: 1 | AA79: 0
A80: 202510 | R80: 18 | S80: 18 | T80: 10 | U80: 11 | V80: 10 | W80: 1 | X80: 1 | Y80: 0 | Z80: 0 | AA80: 0
A81: 202520 | S81: 15 | T81: 14 | U81: 11 | V81: 11 | W81: 9 | X81: 1 | Y81: 1 | Z81: 0 | AA81: 0
A82: 202610 | U82: 11 | V82: 9 | W82: 8 | X82: 7 | Y82: 7 | Z82: 1 | AA82: 1
A83: 202620 (assumed) | V83: 15 | W83: 12 | X83: 10 | Y83: 10 | Z83: 9 | AA83: 1
A84: 202630 (assumed) | W84: 15 | X84: 12 | Y84: 10 | Z84: 10 | AA84: 9
A85: 202710 (assumed) | X85: 15 | Y85: 12 | Z85: 10 | AA85: 10
A86: 202720 (assumed) | Y86: 15 | Z86: 12 | AA86: 10
A87: 202730 (assumed) | Z87: 15 | AA87: 12
A88: 202810 (assumed) | AA88: 15
A89: Total Enrolled (all cohorts) | F89: 23 | G89: 47 | H89: 32 | I89: 65 | J89: 73 | K89: 51 | L89: 68 | M89: 80 | N89: 47 | O89: 62 | P89: 72 | Q89: 45 | R89: 50 | S89: 62 | T89: 44 | U89: 43 | V89: 50 | W89: 50 | X89: 51 | Y89: 59 | Z89: 61 | AA89: 61
A91: M073 — Master of Arts in Arts Management | Historical quadrant: Not screened (below viability threshold)
A92: Assumed future intake per new cohort: 26 students (avg. of last 3 actual entering classes)
A93: Vintage ↓ / Calendar Term → | B93: 201930 | C93: 202010 | D93: 202020 | E93: 202030 | F93: 202110 | G93: 202120 | H93: 202130 | I93: 202210 | J93: 202220 | K93: 202230 | L93: 202310 | M93: 202320 | N93: 202330 | O93: 202410 | P93: 202420 | Q93: 202430 | R93: 202510 | S93: 202520 | T93: 202530 | U93: 202610 | V93: 202620 | W93: 202630 | X93: 202710 | Y93: 202720 | Z93: 202730 | AA93: 202810
A94: 202220 | J94: 6 | K94: 6 | L94: 6 | M94: 5 | N94: 1 | O94: 2 | P94: 1 | Q94: 0 | R94: 0 | S94: 0 | T94: 0 | U94: 0 | V94: 0 | W94: 0 | X94: 0 | Y94: 0 | Z94: 0 | AA94: 0
A95: 202230 | K95: 1 | L95: 1 | M95: 1 | N95: 1 | O95: 1 | P95: 0 | Q95: 0 | R95: 0 | S95: 0 | T95: 0 | U95: 0 | V95: 0 | W95: 0 | X95: 0 | Y95: 0 | Z95: 0 | AA95: 0
A96: 202310 | L96: 31 | M96: 27 | N96: 24 | O96: 25 | P96: 6 | Q96: 2 | R96: 1 | S96: 0 | T96: 0 | U96: 0 | V96: 0 | W96: 0 | X96: 0 | Y96: 0 | Z96: 0 | AA96: 0
A97: 202320 | M97: 42 | N97: 34 | O97: 31 | P97: 30 | Q97: 4 | R97: 3 | S97: 5 | T97: 0 | U97: 2 | V97: 0 | W97: 0 | X97: 0 | Y97: 0 | Z97: 0 | AA97: 0
A98: 202410 | O98: 28 | P98: 25 | Q98: 23 | R98: 21 | S98: 7 | T98: 6 | U98: 5 | V98: 0 | W98: 0 | X98: 0 | Y98: 0 | Z98: 0 | AA98: 0
A99: 202420 | P99: 31 | Q99: 24 | R99: 27 | S99: 26 | T99: 7 | U99: 4 | V99: 4 | W99: 0 | X99: 0 | Y99: 0 | Z99: 0 | AA99: 0
A100: 202510 | R100: 39 | S100: 33 | T100: 29 | U100: 24 | V100: 5 | W100: 3 | X100: 3 | Y100: 0 | Z100: 0 | AA100: 0
A101: 202520 | S101: 16 | T101: 11 | U101: 13 | V101: 13 | W101: 3 | X101: 1 | Y101: 1 | Z101: 0 | AA101: 0
A102: 202610 | U102: 23 | V102: 20 | W102: 18 | X102: 18 | Y102: 3 | Z102: 2 | AA102: 2
A103: 202620 (assumed) | V103: 26 | W103: 22 | X103: 20 | Y103: 20 | Z103: 4 | AA103: 2
A104: 202630 (assumed) | W104: 26 | X104: 22 | Y104: 20 | Z104: 20 | AA104: 4
A105: 202710 (assumed) | X105: 26 | Y105: 22 | Z105: 20 | AA105: 20
A106: 202720 (assumed) | Y106: 26 | Z106: 22 | AA106: 20
A107: 202730 (assumed) | Z107: 26 | AA107: 22
...

Sheet Comparison & Findings
A1: Comparison & Findings — All 41 Graduate Programs
A2: Method A New Student Retention vs Method B Pooled/Simple-Avg S(T3) vs the Revenue model's own pooled T→T+1 rate.
A4: Code | B4: Program Name | C4: N @ T1 | D4: Method A New Retention | E4: Method B Pooled S(T3) | F4: Method B Simple-Avg S(T3) | G4: Revenue Model Pooled Rate | H4: Sample Flag
A5: 1550C | B5: Certificate in Population Health | G5: 0.902 | H5: No data
A6: D318 | B6: Ed.D. in Education Administration | G6: 0.96724138 | H6: No data
A7: M366 | B7: Executive MBA in Energy | C7: 112 | D7: 0.97321429 | E7: 0.97321429 | F7: 0.96780303 | G7: 0.76842105 | H7: OK
A8: 1231EX | B8: Executive Masters in Health Administration | G8: 0.902 | H8: No data
A9: M013 | B9: Master of Accountancy | C9: 272 | D9: 0.69117647 | E9: 0.69117647 | F9: 0.69644281 | G9: 0.77372263 | H9: OK
A10: M075 | B10: Master of Arts in Art and Technology | C10: 146 | D10: 0.69178082 | E10: 0.69178082 | F10: 0.71072091 | G10: 0.73230373 | H10: OK
A11: M073 | B11: Master of Arts in Arts Management | C11: 80 | D11: 0.775 | E11: 0.775 | F11: 0.8780722 | G11: 0.73534338 | H11: OK
A12: M494 | B12: Master of Arts in Global Affairs | C12: 248 | D12: 0.53225806 | E12: 0.53225806 | F12: 0.54563272 | G12: 0.64097969 | H12: OK
A13: M700 | B13: Master of Arts in Museum Studies | C13: 474 | D13: 0.65400844 | E13: 0.65400844 | F13: 0.63771837 | G13: 0.74895397 | H13: OK
A14: M762 | B14: Master of Arts in Organizational Leadership | C14: 505 | D14: 0.57029703 | E14: 0.57029703 | F14: 0.57736759 | G14: 0.66678521 | H14: OK
A15: M859 | B15: Master of Arts in Strategic Communication and Digital Strategy | C15: 256 | D15: 0.8125 | E15: 0.8125 | F15: 0.8097506 | G15: 0.74555792 | H15: OK
A16: M202 | B16: Master of Clinical Mental Health Counseling | C16: 240 | D16: 0.7875 | E16: 0.7875 | F16: 0.79731129 | G16: 0.84652406 | H16: OK
A17: M246 | B17: Master of Construction Business | C17: 115 | D17: 0.86956522 | E17: 0.86956522 | F17: 0.87434605 | G17: 0.74925373 | H17: OK
A18: M297 | B18: Master of Econometrics | G18: 0.73404255 | H18: No data
A19: M383 | B19: Master of Entrepreneurship & Innovation | G19: 0.65789474 | H19: No data
A20: M518 | B20: Master of Environmental Science: Hydrology and Water Security | C20: 254 | D20: 0.72440945 | E20: 0.72440945 | F20: 0.70742494 | G20: 0.70339977 | H20: OK
A21: M368 | B21: Master of Legal Studies - Energy | C21: 82 | D21: 0.70731707 | E21: 0.70731707 | F21: 0.72367306 | G21: 0.67857143 | H21: OK
A22: M636 | B22: Master of Legal Studies - General | G22: 0.902 | H22: No data
A23: M503 | B23: Master of Legal Studies - Healthcare Law | C23: 428 | D23: 0.73364486 | E23: 0.73364486 | F23: 0.74187156 | G23: 0.67091712 | H23: OK
A24: M522 | B24: Master of Legal Studies - Indigenous Peoples Law | C24: 566 | D24: 0.67844523 | E24: 0.67844523 | F24: 0.67878777 | G24: 0.64137676 | H24: OK
A25: M589 | B25: Master of Legal Studies - International Business | C25: 68 | D25: 0.70588235 | E25: 0.70588235 | F25: 0.70757576 | G25: 0.65231788 | H25: OK
A26: M029 | B26: Master of Science in Applied Computing | G26: 0.75 | H26: No data
A27: M035 | B27: Master of Science in Applied Statistics | C27: 49 | D27: 0.42857143 | E27: 0.42857143 | F27: 0.42676768 | G27: 0.7 | H27: OK
A28: M145 | B28: Master of Science in Business Analytics | C28: 77 | D28: 0.61038961 | E28: 0.61038961 | F28: 0.68135621 | G28: 0.71980676 | H28: OK
A29: M191 | B29: Master of Science in Civil Engineering | C29: 145 | D29: 0.83448276 | E29: 0.83448276 | F29: 0.85161364 | G29: 0.70127326 | H29: OK
A30: M260 | B30: Master of Science in Criminal Justice | C30: 218 | D30: 0.55504587 | E30: 0.55504587 | F30: 0.60966448 | G30: 0.65352113 | H30: OK
A31: M264 | B31: Master of Science in Cybersecurity Leadership | G31: 0.902 | H31: No data
A32: M374 | B32: Master of Science in Engineering Leadership and Management | C32: 24 | D32: 0.79166667 | E32: 0.79166667 | F32: 0.79166667 | G32: 0.76719577 | H32: Thin sample (<30)
A33: M435 | B33: Master of Science in Finance | C33: 262 | D33: 0.74427481 | E33: 0.74427481 | F33: 0.76522752 | G33: 0.70160609 | H33: OK
A34: M464 | B34: Master of Science in Geospatial Technology | C34: 103 | D34: 0.69902913 | E34: 0.69902913 | F34: 0.67661648 | G34: 0.72908367 | H34: OK
A35: M527 | B35: Master of Science in Industrial and Systems Engineering | C35: 91 | D35: 0.59340659 | E35: 0.59340659 | F35: 0.57954545 | G35: 0.73257699 | H35: OK
A36: M746 | B36: Master of Science in Natural Gas Engineering and Management | C36: 82 | D36: 0.65853659 | E36: 0.65853659 | F36: 0.69423786 | G36: 0.72615385 | H36: OK
A37: M861 | B37: Master of Science in Supply Chain Management | C37: 88 | D37: 0.81818182 | E37: 0.81818182 | F37: 0.844 | G37: 0.74495413 | H37: OK
A38: M869 | B38: Master of Science in Sustainability - Energy and Materials Mgmt | C38: 26 | D38: 0.61538462 | E38: 0.61538462 | F38: 0.60714286 | G38: 0.76627219 | H38: Thin sample (<30)
A39: M867 | B39: Master of Science in Sustainable Architecture | C39: 20 | D39: 0.75 | E39: 0.75 | F39: 0.75 | G39: 0.68108108 | H39: Thin sample (<30)
A40: M844 | B40: Master of Social Work | C40: 771 | D40: 0.77172503 | E40: 0.77172503 | F40: 0.74614845 | G40: 0.84155582 | H40: OK
A41: 1237Q | B41: Masters in Public Health | G41: 0.902 | H41: No data
A42: M355 | B42: Online LL.M. Energy and Natural Resources | C42: 9 | D42: 0.44444444 | E42: 0.44444444 | F42: 0.43333333 | G42: 0.65625 | H42: Thin sample (<30)
A43: M504 | B43: Online LL.M. Healthcare Law | C43: 9 | D43: 0.33333333 | E43: 0.33333333 | F43: 0.35714286 | G43: 0.902 | H43: Thin sample (<30)
A44: M526 | B44: Online LL.M. Indigenous Peoples Law | C44: 19 | D44: 0.36842105 | E44: 0.36842105 | F44: 0.45714286 | G44: 0.6 | H44: Thin sample (<30)
A45: M592 | B45: Online LL.M. International Business | C45: 2 | D45: 0.5 | E45: 0.5 | F45: 0.5 | G45: 0.902 | H45: Thin sample (<30)
A48: Findings
A50: Every cross-check passed — Method A and Method B agree exactly for all 30 programs with data
A51: Method A's New Student Retention and Method B's Pooled S(T3) are two different computational paths to the same definition (student-weighted T1→T3 presence among mature cohorts), and they reconciled to the decimal for every one of the 30 programs that has any mature-cohort data. That's a strong internal-consistency signal for the pipeline itself — the divergence between methods people actually care about (pooled vs. simple-average) shows up cleanly without being muddied by a computation bug.
A53: 9 of 41 graduate programs have zero mature-cohort data; 7 more are thin-sample (<30 at T1)
A54: That leaves only about half the graduate portfolio (roughly a dozen-plus programs) with genuinely decision-grade sample sizes right now. The zero-data programs are the same new/renumbered-away programs already flagged in the Portfolio Screen (e.g. M867, M297, D318, M264, M029, M374, the three health-cluster programs, M636, M383) — this is a second, independent confirmation of that gap, not a new problem.
A56: Pooled and Simple-Average diverge by 5–11 points for several programs — lopsided cohort sizes are the cause
A57: Arts Management (−10.9pp), Environmental Science: Hydrology (−9.3pp), Business Analytics (−8.7pp), Social Work (−7.1pp), and Global Affairs (−6.8pp) all show Simple-Average sitting well above Pooled — meaning their smaller/older cohorts persisted better than their more recent, larger intakes. Pooled is dragged down by size; Simple-Average treats every cohort equally regardless of size. For these programs specifically, the choice of aggregation method meaningfully changes the headline number — unlike Accounting, where the pilot found this choice was low-stakes. That earlier finding does not generalize across the portfolio; each program needs its own check before you pick one convention for all of them.
A59: Method A's New Retention runs BELOW the Revenue model's own pooled rate for almost every program — by design, not error
A60: For 27 of the 30 programs with data, this workbook's New Student Retention (a strict Term-1→Term-3 measure on new cohorts only) is lower than the Revenue model assumption sheet's empirical rate (a single pooled rate across EVERY consecutive term-pair, new and continuing students alike, 5–18 transitions of history). That's expected: continuing students further into a program tend to persist term-over-term better than students in their first two terms, so a rate that blends all of them in will run higher than one anchored specifically on new-cohort early attrition. The two numbers answer different questions — the Revenue model's rate is closer to average, whole book of business retention; this model's rate is specifically about the new-student funnel. The 3 biggest gaps: Museum Studies (48.7% vs 74.9%, −26pp), Global Affairs (47.6% vs 64.1%, −16pp), and Criminal Justice (53.8% vs 65.4%, −12pp) — worth a closer look at whether these programs specifically lose students hardest in the first two terms.
A62: Returning Student Retention is now a credit-hour-weighted average, not scaled by program length
A63: As of the correction below, Returning Student Retention is a credit-hour-weighted average of each included term's own retention ratio — it no longer divides by the program's Credit Hours to Degree, so a shorter program (e.g. the 24-CH Online LL.M.s) is no longer structurally advantaged over a longer one (e.g. the 60-CH Social Work / Clinical Mental Health Counseling programs) the way the prior version was. It's still most meaningful compared within a program over time rather than ranked head-to-head across programs with very different term-by-term shapes — but program length itself no longer drives the gap.
A65: This build pools Accounting's M002 + M012 (Advanced Standing) + M013 — differs from the earlier single-program pilot by design
A66: Same note as in the Portfolio Screen: the earlier Accounting-only pilot deliberately excluded the Advanced-Standing track (M012) to get the cleanest possible single-track read. This build matches how the Revenue model tracks Accounting as one row, so its 58.5% New Retention here is not directly comparable to the pilot's 67.7% — different population, same math.

Sheet Revenue Outlook
A1: Revenue Outlook — Tuition revenue lost to imperfect retention, per graduate program
A2: LTR now uses the Direct survival-curve method (adopted per your review): Price/Credit × Σ over terms of [share of the Term-1 cohort still enrolled × average credits taken that term], truncated once cohort share first drops below the 12% LTR-inclusion floor (latched). This replaces the earlier cascading (New Retention × Returning Retention) formula. Tuition Cost, Degree Credit Hours, and New Starts are sourced live from Rev_Forecast_Model_final.xlsx; the survival curve and per-term credit loads are this workbook's own raw persistence data. Bad Debt Loss is excluded. See the Read Me for the full formula and the evidence behind the 12% floor.
A4: Program | B4: Degree Credit Hours | C4: Tuition Cost (per Student) | D4: New Starts (Fall 2026) | E4: Revenue (Program Total) | F4: Expected CH/Student (Direct, @12% floor) | G4: LTR as % of Tuition (Direct) | H4: Revenue Loss (Program Total) | I4: LTR (Program Total)
A5: 1550C — Certificate in Population Health | B5: 12 | C5: 6900 | D5: 14.9 | E5: 102672 | F5: No data | G5: No data | H5: No data | I5: No data
A6: D318 — Ed.D. in Education Administration | B6: 54 | C6: 30618 | D6: 0 | E6: 0 | F6: No data | G6: No data | H6: No data | I6: No data
A7: M366 — Executive MBA in Energy | B7: 36 | C7: 88020 | D7: 5.6 | E7: 491152 | F7: 34.89 | G7: 0.96924603 | H7: -15105 | I7: 476047
A8: 1231EX — Executive Masters in Health Administration | B8: 42 | C8: 24150 | D8: 10.2 | E8: 247054 | F8: No data | G8: No data | H8: No data | I8: No data
A9: M013 — Master of Accountancy | B9: 40 | C9: 40600 | D9: 26 | E9: 1057224 | F9: 25.06 | G9: 0.62637868 | H9: -395001 | I9: 662223
A10: M075 — Master of Arts in Art and Technology | B10: 33 | C10: 27885 | D10: 9.3 | E10: 259330 | F10: 23.51 | G10: 0.71232877 | H10: -74602 | I10: 184729
A11: M073 — Master of Arts in Arts Management | B11: 30 | C11: 30450 | D11: 24.2 | E11: 736281 | F11: 24.86 | G11: 0.82875 | H11: -126088 | I11: 610193
A12: M494 — Master of Arts in Global Affairs | B12: 33 | C12: 27885 | D12: 13.9 | E12: 388996 | F12: 22.9 | G12: 0.69403715 | H12: -119018 | I12: 269978
A13: M700 — Master of Arts in Museum Studies | B13: 33 | C13: 27885 | D13: 50.2 | E13: 1400385 | F13: 23.71 | G13: 0.7183864 | H13: -394367 | I13: 1006017
A14: M762 — Master of Arts in Organizational Leadership | B14: 30 | C14: 25350 | D14: 41.8 | E14: 1060897 | F14: 20.89 | G14: 0.69630363 | H14: -322191 | I14: 738707
A15: M859 — Master of Arts in Strategic Communication and Digital Strategy | B15: 33 | C15: 27885 | D15: 11.2 | E15: 311197 | F15: 27.43 | G15: 0.83132102 | H15: -52492 | I15: 258704
A16: M202 — Master of Clinical Mental Health Counseling | B16: 60 | C16: 50700 | D16: 43.7 | E16: 2216097 | F16: 46.27 | G16: 0.77111111 | H16: -507240 | I16: 1708857
A17: M246 — Master of Construction Business | B17: 32 | C17: 32480 | D17: 19.5 | E17: 634334 | F17: 29.07 | G17: 0.90842391 | H17: -58090 | I17: 576245
A18: M297 — Master of Econometrics | B18: 30 | C18: 25350 | D18: 6.5 | E18: 165028 | F18: No data | G18: No data | H18: No data | I18: No data
A19: M383 — Master of Entrepreneurship & Innovation | B19: 30 | C19: 30450 | D19: 5.6 | E19: 169911 | F19: No data | G19: No data | H19: No data | I19: No data
A20: M518 — Master of Environmental Science: Hydrology and Water Security | B20: 30 | C20: 30450 | D20: 29.8 | E20: 906192 | F20: 23.97 | G20: 0.79895013 | H20: -182190 | I20: 724002
A21: M368 — Master of Legal Studies - Energy | B21: 32 | C21: 27027 | D21: 17.7 | E21: 477571 | F21: 22.99 | G21: 0.7183689 | H21: -134499 | I21: 343072
A22: M636 — Master of Legal Studies - General | B22: 32 | C22: 27027 | D22: 14.9 | E22: 402165 | F22: No data | G22: No data | H22: No data | I22: No data
A23: M503 — Master of Legal Studies - Healthcare Law | B23: 32 | C23: 27027 | D23: 20.5 | E23: 552977 | F23: 25.96 | G23: 0.81118575 | H23: -104410 | I23: 448567
A24: M522 — Master of Legal Studies - Indigenous Peoples Law | B24: 33 | C24: 27872 | D24: 23.2 | E24: 648019 | F24: 25.42 | G24: 0.7704251 | H24: -148769 | I24: 499250
A25: M589 — Master of Legal Studies - International Business | B25: 32 | C25: 27027 | D25: 4.6 | E25: 125676 | F25: 23.82 | G25: 0.74448529 | H25: -32112 | I25: 93564
A26: M029 — Master of Science in Applied Computing | B26: 30 | C26: 30450 | D26: 19.5 | E26: 594688 | F26: No data | G26: No data | H26: No data | I26: No data
A27: M035 — Master of Science in Applied Statistics | B27: 30 | C27: 25350 | D27: 1.9 | E27: 47151 | F27: 13.04 | G27: 0.43469388 | H27: -26655 | I27: 20496
A28: M145 — Master of Science in Business Analytics | B28: 32 | C28: 32480 | D28: 12.1 | E28: 392683 | F28: 22.1 | G28: 0.69074675 | H28: -121439 | I28: 271245
A29: M191 — Master of Science in Civil Engineering | B29: 30 | C29: 30450 | D29: 20.5 | E29: 623007 | F29: 24.34 | G29: 0.81126437 | H29: -117584 | I29: 505423
A30: M260 — Master of Science in Criminal Justice | B30: 30 | C30: 21150 | D30: 18.6 | E30: 393390 | F30: 21.01 | G30: 0.70045872 | H30: -117837 | I30: 275553
A31: M264 — Master of Science in Cybersecurity Leadership | B31: 30 | C31: 30450 | D31: 21.4 | E31: 651325 | F31: No data | G31: No data | H31: No data | I31: No data
A32: M374 — Master of Science in Engineering Leadership and Management | B32: 30 | C32: 30450 | D32: 40 | E32: 1217695 | F32: 25.62 | G32: 0.85416667 | H32: -177581 | I32: 1040115
A33: M435 — Master of Science in Finance | B33: 32 | C33: 32480 | D33: 18.6 | E33: 604128 | F33: 24.76 | G33: 0.77373569 | H33: -136693 | I33: 467435
A34: M464 — Master of Science in Geospatial Technology | B34: 33 | C34: 33495 | D34: 4.6 | E34: 155752 | F34: 24.2 | G34: 0.73345102 | H34: -41515 | I34: 114236
A35: M527 — Master of Science in Industrial and Systems Engineering | B35: 30 | C35: 30450 | D35: 39.1 | E35: 1189377 | F35: 18.36 | G35: 0.61208791 | H35: -461374 | I35: 728003
A36: M746 — Master of Science in Natural Gas Engineering and Management | B36: 30 | C36: 30450 | D36: 17.7 | E36: 538052 | F36: 22.22 | G36: 0.74065041 | H36: -139543 | I36: 398508
A37: M861 — Master of Science in Supply Chain Management | B37: 32 | C37: 32480 | D37: 21.4 | E37: 694747 | F37: 26.39 | G37: 0.82457386 | H37: -121877 | I37: 572870
A38: M869 — Master of Science in Sustainability - Energy and Materials Mgmt | B38: 30 | C38: 30450 | D38: 15.8 | E38: 481414 | F38: 17.65 | G38: 0.58846154 | H38: -198121 | I38: 283294
A39: M867 — Master of Science in Sustainable Architecture | B39: 30 | C39: 30450 | D39: 6.5 | E39: 198230 | F39: 21.7 | G39: 0.72333333 | H39: -54843 | I39: 143386
A40: M844 — Master of Social Work | B40: 60 | C40: 38700 | D40: 111.6 | E40: 4318920 | F40: 45.6 | G40: 0.76003026 | H40: -1036410 | I40: 3282510
A41: 1237Q — Masters in Public Health | B41: 42 | C41: 24150 | D41: 14.9 | E41: 359352 | F41: No data | G41: No data | H41: No data | I41: No data
A42: M355 — Online LL.M. Energy and Natural Resources | B42: 24 | C42: 20270 | D42: 0.9 | E42: 18851 | F42: 13.67 | G42: 0.56944444 | H42: -8117 | I42: 10735
A43: M504 — Online LL.M. Healthcare Law | B43: 24 | C43: 20270 | D43: 0 | E43: 0 | F43: 12.44 | G43: 0.51851852 | H43: 0 | I43: 0
A44: M526 — Online LL.M. Indigenous Peoples Law | B44: 25 | C44: 21115 | D44: 0 | E44: 0 | F44: 16 | G44: 0.64 | H44: 0 | I44: 0
A45: M592 — Online LL.M. International Business | B45: 24 | C45: 20270 | D45: 0 | E45: 0 | F45: 13.5 | G45: 0.5625 | H45: 0 | I45: 0
A48: Tuition Owed, Pending Clearance — Summer 2026 (Informational only)
A49: From the Su26 Cognos Final Clearance List: 31 students across our 41 tracked programs met their degree requirements this term but have not had their degree posted because they owe tuition ('Will Graduate — Owes Tuition'). This is a count only -- the source list does not carry a dollar amount owed per student, so no revenue figure is estimated here. Not included in Revenue Loss, LTR, or any retention figure above or elsewhere in this workbook.
A51: Program | B51: Su26 Students Owing Tuition
A52: M844 — Master of Social Work | B52: 6
A53: M762 — Master of Arts in Organizational Leadership | B53: 3
A54: M503 — Master of Legal Studies - Healthcare Law | B54: 3
A55: M029 — Master of Science in Applied Computing | B55: 3
A56: M073 — Master of Arts in Arts Management | B56: 2
A57: M297 — Master of Econometrics | B57: 2
A58: M700 — Master of Arts in Museum Studies | B58: 2
A59: M494 — Master of Arts in Global Affairs | B59: 2
A60: M035 — Master of Science in Applied Statistics | B60: 2
A61: M859 — Master of Arts in Strategic Communication and Digital Strategy | B61: 1
A62: M374 — Master of Science in Engineering Leadership and Management | B62: 1
A63: M013 — Master of Accountancy | B63: 1
... A67: Total | B67: 31

Sheet FY Trend - New vs Continuing
A1: FY Trend — New Student % vs Continuing Student %, by fiscal year
A2: New Student % = Term-1→Term-3 survival for the class that first enrolled in that fiscal year (Method A's own definition, pooled by entry FY instead of pooled across all history). Continuing Student % = credit-hour-weighted retention of that same class beyond Term 3 (same 20% floor as Method A). FY runs July–June. Recent fiscal years' Continuing% rest on fewer observed terms than older ones — see the 'Terms Observed' row and the Read Me note before reading a rising trend as pure improvement. FY2026 is the latest complete fiscal year. Yellow = thin sample (fewer than 30 eligible students that FY). Orange = a later term's headcount exceeded its own Term-3 base (usually a stop-out student re-enrolling) — mathematically valid, just something a small per-FY cohort can show that a full-history pool essentially never does; not capped, so the number is never silently altered.
A4: Portfolio-Wide (All 41 Graduate Programs)
A5: Metric | B5: FY2021 | C5: FY2022 | D5: FY2023 | E5: FY2024 | F5: FY2025 | G5: FY2026
A6: New Student % | B6: 0.73453608 | C6: 0.68263473 | D6: 0.69556452 | E6: 0.69565217 | F6: 0.72041763 | G6: 0.72739917
A7: Continuing Student % | B7: 0.6742008 | C7: 0.64029235 | D7: 0.70159421 | E7: 0.63942098 | F7: 0.7652169 | G7: 0.80218629
A8: Terms Observed (Continuing%) | B8: 5 | C8: 6 | D8: 5 | E8: 6 | F8: 4 | G8: 2
A9: Eligible Students at Term 1 (n) | B9: 1164 | C9: 1503 | D9: 1488 | E9: 1840 | F9: 1724 | G9: 1438
A12: Per-Program Detail
A13: Program | B13: FY2021 | D13: FY2022 | F13: FY2023 | H13: FY2024 | J13: FY2025 | L13: FY2026
B14: New% | C14: Cont% | D14: New% | E14: Cont% | F14: New% | G14: Cont% | H14: New% | I14: Cont% | J14: New% | K14: Cont% | L14: New% | M14: Cont%
A15: 1550C — Certificate in Population Health | B15: No data | C15: No data | D15: No data | E15: No data | F15: No data | G15: No data | H15: No data | I15: No data | J15: No data | K15: No data | L15: No data | M15: No data
A16: D318 — Ed.D. in Education Administration | B16: No data | C16: No data | D16: No data | E16: No data | F16: No data | G16: No data | H16: 0.90625 | I16: 0.97111595 | J16: 0.90666667 | K16: 0.97544005 | L16: No data | M16: No data
A17: M366 — Executive MBA in Energy | B17: 0.97368421 | C17: 0.7380117 | D17: 0.96551724 | E17: 0.97625891 | F17: 0.96666667 | G17: 1 | H17: 1 | I17: 1 | J17: 0.94444444 | K17: 1 | L17: 0.9 | M17: 1
A18: 1231EX — Executive Masters in Health Administration | B18: No data | C18: No data | D18: No data | E18: No data | F18: No data | G18: No data | H18: No data | I18: No data | J18: No data | K18: No data | L18: No data | M18: No data
A19: M013 — Master of Accountancy | B19: 0.72619048 | C19: 0.64180948 | D19: 0.734375 | E19: 0.6397158 | F19: 0.58064516 | G19: 0.60347397 | H19: 0.6984127 | I19: 0.57360777 | J19: 0.81355932 | K19: 0.76853104 | L19: 0.59615385 | M19: 0.77061961
A20: M075 — Master of Arts in Art and Technology | B20: No data | C20: No data | D20: 0.64 | E20: 0.952241 | F20: 0.79166667 | G20: 0.91858493 | H20: 0.64583333 | I20: 0.96984925 | J20: 0.68888889 | K20: 0.78746977 | L20: 0.63636364 | M20: 0.78723404
A21: M073 — Master of Arts in Arts Management | B21: No data | C21: No data | D21: No data | E21: No data | F21: 1 | G21: 0.69964664 | H21: 0.75342466 | I21: 1 | J21: 0.84745763 | K21: 0.67172522 | L21: 0.76363636 | M21: 0.77150436
A22: M494 — Master of Arts in Global Affairs | B22: 0.48387097 | C22: 0.84204921 | D22: 0.48780488 | E22: 0.94468286 | F22: 0.52777778 | G22: 0.80179475 | H22: 0.6 | I22: 0.78999518 | J22: 0.54320988 | K22: 0.77356805 | L22: 0.5 | M22: 0.91357309
A23: M700 — Master of Arts in Museum Studies | B23: 0.62222222 | C23: 0.8455999 | D23: 0.53684211 | E23: 0.83736622 | F23: 0.71751412 | G23: 0.77942588 | H23: 0.64606742 | I23: 0.92400999 | J23: 0.63586957 | K23: 0.89614484 | L23: 0.6036036 | M23: 0.82551595
A24: M762 — Master of Arts in Organizational Leadership | B24: 0.5462963 | C24: 0.67587265 | D24: 0.55555556 | E24: 0.6837701 | F24: 0.53636364 | G24: 0.76156251 | H24: 0.60784314 | I24: 0.76252151 | J24: 0.55339806 | K24: 0.8499022 | L24: 0.59459459 | M24: 0.74278283
A25: M859 — Master of Arts in Strategic Communication and Digital Strategy | B25: 0.90322581 | C25: 0.99487253 | D25: 0.75342466 | E25: 0.81636267 | F25: 0.84848485 | G25: 0.99437419 | H25: 0.75362319 | I25: 0.81343757 | J25: 0.77941176 | K25: 0.98768405 | L25: 0.83783784 | M25: 0.75098814
A26: M202 — Master of Clinical Mental Health Counseling | B26: No data | C26: No data | D26: 0.7184466 | E26: 0.81094262 | F26: 0.82022472 | G26: 0.92772782 | H26: 0.89393939 | I26: 0.93950781 | J26: 0.89189189 | K26: 0.84621014 | L26: 0.78481013 | M26: 0.74663073
A27: M246 — Master of Construction Business | B27: No data | C27: No data | D27: 0.87804878 | E27: 0.6770029 | F27: 0.875 | G27: 0.69565217 | H27: 0.85294118 | I27: 0.61794244 | J27: 0.97058824 | K27: 0.80869915 | L27: 0.75862069 | M27: 0.78563152
A28: M297 — Master of Econometrics | B28: No data | C28: No data | D28: No data | E28: No data | F28: No data | G28: No data | H28: No data | I28: No data | J28: 0.64705882 | K28: 0.88201161 | L28: 0.59375 | M28: 0.8988764
A29: M383 — Master of Entrepreneurship & Innovation | B29: No data | C29: No data | D29: No data | E29: No data | F29: No data | G29: No data | H29: No data | I29: No data | J29: 0.54545455 | K29: 1 | L29: 0.81818182 | M29: 1
A30: M518 — Master of Environmental Science: Hydrology and Water Security | B30: 0.76767677 | C30: 0.96709554 | D30: 0.66666667 | E30: 0.78280337 | F30: 0.68085106 | G30: 0.73294291 | H30: 0.75 | I30: 0.71624566 | J30: 0.70909091 | K30: 0.86147108 | L30: 0.78947368 | M30: 0.87023335
A31: M368 — Master of Legal Studies - Energy | B31: 0.9 | C31: 0.94594595 | D31: 0.64 | E31: 0.93757576 | F31: 0.61538462 | G31: 1 | H31: 0.80952381 | I31: 1.0300373 | J31: 0.76470588 | K31: 1 | L31: 0.8125 | M31: 0.80861244
A32: M636 — Master of Legal Studies - General | B32: No data | C32: No data | D32: No data | E32: No data | F32: No data | G32: No data | H32: No data | I32: No data | J32: 1 | K32: 1 | L32: 0.25 | M32: 1
A33: M503 — Master of Legal Studies - Healthcare Law | B33: 0.72727273 | C33: 1.0130042 | D33: 0.78571429 | E33: 0.98114627 | F33: 0.69642857 | G33: 0.83314469 | H33: 0.67567568 | I33: 0.83213352 | J33: 0.72222222 | K33: 0.81741279 | L33: 0.75555556 | M33: 0.81439321
A34: M522 — Master of Legal Studies - Indigenous Peoples Law | B34: 0.73291925 | C34: 0.7908798 | D34: 0.62732919 | E34: 0.78915206 | F34: 0.64957265 | G34: 0.75647762 | H34: 0.65322581 | I34: 0.7864861 | J34: 0.70786517 | K34: 0.83330625 | L34: 0.70175439 | M34: 0.77588212
A35: M589 — Master of Legal Studies - International Business | B35: 0.75 | C35: 0.86049544 | D35: 0.6875 | E35: 0.95613048 | F35: 0.9 | G35: 0.9467028 | H35: 0.5 | I35: 0.97358491 | J35: No data | K35: No data | L35: 0.71428571 | M35: 0.90032154
A36: M029 — Master of Science in Applied Computing | B36: No data | C36: No data | D36: No data | E36: No data | F36: No data | G36: No data | H36: No data | I36: No data | J36: 0.79310345 | K36: 0.57719054 | L36: 0.77777778 | M36: 0.76923077
A37: M035 — Master of Science in Applied Statistics | B37: No data | C37: No data | D37: No data | E37: No data | F37: No data | G37: No data | H37: 0.44 | I37: 0.69007537 | J37: 0.68085106 | K37: 0.95667856 | L37: 0.7 | M37: 0.95128552
A38: M145 — Master of Science in Business Analytics | B38: No data | C38: No data | D38: No data | E38: No data | F38: 0.69444444 | G38: 0.79665347 | H38: 0.53658537 | I38: 1.1171191 | J38: 0.75 | K38: 0.73116362 | L38: 0.85 | M38: 0.85331633
A39: M191 — Master of Science in Civil Engineering | B39: 0.88372093 | C39: 0.73201292 | D39: 0.86111111 | E39: 0.75142722 | F39: 0.83333333 | G39: 0.70831523 | H39: 0.75 | I39: 0.77695482 | J39: 0.75 | K39: 0.82496593 | L39: 0.85365854 | M39: 0.76374077
A40: M260 — Master of Science in Criminal Justice | B40: 0.61904762 | C40: 0.79828996 | D40: 0.50769231 | E40: 0.74553824 | F40: 0.52777778 | G40: 0.77087909 | H40: 0.62857143 | I40: 0.65273345 | J40: 0.57446809 | K40: 0.99368045 | L40: 0.68421053 | M40: 0.87765957
A41: M264 — Master of Science in Cybersecurity Leadership | B41: No data | C41: No data | D41: No data | E41: No data | F41: No data | G41: No data | H41: No data | I41: No data | J41: No data | K41: No data | L41: 0.85714286 | M41: 1
A42: M374 — Master of Science in Engineering Leadership and Management | B42: No data | C42: No data | D42: No data | E42: No data | F42: No data | G42: No data | H42: 0.79166667 | I42: 0.7860262 | J42: 0.84375 | K42: 0.56291391 | L42: 0.875 | M42: 0.6816574
A43: M435 — Master of Science in Finance | B43: 0.78313253 | C43: 0.7826389 | D43: 0.7721519 | E43: 0.80615928 | F43: 0.60344828 | G43: 0.85654596 | H43: 0.7804878 | I43: 0.95352915 | J43: 0.62962963 | K43: 0.79212612 | L43: 0.75 | M43: 0.79829325
A44: M464 — Master of Science in Geospatial Technology | B44: 0.76923077 | C44: 0.71536117 | D44: 0.7037037 | E44: 0.85697831 | F44: 0.82352941 | G44: 0.93913043 | H44: 0.45 | I44: 0.87301587 | J44: 0.58333333 | K44: 0.94736842 | L44: 0.76923077 | M44: 0.85171103
A45: M527 — Master of Science in Industrial and Systems Engineering | B45: No data | C45: No data | D45: 0.47619048 | E45: 0.87910328 | F45: 0.52173913 | G45: 0.68215476 | H45: 0.68085106 | I45: 0.74457781 | J45: 0.59259259 | K45: 0.85286326 | L45: 0.60344828 | M45: 0.8190675
A46: M746 — Master of Science in Natural Gas Engineering and Management | B46: 0.66666667 | C46: 0.93541203 | D46: 0.625 | E46: 0.59052248 | F46: 0.6 | G46: 0.77555749 | H46: 0.68571429 | I46: 0.85843102 | J46: 0.5 | K46: 0.9097037 | L46: 0.73684211 | M46: 0.82084691
A47: M861 — Master of Science in Supply Chain Management | B47: No data | C47: No data | D47: No data | E47: No data | F47: 0.80645161 | G47: 0.83905913 | H47: 0.81034483 | I47: 0.97875 | J47: 0.67391304 | K47: 1.0316651 | L47: 0.81632653 | M47: 0.84589041
A48: M869 — Master of Science in Sustainability - Energy and Materials Mgmt | B48: No data | C48: No data | D48: No data | E48: No data | F48: No data | G48: No data | H48: 0.61538462 | I48: 0.91496063 | J48: 0.75925926 | K48: 0.94291116 | L48: 0.5625 | M48: 0.83687943
A49: M867 — Master of Science in Sustainable Architecture | B49: No data | C49: No data | D49: No data | E49: No data | F49: No data | G49: No data | H49: 0.75 | I49: 0.97104377 | J49: 0.65517241 | K49: 0.83685477 | L49: 0.73333333 | M49: 0.91709845
A50: M844 — Master of Social Work | B50: 0.80722892 | C50: 0.83921512 | D50: 0.74678112 | E50: 0.75635235 | F50: 0.78285714 | G50: 0.78908709 | H50: 0.76142132 | I50: 0.90823612 | J50: 0.85549133 | K50: 0.84786735 | L50: 0.85483871 | M50: 0.79442594
A51: 1237Q — Masters in Public Health | B51: No data | C51: No data | D51: No data | E51: No data | F51: No data | G51: No data | H51: No data | I51: No data | J51: No data | K51: No data | L51: No data | M51: No data
A52: M355 — Online LL.M. Energy and Natural Resources | B52: No data | C52: No data | D52: 0.33333333 | E52: 1 | F52: 0 | G52: No data | H52: 0.6 | I52: 1 | J52: 0.75 | K52: 1 | L52: 0.5 | M52: 1
A53: M504 — Online LL.M. Healthcare Law | B53: 1 | C53: 1 | D53: 0 | E53: No data | F53: 0.5 | G53: 1 | H53: 0.25 | I53: 1 | J53: 1 | K53: 1 | L53: 0.33333333 | M53: 1
A54: M526 — Online LL.M. Indigenous Peoples Law | B54: 0.16666667 | C54: 1 | D54: 1 | E54: 1 | F54: 0.14285714 | G54: 1.3684211 | H54: 0.75 | I54: 0.77777778 | J54: 0.55555556 | K54: 0.84 | L54: 1 | M54: 1
A55: M592 — Online LL.M. International Business | B55: No data | C55: No data | D55: No data | E55: No data | F55: 0 | G55: No data | H55: 1 | I55: 1 | J55: No data | K55: No data | L55: 0.25 | M55: 1.3793103

Sheet FY Outlook - 3Yr vs FY27
A1: FY Outlook — 3-Year Rolling vs. FY2026 vs. FY2027 (Projected)
A2: 3-Yr Rolling Avg = average of FY2024-FY2026. FY2026 = latest complete fiscal year (observed). FY2027 = straight-line (least-squares) extrapolation of each series' fiscal-year history, clipped to 0-100%, shown only where at least 3 fiscal years of data exist — otherwise 'Insufficient trend data'. FY2027 is a projection, not an observed result (only Fall 2026 of its three terms exists so far) — shown shaded and italicized, the same convention used for every other projected figure in this workbook. Use it for goal-setting discussion, not as a forecast commitment. See the Read Me for the Continuing% maturity-artifact caution before setting a target off its trend.
A4: Portfolio-Wide (All 41 Graduate Programs)
A5: Metric | B5: 3-Yr Rolling Avg (FY24-26) | C5: FY2026 (Latest Complete) | D5: FY2027 (Projected)
A6: New Student % | B6: 0.71448966 | C6: 0.72739917 | D6: 0.71714256
A7: Continuing Student % | B7: 0.73560806 | C7: 0.80218629 | D7: 0.79907138
A10: Per-Program Detail
A11: Program | B11: 3-Yr Rolling Avg (FY24-26) | D11: FY2026 (Latest Complete) | F11: FY2027 (Projected)
B12: New% | C12: Cont% | D12: New% | E12: Cont% | F12: New% | G12: Cont%
A13: 1550C — Certificate in Population Health | B13: No data | C13: No data | D13: No data | E13: No data | F13: Insufficient data | G13: Insufficient data
A14: D318 — Ed.D. in Education Administration | B14: 0.90645833 | C14: 0.973278 | D14: No data | E14: No data | F14: Insufficient data | G14: Insufficient data
A15: M366 — Executive MBA in Energy | B15: 0.94814815 | C15: 1 | D15: 0.9 | E15: 1 | F15: 0.91855482 | G15: 1
A16: 1231EX — Executive Masters in Health Administration | B16: No data | C16: No data | D16: No data | E16: No data | F16: Insufficient data | G16: Insufficient data
A17: M013 — Master of Accountancy | B17: 0.70270862 | C17: 0.70425281 | D17: 0.59615385 | E17: 0.77061961 | F17: 0.66206982 | G17: 0.76635597
A18: M075 — Master of Arts in Art and Technology | B18: 0.65702862 | C18: 0.84818435 | D18: 0.63636364 | E18: 0.78723404 | F18: 0.64753535 | G18: 0.74473708
A19: M073 — Master of Arts in Arts Management | B19: 0.78817288 | C19: 0.81440986 | D19: 0.76363636 | E19: 0.77150436 | F19: 0.68736518 | G19: 0.75754365
A20: M494 — Master of Arts in Global Affairs | B20: 0.54773663 | C20: 0.8257121 | D20: 0.5 | E20: 0.91357309 | F20: 0.55568549 | G20: 0.82752472
A21: M700 — Master of Arts in Museum Studies | B21: 0.62851353 | C21: 0.88189026 | D21: 0.6036036 | E21: 0.82551595 | F21: 0.6402741 | G21: 0.87339382
A22: M762 — Master of Arts in Organizational Leadership | B22: 0.5852786 | C22: 0.78506885 | D22: 0.59459459 | E22: 0.74278283 | F22: 0.59632506 | G22: 0.82945926
A23: M859 — Master of Arts in Strategic Communication and Digital Strategy | B23: 0.79029093 | C23: 0.85070325 | D23: 0.83783784 | E23: 0.75098814 | F23: 0.778284 | G23: 0.80431375
A24: M202 — Master of Clinical Mental Health Counseling | B24: 0.85688047 | C24: 0.84411623 | D24: 0.78481013 | E24: 0.74663073 | F24: 0.88318081 | G24: 0.79116139
A25: M246 — Master of Construction Business | B25: 0.8607167 | C25: 0.73742437 | D25: 0.75862069 | E25: 0.78563152 | F25: 0.82405939 | G25: 0.8160769
A26: M297 — Master of Econometrics | B26: 0.62040441 | C26: 0.890444 | D26: 0.59375 | E26: 0.8988764 | F26: Insufficient data | G26: Insufficient data
A27: M383 — Master of Entrepreneurship & Innovation | B27: 0.68181818 | C27: 1 | D27: 0.81818182 | E27: 1 | F27: Insufficient data | G27: Insufficient data
A28: M518 — Master of Environmental Science: Hydrology and Water Security | B28: 0.74952153 | C28: 0.81598336 | D28: 0.78947368 | E28: 0.87023335 | F28: 0.75783381 | G28: 0.79529815
A29: M368 — Master of Legal Studies - Energy | B29: 0.79557656 | C29: 0.94621657 | D29: 0.8125 | E29: 0.80861244 | F29: 0.77009474 | G29: 0.90675948
A30: M636 — Master of Legal Studies - General | B30: 0.625 | C30: 1 | D30: 0.25 | E30: 1 | F30: Insufficient data | G30: Insufficient data
A31: M503 — Master of Legal Studies - Healthcare Law | B31: 0.71781782 | C31: 0.82131318 | D31: 0.75555556 | E31: 0.81439321 | F31: 0.72016335 | G31: 0.73334581
A32: M522 — Master of Legal Studies - Indigenous Peoples Law | B32: 0.68761512 | C32: 0.79855816 | D32: 0.70175439 | E32: 0.77588212 | F32: 0.68772142 | G32: 0.79744559
A33: M589 — Master of Legal Studies - International Business | B33: 0.60714286 | C33: 0.93695322 | D33: 0.71428571 | E33: 0.90032154 | F33: 0.64488417 | G33: 0.94541517
A34: M029 — Master of Science in Applied Computing | B34: 0.78544061 | C34: 0.67321066 | D34: 0.77777778 | E34: 0.76923077 | F34: Insufficient data | G34: Insufficient data
A35: M035 — Master of Science in Applied Statistics | B35: 0.60695035 | C35: 0.86601315 | D35: 0.7 | E35: 0.95128552 | F35: 0.86695035 | G35: 1
A36: M145 — Master of Science in Business Analytics | B36: 0.71219512 | C36: 0.90053301 | D36: 0.85 | E36: 0.85331633 | F36: 0.87777778 | G36: 0.8205714
A37: M191 — Master of Science in Civil Engineering | B37: 0.78455285 | C37: 0.78855384 | D37: 0.85365854 | E37: 0.76374077 | F37: 0.76527279 | G37: 0.80435898
A38: M260 — Master of Science in Criminal Justice | B38: 0.62908335 | C38: 0.84135782 | D38: 0.68421053 | E38: 0.87765957 | F38: 0.65298818 | G38: 0.90877637
A39: M264 — Master of Science in Cybersecurity Leadership | B39: 0.85714286 | C39: 1 | D39: 0.85714286 | E39: 1 | F39: Insufficient data | G39: Insufficient data
A40: M374 — Master of Science in Engineering Leadership and Management | B40: 0.83680556 | C40: 0.67686584 | D40: 0.875 | E40: 0.6816574 | F40: 0.92013889 | G40: 0.57249704
A41: M435 — Master of Science in Finance | B41: 0.72003914 | C41: 0.84798284 | D41: 0.75 | E41: 0.79829325 | F41: 0.67818936 | G41: 0.84486433
A42: M464 — Master of Science in Geospatial Technology | B42: 0.6008547 | C42: 0.89069844 | D42: 0.76923077 | E42: 0.85171103 | F42: 0.60970728 | G42: 0.95260804
A43: M527 — Master of Science in Industrial and Systems Engineering | B43: 0.62563064 | C43: 0.80550285 | D43: 0.60344828 | E43: 0.8190675 | F43: 0.67257503 | G43: 0.8107444
A44: M746 — Master of Science in Natural Gas Engineering and Management | B44: 0.64085213 | C44: 0.86299388 | D44: 0.73684211 | E44: 0.82084691 | F44: 0.64186299 | G44: 0.8618381
A45: M861 — Master of Science in Supply Chain Management | B45: 0.76686147 | C45: 0.95210184 | D45: 0.81632653 | E45: 0.84589041 | F45: 0.75005725 | G45: 0.9421934
A46: M869 — Master of Science in Sustainability - Energy and Materials Mgmt | B46: 0.64571462 | C46: 0.89825041 | D46: 0.5625 | E46: 0.83687943 | F46: 0.59283001 | G46: 0.82016921
A47: M867 — Master of Science in Sustainable Architecture | B47: 0.71283525 | C47: 0.90833233 | D47: 0.73333333 | E47: 0.91709845 | F47: 0.69616858 | G47: 0.854387
A48: M844 — Master of Social Work | B48: 0.82391712 | C48: 0.85017647 | D48: 0.85483871 | E48: 0.79442594 | F48: 0.8557108 | G48: 0.83950548
A49: 1237Q — Masters in Public Health | B49: No data | C49: No data | D49: No data | E49: No data | F49: Insufficient data | G49: Insufficient data
A50: M355 — Online LL.M. Energy and Natural Resources | B50: 0.61666667 | C50: 1 | D50: 0.5 | E50: 1 | F50: 0.76166667 | G50: 1
A51: M504 — Online LL.M. Healthcare Law | B51: 0.52777778 | C51: 1 | D51: 0.33333333 | E51: 1 | F51: 0.45555556 | G51: 1
A52: M526 — Online LL.M. Indigenous Peoples Law | B52: 0.76851852 | C52: 0.87259259 | D52: 1 | E52: 1 | F52: 0.94656085 | G52: 0.89063548
A53: M592 — Online LL.M. International Business | B53: 0.625 | C53: 1.1896552 | D53: 0.25 | E53: 1.3793103 | F53: 0.46428571 | G53: Insufficient data

Sheet Margin View (Trial, Approx.)
A1: TRIAL, APPROXIMATE — Margin-Adjusted LTR vs. CAC
A2: Why this sheet exists: 'CAC & LTR Data (Trial)' and the matrix compare GROSS tuition revenue to paid-media spend — a real number, but not the margin-based LTV:CAC the 3:1 benchmark is built for. This sheet applies a rough cost-to-deliver proxy so you can see how much of that gross picture survives on a margin basis. Proxy: FY25 program-level (Dept OPEX + Elsmere/EAB) expense ÷ FY25 program revenue, from the Financial Viability file's own 'P&L - Oct 2025' sheet (matched to our 41 programs by name — 28 of 41 matched; the rest are other Norman -OL programs outside this workbook's scope, listed below). That expense ratio is applied to each program's per-student Direct-method LTR to get an approximate margin LTR/student.
A3: Read this as a FLOOR, not a final number, in both directions: (1) Dept OPEX is an average cost that already includes fixed overhead the program is currently covering — the incremental cost of one more student is almost always lower than this average, so this proxy UNDERSTATES true marginal margin. (2) CAC itself is still paid-media spend only (see the CAC-scope check below) — a fully-loaded acquisition cost would push CAC up and every multiple on this sheet down further. Neither has been reviewed by Finance or Marketing Ops — treat every number below as directional, pending that confirmation, not as what goes in front of the Board.
A5: Program | B5: CAC ($/student, media-only) | C5: Gross LTR /Student | D5: Gross Revenue Multiple | E5: FY25 Program Revenue | F5: FY25 Program Cost (proxy) | G5: Approx. Margin % | H5: Approx. Margin LTR/Student | I5: Approx. Margin Multiple
A6: M366 — Executive MBA in Energy | B6: 9652 | C6: 85313 | D6: 8.8 | E6: 5000062 | F6: 2464238 | G6: 0.50715851 | H6: 43267 | I6: 4.5
A7: M035 — Master of Science in Applied Statistics | B7: 562 | C7: 11019 | D7: 19.6 | E7: 846854 | F7: 663666 | G7: 0.21631592 | H7: 2384 | I7: 4.2
A8: M073 — Master of Arts in Arts Management | B8: 3492 | C8: 25235 | D8: 7.2 | E8: 1473457 | F8: 650509 | G8: 0.55851511 | H8: 14094 | I8: 4
A9: M145 — Master of Science in Business Analytics | B9: 3072 | C9: 22435 | D9: 7.3 | E9: 1823464 | F9: 1107355 | G9: 0.39271902 | H9: 8811 | I9: 2.9
A10: M494 — Master of Arts in Global Affairs | B10: 1587 | C10: 19353 | D10: 12.2 | E10: 1351051 | F10: 1036291 | G10: 0.23297418 | H10: 4509 | I10: 2.8
A11: M374 — Master of Science in Engineering Leadership and Management | B11: 4750 | C11: 26009 | D11: 5.5 | E11: 1471590 | F11: 727153 | G11: 0.50587256 | H11: 13157 | I11: 2.8
A12: M700 — Master of Arts in Museum Studies | B12: 1786 | C12: 20032 | D12: 11.2 | E12: 2115540 | F12: 1655175 | G12: 0.21761111 | H12: 4359 | I12: 2.4
A13: M527 — Master of Science in Industrial and Systems Engineering | B13: 3598 | C13: 18638 | D13: 5.2 | E13: 1039529 | F13: 572756 | G13: 0.44902355 | H13: 8369 | I13: 2.3
A14: M435 — Master of Science in Finance | B14: 1510 | C14: 25131 | D14: 16.6 | E14: 1167805 | F14: 1026167 | G14: 0.12128566 | H14: 3048 | I14: 2
A15: M844 — Master of Social Work | B15: 1766 | C15: 29413 | D15: 16.7 | E15: 5065376 | F15: 4458937 | G15: 0.11972241 | H15: 3521 | I15: 2
A16: M464 — Master of Science in Geospatial Technology | B16: 2694 | C16: 24567 | D16: 9.1 | E16: 463801 | F16: 370447 | G16: 0.20128029 | H16: 4945 | I16: 1.8
A17: M762 — Master of Arts in Organizational Leadership | B17: 3133 | C17: 17651 | D17: 5.6 | E17: 1872608 | F17: 1394167 | G17: 0.25549448 | H17: 4510 | I17: 1.4
... A29: M013 — Master of Accountancy | B29: 3073 | C29: 25431 | D29: 8.3 | E29: 1537191 | F29: 1604877 | G29: -0.044032264 | H29: -1120 | I29: -0.4
A30: D318 — Ed.D. in Education Administration | B30: 1571 | C30: No data | D30: — | E30: 876975 | F30: 406483 | G30: 0.5364942 | H30: No CAC/LTR | I30: No CAC/LTR
A31: M029 — Master of Science in Applied Computing | B31: 2078 | C31: No data | D31: — | E31: 528945 | F31: 770900 | G31: -0.45742941 | H31: No CAC/LTR | I31: No CAC/LTR
A32: M297 — Master of Econometrics | B32: 1140 | C32: No data | D32: — | E32: 107976 | F32: 647153 | G32: -4.9934893 | H32: No CAC/LTR | I32: No CAC/LTR
A33: M383 — Master of Entrepreneurship & Innovation | B33: 5849 | C33: No data | D33: — | E33: 261018 | F33: 649190 | G33: -1.4871465 | H33: No CAC/LTR | I33: No CAC/LTR
A35: Of 24 programs with a full margin read: 2 show a NEGATIVE approximate margin (FY25 program cost exceeded FY25 program revenue on this proxy) and 10 fall below a 1:1 margin multiple — several of these look comfortably 'Financial Health' on the gross view. Red text flags both.
A37: Programs in the P&L file NOT matched to one of our 41 (other Norman -OL graduate programs outside this workbook's scope, or too uncertain a name match to assert): Computer Science, Data Science, EACS, EMAD, Health & Human Services Administration, Human Relations, Instructional Leadership, Integrative Studies, Native American Studies, Online MBA, Prevention Science.
A39: CAC-scope check: FY26 Media spend vs. FY25 P&L 'Marketing' line, same program
A40: Two different files, two different answers for 'what did this program spend to market itself.' Until Finance/Marketing Ops confirms which scope is right (or that both are legitimately partial views of a larger total), neither CAC figure in this workbook should be called fully-loaded.
A41: Program | B41: FY26 Media Spend (Follow the Lead) | C41: FY25 P&L 'Marketing' Line | D41: Gap (x)
A42: M202 — Master of Clinical Mental Health Counseling | B42: 295485 | C42: 1763 | D42: 167.6
A43: M191 — Master of Science in Civil Engineering | B43: 375181 | C43: 14343 | D43: 26.2
A44: M246 — Master of Construction Business | B44: 287274 | C44: 15847 | D44: 18.1
A45: M260 — Master of Science in Criminal Justice | B45: 273967 | C45: 16877 | D45: 16.2
A46: M374 — Master of Science in Engineering Leadership and Management | B46: 265988 | C46: 18264 | D46: 14.6
A47: M518 — Master of Environmental Science: Hydrology and Water Security | B47: 251610 | C47: 17510 | D47: 14.4
A48: M700 — Master of Arts in Museum Studies | B48: 237540 | C48: 16996 | D48: 14
A49: M762 — Master of Arts in Organizational Leadership | B49: 300760 | C49: 22125 | D49: 13.6
A50: M746 — Master of Science in Natural Gas Engineering and Management | B50: 144540 | C50: 10775 | D50: 13.4
A51: M435 — Master of Science in Finance | B51: 86072 | C51: 7898 | D51: 10.9
A52: M073 — Master of Arts in Arts Management | B52: 192074 | C52: 17774 | D52: 10.8
A53: M844 — Master of Social Work | B53: 331986 | C53: 31402 | D53: 10.6
... A68: M035 — Master of Science in Applied Statistics | B68: 19676 | C68: 16783 | D68: 1.2
A70: Median gap across 27 matched programs: 10.5x (Media spend higher than the P&L 'Marketing' line).
A72: (chart data)
A73: Code | B73: Gross Revenue Multiple | C73: Approx. Margin Multiple
A74: M366 | B74: 8.84 | C74: 4.48
A75: M035 | B75: 19.6 | C75: 4.24
A76: M073 | B76: 7.23 | C76: 4.04
A77: M145 | B77: 7.3 | C77: 2.87
A78: M494 | B78: 12.19 | C78: 2.84
A79: M374 | B79: 5.48 | C79: 2.77
A80: M700 | B80: 11.22 | C80: 2.44
A81: M527 | B81: 5.18 | C81: 2.33
A82: M435 | B82: 16.64 | C82: 2.02
A83: M844 | B83: 16.66 | C83: 1.99
A84: M464 | B84: 9.12 | C84: 1.84
A85: M762 | B85: 5.63 | C85: 1.44
... A97: M013 | B97: 8.28 | C97: -0.36

Sheet FY Trend - Matched (Trial)
A1: TRIAL — FY Trend, Maturity-Matched (Continuing% Reality Check)
A2: Why this sheet exists: on 'FY Trend - New vs Continuing,' each fiscal year's Continuing% uses however many terms have been observed so far for that year's entering class (disclosed there via the 'Terms Observed' row) -- so FY2026 (2 terms observed) is measured much earlier in its lifecycle than FY2021 (5 terms observed), and retention mechanically declines with more terms observed. That makes the rising trend shown there partly a maturity artifact, not pure improvement. This sheet re-measures every fiscal year at the SAME number of terms elapsed so the comparison is apples-to-apples. New% is not affected by any of this -- it is always Term1->Term3 for every FY already.
A3: Two matched cuts, because one horizon can't answer both questions. Cut A matches all 6 fiscal years at 4 terms elapsed -- the only depth the brand-new FY2026 cohort has reached -- to test whether FY2026's headline number is provably better than history this early (it isn't: every FY looks ~98-100% this early, because almost no decay has had time to happen for anyone yet). Cut B drops FY2026 (too immature) and matches FY2021-FY2025 at 7 terms elapsed instead, for a more informative read on whether the underlying multi-year trend is real.
A5: Portfolio-Wide Continuing% — Original vs. Matched
A6: Fiscal Year | B6: Original (as observed so far) | C6: Cut A (matched @ 4 terms, all 6 FYs) | D6: Cut B (matched @ 7 terms, FY21-25 only)
A7: FY2021 | B7: 0.6742008 | C7: 1.0005928 | D7: 0.6742008
A8: FY2022 | B8: 0.64029235 | C8: 0.98614901 | D8: 0.70923064
A9: FY2023 | B9: 0.70159421 | C9: 0.98427802 | D9: 0.70159421
A10: FY2024 | B10: 0.63942098 | C10: 0.99728791 | D10: 0.71308593
A11: FY2025 | B11: 0.7652169 | C11: 0.981218 | D11: 0.7652169
A12: FY2026 | B12: 0.80218629 | C12: 0.80218629
A14: Gray cell = FY2026 hasn't reached 7 terms elapsed yet, so it can't be included in Cut B (shown as a gap in the chart below, not a zero).
A15: Bottom line: FY2026's standalone 80.2% cannot yet be shown to beat history -- at the same very early point (4 terms in), every fiscal year in this book looks like ~98-100%, since almost none of them have had time to decay yet either. But the underlying FY2021-FY2025 trend DOES hold up on an apples-to-apples 7-term view -- 67.4% -> 70.9% -> 70.2% -> 71.3% -> 76.5% -- a real, not purely mechanical, improvement across those five years. FY2026 will need another 2-3 terms of data before we can say whether it continues that climb or settles back toward the FY2021-2024 range.
A41: Per-Program Detail — Cut B Continuing% (matched @ 7 terms, FY2021-FY2025 only)
A42: Same matched-maturity logic applied per program, so a program's own year-over-year comparison is fair too. FY2026 omitted here (not mature enough at any program to include in Cut B).
A43: Program | B43: FY2021 | C43: FY2022 | D43: FY2023 | E43: FY2024 | F43: FY2025
A44: 1231EX — Executive Masters in Health Administration | B44: No data | C44: No data | D44: No data | E44: No data | F44: No data
A45: 1237Q — Masters in Public Health | B45: No data | C45: No data | D45: No data | E45: No data | F45: No data
A46: 1550C — Certificate in Population Health | B46: No data | C46: No data | D46: No data | E46: No data | F46: No data
A47: D318 — Ed.D. in Education Administration | B47: No data | C47: No data | D47: No data | E47: 0.97921706 | F47: 0.97544005
A48: M013 — Master of Accountancy | B48: 0.70098458 | C48: 0.75331001 | D48: 0.66796666 | E48: 0.63990217 | F48: 0.76853104
A49: M029 — Master of Science in Applied Computing | B49: No data | C49: No data | D49: No data | E49: No data | F49: 0.57719054
A50: M035 — Master of Science in Applied Statistics | B50: No data | C50: No data | D50: No data | E50: 0.69007537 | F50: 0.95667856
A51: M073 — Master of Arts in Arts Management | B51: No data | C51: No data | D51: 0.69964664 | E51: 1 | F51: 0.67172522
A52: M075 — Master of Arts in Art and Technology | B52: No data | C52: 0.952241 | D52: 0.91858493 | E52: 0.96984925 | F52: 0.78746977
A53: M145 — Master of Science in Business Analytics | B53: No data | C53: No data | D53: 0.79665347 | E53: 1.1171191 | F53: 0.73116362
A54: M191 — Master of Science in Civil Engineering | B54: 0.73201292 | C54: 0.75142722 | D54: 0.70831523 | E54: 0.77695482 | F54: 0.82496593
A55: M202 — Master of Clinical Mental Health Counseling | B55: No data | C55: 0.89240863 | D55: 0.93585477 | E55: 0.95152378 | F55: 0.84621014
A56: M246 — Master of Construction Business | B56: No data | C56: 0.6770029 | D56: 0.69565217 | E56: 0.61794244 | F56: 0.80869915
A57: M260 — Master of Science in Criminal Justice | B57: 0.92629322 | C57: 0.83002485 | D57: 0.77087909 | E57: 0.65273345 | F57: 0.99368045
A58: M264 — Master of Science in Cybersecurity Leadership | B58: No data | C58: No data | D58: No data | E58: No data | F58: No data
A59: M297 — Master of Econometrics | B59: No data | C59: No data | D59: No data | E59: No data | F59: 0.88201161
A60: M355 — Online LL.M. Energy and Natural Resources | B60: No data | C60: 1 | D60: No data | E60: 1 | F60: 1
A61: M366 — Executive MBA in Energy | B61: 0.7380117 | C61: 0.97625891 | D61: 1 | E61: 1 | F61: 1
A62: M368 — Master of Legal Studies - Energy | B62: 0.94594595 | C62: 0.93757576 | D62: 1 | E62: 1.0300373 | F62: 1
A63: M374 — Master of Science in Engineering Leadership and Management | B63: No data | C63: No data | D63: No data | E63: 0.7860262 | F63: 0.56291391
A64: M383 — Master of Entrepreneurship & Innovation | B64: No data | C64: No data | D64: No data | E64: No data | F64: 1
A65: M435 — Master of Science in Finance | B65: 0.7826389 | C65: 0.80615928 | D65: 0.85654596 | E65: 0.95352915 | F65: 0.79212612
A66: M464 — Master of Science in Geospatial Technology | B66: 0.71536117 | C66: 0.85697831 | D66: 0.93913043 | E66: 0.87301587 | F66: 0.94736842
A67: M494 — Master of Arts in Global Affairs | B67: 0.94211077 | C67: 1.1119175 | D67: 0.88800179 | E67: 0.8642375 | F67: 0.77356805
A68: M503 — Master of Legal Studies - Healthcare Law | B68: 1.0130042 | C68: 0.98114627 | D68: 0.83314469 | E68: 0.83213352 | F68: 0.81741279
A69: M504 — Online LL.M. Healthcare Law | B69: 1 | C69: No data | D69: 1 | E69: 1 | F69: 1
A70: M518 — Master of Environmental Science: Hydrology and Water Security | B70: 0.96709554 | C70: 0.78280337 | D70: 0.73294291 | E70: 0.78129758 | F70: 0.86147108
A71: M522 — Master of Legal Studies - Indigenous Peoples Law | B71: 0.7908798 | C71: 0.78915206 | D71: 0.75647762 | E71: 0.7864861 | F71: 0.83330625
A72: M526 — Online LL.M. Indigenous Peoples Law | B72: 1 | C72: 1 | D72: 1.4117647 | E72: 0.77777778 | F72: 0.84
A73: M527 — Master of Science in Industrial and Systems Engineering | B73: No data | C73: 0.87910328 | D73: 0.7450295 | E73: 0.74457781 | F73: 0.85286326
A74: M589 — Master of Legal Studies - International Business | B74: 0.86049544 | C74: 0.95613048 | D74: 0.9467028 | E74: 0.97358491 | F74: No data
A75: M592 — Online LL.M. International Business | B75: No data | C75: No data | D75: No data | E75: 1 | F75: No data
A76: M636 — Master of Legal Studies - General | B76: No data | C76: No data | D76: No data | E76: No data | F76: 1
A77: M700 — Master of Arts in Museum Studies | B77: 0.91859877 | C77: 0.89120236 | D77: 0.77942588 | E77: 0.92400999 | F77: 0.89614484
A78: M746 — Master of Science in Natural Gas Engineering and Management | B78: 1.0336788 | C78: 0.8447205 | D78: 0.77555749 | E78: 0.85843102 | F78: 0.9097037
A79: M762 — Master of Arts in Organizational Leadership | B79: 0.79881532 | C79: 0.75549409 | D79: 0.76156251 | E79: 0.76252151 | F79: 0.8499022
A80: M844 — Master of Social Work | B80: 0.9468352 | C80: 0.93198137 | D80: 0.96395751 | E80: 0.97348858 | F80: 0.84786735
A81: M859 — Master of Arts in Strategic Communication and Digital Strategy | B81: 0.99487253 | C81: 0.81636267 | D81: 0.99437419 | E81: 0.81343757 | F81: 0.98768405
A82: M861 — Master of Science in Supply Chain Management | B82: No data | C82: No data | D82: 0.83905913 | E82: 0.97875 | F82: 1.0316651
A83: M867 — Master of Science in Sustainable Architecture | B83: No data | C83: No data | D83: No data | E83: 0.97104377 | F83: 0.83685477
A84: M869 — Master of Science in Sustainability - Energy and Materials Mgmt | B84: No data | C84: No data | D84: No data | E84: 0.91496063 | F84: 0.94291116

Sheet CAC & LTR Data (Trial)
A1: TRIAL — LTR-to-CAC Portfolio View (Norman Graduate Programs)
A2: This sheet and 'LTR vs CAC Matrix' are a TRIAL, added at your request to test whether this view is useful — they do not change anything in the persistence/LTR model itself, and nothing here feeds back into any other sheet in this workbook. LTR/Student is the same Direct-method figure already on Revenue Outlook (unchanged, read-only). CAC = FY26 'Using Follow the Lead' direct marketing spend (from 'OU Online FY26 Media August 2026.xlsx') ÷ FY26 gross New Starts (a straight count of distinct students who first entered that program in FY2026, from this workbook's own raw data — not the same 'New Starts' figure used on Revenue Outlook, which is a single-term, forward-looking model estimate rather than a FY26 actual count).
A3: Two things to know before reading this as decision-grade, not just directional: (1) 'Revenue Multiple' below is GROSS tuition revenue ÷ CAC — it is NOT a margin-based LTV:CAC, so the standard '3:1 is healthy' benchmark does not apply to it. See 'Margin View (Trial, Approx.)' for a rough margin-adjusted cut using program-level cost data. (2) CAC here is FY26 paid-media spend only — the Financial Viability file's own P&L has a separate 'Marketing' expense line for the same programs that disagrees with it by a wide margin (median ~10x, up to ~170x for one program). Neither has been confirmed by Finance/Marketing Ops as fully-loaded — see 'Margin View (Trial, Approx.)' for the side-by-side.
A4: Quadrant labels (this version): re-cut around the four strategic actions you asked for — Max Spend / Evaluate Spend & Channel Strategy / Throttle Spend — Fix Persistence / Sunset Candidates — using the SAME median-CAC/median-LTR split as before, recomputed on 23 programs after excluding M366 (Executive MBA in Energy) as a chart-only outlier (see 'LTR vs CAC Matrix' sheet). One program's quadrant shifted as a result of the recomputed median: M859 — sitting almost exactly on the new LTR median, so treat that one as a borderline call, not a firm read.
A5: Coverage: the Media file has no marketing-spend row at all for the 4 College of Law LL.M./Legal Studies programs' Law-only siblings and the 3 Health-campus programs (Certificate in Population Health, Executive Masters in Health Administration, Masters in Public Health) plus 5 Legal Studies programs — 12 of our 41 programs have NO CAC figure here and are excluded from the matrix, not assumed to be zero-cost. A further 5 programs have FY26 marketing spend but haven't reached a mature enough cohort yet for a Direct-method LTR figure. Both groups are listed below with the rest, flagged rather than hidden.
A7: Program | B7: FY26 Media Spend (Follow the Lead) | C7: FY26 New Starts (Gross) | D7: CAC ($/student) | E7: LTR/Student (Direct method) | F7: Revenue Multiple (Gross LTR ÷ CAC) | G7: Quadrant (Strategic Action) | H7: Coverage Note
A8: M035 — Master of Science in Applied Statistics | B8: 19676 | C8: 35 | D8: 562 | E8: 11019 | F8: 19.6 | G8: Throttle Spend — Fix Persistence
A9: M844 — Master of Social Work | B9: 331986 | C9: 188 | D9: 1766 | E9: 29413 | F9: 16.7 | G9: Max Spend
A10: M435 — Master of Science in Finance | B10: 86072 | C10: 57 | D10: 1510 | E10: 25131 | F10: 16.6 | G10: Max Spend
A11: M494 — Master of Arts in Global Affairs | B11: 93651 | C11: 59 | D11: 1587 | E11: 19353 | F11: 12.2 | G11: Throttle Spend — Fix Persistence
A12: M202 — Master of Clinical Mental Health Counseling | B12: 295485 | C12: 89 | D12: 3320 | E12: 39095 | F12: 11.8 | G12: Max Spend
A13: M700 — Master of Arts in Museum Studies | B13: 237540 | C13: 133 | D13: 1786 | E13: 20032 | F13: 11.2 | G13: Throttle Spend — Fix Persistence
A14: M464 — Master of Science in Geospatial Technology | B14: 35024 | C14: 13 | D14: 2694 | E14: 24567 | F14: 9.1 | G14: Max Spend
A15: M366 — Executive MBA in Energy | B15: 144774 | C15: 15 | D15: 9652 | E15: 85313 | F15: 8.8 | G15: Evaluate Spend & Channel Strategy | H15: Excluded from chart (outlier — see Matrix sheet)
A16: M013 — Master of Accountancy | B16: 215122 | C16: 70 | D16: 3073 | E16: 25431 | F16: 8.3 | G16: Max Spend
A17: M145 — Master of Science in Business Analytics | B17: 122873 | C17: 40 | D17: 3072 | E17: 22435 | F17: 7.3 | G17: Throttle Spend — Fix Persistence
A18: M073 — Master of Arts in Arts Management | B18: 192074 | C18: 55 | D18: 3492 | E18: 25235 | F18: 7.2 | G18: Max Spend
A19: M861 — Master of Science in Supply Chain Management | B19: 239637 | C19: 57 | D19: 4204 | E19: 26782 | F19: 6.4 | G19: Evaluate Spend & Channel Strategy
A20: M746 — Master of Science in Natural Gas Engineering and Management | B20: 144540 | C20: 38 | D20: 3804 | E20: 22553 | F20: 5.9 | G20: Sunset Candidates
A21: M762 — Master of Arts in Organizational Leadership | B21: 300760 | C21: 96 | D21: 3133 | E21: 17651 | F21: 5.6 | G21: Throttle Spend — Fix Persistence
A22: M518 — Master of Environmental Science: Hydrology and Water Security | B22: 251610 | C22: 57 | D22: 4414 | E22: 24328 | F22: 5.5 | G22: Evaluate Spend & Channel Strategy
A23: M374 — Master of Science in Engineering Leadership and Management | B23: 265988 | C23: 56 | D23: 4750 | E23: 26009 | F23: 5.5 | G23: Evaluate Spend & Channel Strategy
A24: M527 — Master of Science in Industrial and Systems Engineering | B24: 208677 | C24: 58 | D24: 3598 | E24: 18638 | F24: 5.2 | G24: Throttle Spend — Fix Persistence
A25: M859 — Master of Arts in Strategic Communication and Digital Strategy | B25: 230261 | C25: 47 | D25: 4899 | E25: 23181 | F25: 4.7 | G25: Evaluate Spend & Channel Strategy
A26: M869 — Master of Science in Sustainability - Energy and Materials Mgmt | B26: 135973 | C26: 32 | D26: 4249 | E26: 17919 | F26: 4.2 | G26: Sunset Candidates
A27: M075 — Master of Arts in Art and Technology | B27: 187849 | C27: 33 | D27: 5692 | E27: 19863 | F27: 3.5 | G27: Sunset Candidates
... A31: M260 — Master of Science in Criminal Justice | B31: 273967 | C31: 45 | D31: 6088 | E31: 14815 | F31: 2.4 | G31: Sunset Candidates
A32: D318 — Ed.D. in Education Administration | B32: 108405 | C32: 69 | D32: 1571 | E32: No data | F32: — | G32: Not in matrix | H32: No mature-cohort LTR yet
A33: M029 — Master of Science in Applied Computing | B33: 37402 | C33: 18 | D33: 2078 | E33: No data | F33: — | G33: Not in matrix | H33: No mature-cohort LTR yet
A34: M264 — Master of Science in Cybersecurity Leadership | B34: 98533 | C34: 7 | D34: 14076 | E34: No data | F34: — | G34: Not in matrix | H34: No mature-cohort LTR yet
A35: M297 — Master of Econometrics | B35: 36483 | C35: 32 | D35: 1140 | E35: No data | F35: — | G35: Not in matrix | H35: No mature-cohort LTR yet
A36: M383 — Master of Entrepreneurship & Innovation | B36: 64343 | C36: 11 | D36: 5849 | E36: No data | F36: — | G36: Not in matrix | H36: No mature-cohort LTR yet
A37: 1231EX — Executive Masters in Health Administration | B37: No data | C37: No data | D37: No data | E37: No data | F37: — | G37: Not in matrix | H37: No CAC data (Law/Health, not in Media file)
A38: 1237Q — Masters in Public Health | B38: No data | C38: No data | D38: No data | E38: No data | F38: — | G38: Not in matrix | H38: No CAC data (Law/Health, not in Media file)
A39: 1550C — Certificate in Population Health | B39: No data | C39: No data | D39: No data | E39: No data | F39: — | G39: Not in matrix | H39: No CAC data (Law/Health, not in Media file)
A40: M355 — Online LL.M. Energy and Natural Resources | B40: No data | C40: No data | D40: No data | E40: 11543 | F40: — | G40: Not in matrix | H40: No CAC data (Law/Health, not in Media file)
A41: M368 — Master of Legal Studies - Energy | B41: No data | C41: No data | D41: No data | E41: 19416 | F41: — | G41: Not in matrix | H41: No CAC data (Law/Health, not in Media file)
A42: M503 — Master of Legal Studies - Healthcare Law | B42: No data | C42: No data | D42: No data | E42: 21924 | F42: — | G42: Not in matrix | H42: No CAC data (Law/Health, not in Media file)
A43: M504 — Online LL.M. Healthcare Law | B43: No data | C43: No data | D43: No data | E43: 10511 | F43: — | G43: Not in matrix | H43: No CAC data (Law/Health, not in Media file)
A44: M522 — Master of Legal Studies - Indigenous Peoples Law | B44: No data | C44: No data | D44: No data | E44: 21473 | F44: — | G44: Not in matrix | H44: No CAC data (Law/Health, not in Media file)
A45: M526 — Online LL.M. Indigenous Peoples Law | B45: No data | C45: No data | D45: No data | E45: 13514 | F45: — | G45: Not in matrix | H45: No CAC data (Law/Health, not in Media file)
A46: M589 — Master of Legal Studies - International Business | B46: No data | C46: No data | D46: No data | E46: 20121 | F46: — | G46: Not in matrix | H46: No CAC data (Law/Health, not in Media file)
A47: M592 — Online LL.M. International Business | B47: No data | C47: No data | D47: No data | E47: 11402 | F47: — | G47: Not in matrix | H47: No CAC data (Law/Health, not in Media file)
A48: M636 — Master of Legal Studies - General | B48: No data | C48: No data | D48: No data | E48: No data | F48: — | G48: Not in matrix | H48: No CAC data (Law/Health, not in Media file)
A50: Median CAC (of 23 charted programs, excl. M366): $3,598
A51: Median LTR/Student (of 23 charted programs, excl. M366): $23,181
A52: Revenue Multiple is gross-tuition-based (see note above) — see 'Margin View (Trial, Approx.)' for the margin-adjusted read.
A54: Media-file rows not matched to our 41 programs (undergraduate degrees, ADC/PACS certificate programs out of this workbook's current scope, and a few programs not in our 41) are omitted from this table entirely rather than shown as zero — see build script for the full list if needed.

Sheet LTR vs CAC Matrix (Trial)
A1: TRIAL — LTR vs. CAC Strategic Matrix, Norman Graduate Programs (FY26)
A2: Redesigned per your review: X-axis is now LTR (low->high, left->right), Y-axis is CAC but INVERTED (low CAC at top, high CAC at bottom), so the best unit economics sit in the TOP-RIGHT. Quadrant lines are drawn at the median LTR ($23,181) and median CAC ($3,598) across the 23 programs plotted below. Executive MBA in Energy (M366) is EXCLUDED from this chart — its Direct-method LTR ($85,313) is roughly double the next-highest program's, which compressed the other 23 points into one corner; its row and quadrant are still in 'CAC & LTR Data (Trial).' See 'Margin View (Trial, Approx.)' for why a program's position here can look stronger than its margin-adjusted economics.
A4: (chart data — quadrant-split for coloring)
A5: Max Spend - Code | B5: Max Spend - LTR | C5: Max Spend - CAC | D5: Evaluate Spend & Channel Strategy - Code | E5: Evaluate Spend & Channel Strategy - LTR | F5: Evaluate Spend & Channel Strategy - CAC | G5: Throttle Spend — Fix Persistence - Code | H5: Throttle Spend — Fix Persistence - LTR | I5: Throttle Spend — Fix Persistence - CAC | J5: Sunset Candidates - Code | K5: Sunset Candidates - LTR | L5: Sunset Candidates - CAC
A6: M844 | B6: 29413.17 | C6: 1765.88 | D6: M246 | E6: 29505.61 | F6: 9906.01 | G6: M494 | H6: 19353.23 | I6: 1587.31 | J6: M867 | K6: 22025.5 | L6: 8456.52
A7: M202 | B7: 39095.33 | C7: 3320.06 | D7: M374 | E7: 26009.38 | F7: 4749.79 | G7: M700 | H7: 20032.2 | I7: 1786.02 | J7: M260 | K7: 14814.7 | L7: 6088.15
A8: M464 | B8: 24566.94 | C8: 2694.18 | D8: M518 | E8: 24328.03 | F8: 4414.21 | G8: M035 | H8: 11019.49 | I8: 562.17 | J8: M746 | K8: 22552.8 | L8: 3803.68
A9: M073 | B9: 25235.44 | C9: 3492.26 | D9: M191 | E9: 24703 | F9: 9150.74 | G9: M762 | H9: 17651.3 | I9: 3132.91 | J9: M869 | K9: 17918.65 | L9: 4249.14
A10: M435 | B10: 25130.94 | C10: 1510.04 | D10: M859 | E10: 23181.39 | F10: 4899.18 | G10: M527 | H10: 18638.08 | I10: 3597.88 | J10: M075 | K10: 19863.29 | L10: 5692.38
A11: M013 | B11: 25430.97 | C11: 3073.17 | D11: M861 | E11: 26782.16 | F11: 4204.16 | G11: M145 | H11: 22435.45 | I11: 3071.82
A13: vline_x | B13: 23181.387 | C13: 23181.387
A14: vline_y | B14: 0 | C14: 10896.607
A15: hline_x | B15: 0 | C15: 43004.867
A16: hline_y | B16: 3597.8757 | C16: 3597.8757
A45: What each quadrant means (matches the chart's layout)
B46: ← Low LTR | D46: High LTR →
A47: ↑ Low CAC | B47: THROTTLE SPEND — FIX PERSISTENCE | D47: MAX SPEND
A48: ↓ High CAC | B48: SUNSET CANDIDATES | D48: EVALUATE SPEND & CHANNEL STRATEGY
B50: Max Spend | C50: High LTR, low CAC — the best unit economics in the portfolio. Protect and grow marketing budget here; look for scale opportunity.
B51: Evaluate Spend & Channel Strategy | C51: High LTR, high CAC — valuable programs, but expensive to acquire. Evaluate spend and channel strategy, and look at conversion barriers (admissions friction, lockstep terms) before assuming the spend itself is the problem.
B52: Throttle Spend — Fix Persistence | C52: Low LTR, low CAC — cheap to acquire, but revenue per student is thin. Throttle spend until persistence barriers (the reason LTR is low) are identified and addressed — more spend here just buys more of a leaky bucket.
B53: Sunset Candidates | C53: Low LTR, high CAC — the worst unit economics: expensive to acquire, low revenue per student once acquired. Highest-priority programs to ask how quickly they can be sunset or fundamentally restructured.

Sheet HC by Program-Year
A1: Headcount by Program × Year
A2: Total enrolled per program per OU academic year (term-code prefix). AY×××× = Fall ×××× + Spring & Summer (××××+1). Rolls up “HC by Program-Term”. 2019 (Summer 2020 only) and 2026 (Fall 2026 only) are partial — the data window is 201930–202610. “—” = no term-level data in source.
A5: Program Code | B5: Program Name | C5: 2019 | D5: 2020 | E5: 2021 | F5: 2022 | G5: 2023 | H5: 2024 | I5: 2025 | J5: 2026 | K5: Total
A7: ='Program List'!A2 -> 1550C | B7: ='Program List'!B2 -> Certificate in Population Health | C7: =IF('HC by Program-Term'!$Y7="","—",'HC by Program-Term'!C7) -> — | D7: =IF('HC by Program-Term'!$Y7="","—",SUM('HC by Program-Term'!D7:F7)) -> — | E7: =IF('HC by Program-Term'!$Y7="","—",SUM('HC by Program-Term'!G7:I7)) -> — | F7: =IF('HC by Program-Term'!$Y7="","—",SUM('HC by Program-Term'!J7:L7)) -> — | G7: =IF('HC by Program-Term'!$Y7="","—",SUM('HC by Program-Term'!M7:O7)) -> — | H7: =IF('HC by Program-Term'!$Y7="","—",SUM('HC by Program-Term'!P7:R7)) -> — | I7: =IF('HC by Program-Term'!$Y7="","—",SUM('HC by Program-Term'!S7:U7)) -> — | J7: =IF('HC by Program-Term'!$Y7="","—",'HC by Program-Term'!V7) -> — | K7: =IF('HC by Program-Term'!$Y7="","—",SUM(C7:J7)) -> —
A8: ='Program List'!A3 -> D318 | B8: ='Program List'!B3 -> Ed.D. in Education Administration | C8: =IF('HC by Program-Term'!$Y8="","—",'HC by Program-Term'!C8) -> — | D8: =IF('HC by Program-Term'!$Y8="","—",SUM('HC by Program-Term'!D8:F8)) -> — | E8: =IF('HC by Program-Term'!$Y8="","—",SUM('HC by Program-Term'!G8:I8)) -> — | F8: =IF('HC by Program-Term'!$Y8="","—",SUM('HC by Program-Term'!J8:L8)) -> — | G8: =IF('HC by Program-Term'!$Y8="","—",SUM('HC by Program-Term'!M8:O8)) -> — | H8: =IF('HC by Program-Term'!$Y8="","—",SUM('HC by Program-Term'!P8:R8)) -> — | I8: =IF('HC by Program-Term'!$Y8="","—",SUM('HC by Program-Term'!S8:U8)) -> — | J8: =IF('HC by Program-Term'!$Y8="","—",'HC by Program-Term'!V8) -> — | K8: =IF('HC by Program-Term'!$Y8="","—",SUM(C8:J8)) -> —
A9: ='Program List'!A4 -> M366 | B9: ='Program List'!B4 -> Executive MBA in Energy | C9: =IF('HC by Program-Term'!$Y9="","—",'HC by Program-Term'!C9) -> 0 | D9: =IF('HC by Program-Term'!$Y9="","—",SUM('HC by Program-Term'!D9:F9)) -> 82 | E9: =IF('HC by Program-Term'!$Y9="","—",SUM('HC by Program-Term'!G9:I9)) -> 115 | F9: =IF('HC by Program-Term'!$Y9="","—",SUM('HC by Program-Term'!J9:L9)) -> 150 | G9: =IF('HC by Program-Term'!$Y9="","—",SUM('HC by Program-Term'!M9:O9)) -> 147 | H9: =IF('HC by Program-Term'!$Y9="","—",SUM('HC by Program-Term'!P9:R9)) -> 123 | I9: =IF('HC by Program-Term'!$Y9="","—",SUM('HC by Program-Term'!S9:U9)) -> 88 | J9: =IF('HC by Program-Term'!$Y9="","—",'HC by Program-Term'!V9) -> 21 | K9: =IF('HC by Program-Term'!$Y9="","—",SUM(C9:J9)) -> 726
A10: ='Program List'!A5 -> 1231EX | B10: ='Program List'!B5 -> Executive Masters in Health Administration | C10: =IF('HC by Program-Term'!$Y10="","—",'HC by Program-Term'!C10) -> — | D10: =IF('HC by Program-Term'!$Y10="","—",SUM('HC by Program-Term'!D10:F10)) -> — | E10: =IF('HC by Program-Term'!$Y10="","—",SUM('HC by Program-Term'!G10:I10)) -> — | F10: =IF('HC by Program-Term'!$Y10="","—",SUM('HC by Program-Term'!J10:L10)) -> — | G10: =IF('HC by Program-Term'!$Y10="","—",SUM('HC by Program-Term'!M10:O10)) -> — | H10: =IF('HC by Program-Term'!$Y10="","—",SUM('HC by Program-Term'!P10:R10)) -> — | I10: =IF('HC by Program-Term'!$Y10="","—",SUM('HC by Program-Term'!S10:U10)) -> — | J10: =IF('HC by Program-Term'!$Y10="","—",'HC by Program-Term'!V10) -> — | K10: =IF('HC by Program-Term'!$Y10="","—",SUM(C10:J10)) -> —
A11: ='Program List'!A6 -> M013 | B11: ='Program List'!B6 -> Master of Accountancy | C11: =IF('HC by Program-Term'!$Y11="","—",'HC by Program-Term'!C11) -> 8 | D11: =IF('HC by Program-Term'!$Y11="","—",SUM('HC by Program-Term'!D11:F11)) -> 178 | E11: =IF('HC by Program-Term'!$Y11="","—",SUM('HC by Program-Term'!G11:I11)) -> 279 | F11: =IF('HC by Program-Term'!$Y11="","—",SUM('HC by Program-Term'!J11:L11)) -> 298 | G11: =IF('HC by Program-Term'!$Y11="","—",SUM('HC by Program-Term'!M11:O11)) -> 286 | H11: =IF('HC by Program-Term'!$Y11="","—",SUM('HC by Program-Term'!P11:R11)) -> 274 | I11: =IF('HC by Program-Term'!$Y11="","—",SUM('HC by Program-Term'!S11:U11)) -> 301 | J11: =IF('HC by Program-Term'!$Y11="","—",'HC by Program-Term'!V11) -> 96 | K11: =IF('HC by Program-Term'!$Y11="","—",SUM(C11:J11)) -> 1720
A12: ='Program List'!A7 -> M075 | B12: ='Program List'!B7 -> Master of Arts in Art and Technology | C12: =IF('HC by Program-Term'!$Y12="","—",'HC by Program-Term'!C12) -> 0 | D12: =IF('HC by Program-Term'!$Y12="","—",SUM('HC by Program-Term'!D12:F12)) -> 0 | E12: =IF('HC by Program-Term'!$Y12="","—",SUM('HC by Program-Term'!G12:I12)) -> 102 | F12: =IF('HC by Program-Term'!$Y12="","—",SUM('HC by Program-Term'!J12:L12)) -> 189 | G12: =IF('HC by Program-Term'!$Y12="","—",SUM('HC by Program-Term'!M12:O12)) -> 195 | H12: =IF('HC by Program-Term'!$Y12="","—",SUM('HC by Program-Term'!P12:R12)) -> 179 | I12: =IF('HC by Program-Term'!$Y12="","—",SUM('HC by Program-Term'!S12:U12)) -> 156 | J12: =IF('HC by Program-Term'!$Y12="","—",'HC by Program-Term'!V12) -> 43 | K12: =IF('HC by Program-Term'!$Y12="","—",SUM(C12:J12)) -> 864
A13: ='Program List'!A8 -> M073 | B13: ='Program List'!B8 -> Master of Arts in Arts Management | C13: =IF('HC by Program-Term'!$Y13="","—",'HC by Program-Term'!C13) -> 0 | D13: =IF('HC by Program-Term'!$Y13="","—",SUM('HC by Program-Term'!D13:F13)) -> 0 | E13: =IF('HC by Program-Term'!$Y13="","—",SUM('HC by Program-Term'!G13:I13)) -> 0 | F13: =IF('HC by Program-Term'!$Y13="","—",SUM('HC by Program-Term'!J13:L13)) -> 13 | G13: =IF('HC by Program-Term'!$Y13="","—",SUM('HC by Program-Term'!M13:O13)) -> 173 | H13: =IF('HC by Program-Term'!$Y13="","—",SUM('HC by Program-Term'!P13:R13)) -> 233 | I13: =IF('HC by Program-Term'!$Y13="","—",SUM('HC by Program-Term'!S13:U13)) -> 231 | J13: =IF('HC by Program-Term'!$Y13="","—",'HC by Program-Term'!V13) -> 71 | K13: =IF('HC by Program-Term'!$Y13="","—",SUM(C13:J13)) -> 721
A14: ='Program List'!A9 -> M494 | B14: ='Program List'!B9 -> Master of Arts in Global Affairs | C14: =IF('HC by Program-Term'!$Y14="","—",'HC by Program-Term'!C14) -> 4 | D14: =IF('HC by Program-Term'!$Y14="","—",SUM('HC by Program-Term'!D14:F14)) -> 102 | E14: =IF('HC by Program-Term'!$Y14="","—",SUM('HC by Program-Term'!G14:I14)) -> 180 | F14: =IF('HC by Program-Term'!$Y14="","—",SUM('HC by Program-Term'!J14:L14)) -> 254 | G14: =IF('HC by Program-Term'!$Y14="","—",SUM('HC by Program-Term'!M14:O14)) -> 298 | H14: =IF('HC by Program-Term'!$Y14="","—",SUM('HC by Program-Term'!P14:R14)) -> 349 | I14: =IF('HC by Program-Term'!$Y14="","—",SUM('HC by Program-Term'!S14:U14)) -> 331 | J14: =IF('HC by Program-Term'!$Y14="","—",'HC by Program-Term'!V14) -> 100 | K14: =IF('HC by Program-Term'!$Y14="","—",SUM(C14:J14)) -> 1618
A15: ='Program List'!A10 -> M700 | B15: ='Program List'!B10 -> Master of Arts in Museum Studies | C15: =IF('HC by Program-Term'!$Y15="","—",'HC by Program-Term'!C15) -> 7 | D15: =IF('HC by Program-Term'!$Y15="","—",SUM('HC by Program-Term'!D15:F15)) -> 100 | E15: =IF('HC by Program-Term'!$Y15="","—",SUM('HC by Program-Term'!G15:I15)) -> 241 | F15: =IF('HC by Program-Term'!$Y15="","—",SUM('HC by Program-Term'!J15:L15)) -> 524 | G15: =IF('HC by Program-Term'!$Y15="","—",SUM('HC by Program-Term'!M15:O15)) -> 815 | H15: =IF('HC by Program-Term'!$Y15="","—",SUM('HC by Program-Term'!P15:R15)) -> 854 | I15: =IF('HC by Program-Term'!$Y15="","—",SUM('HC by Program-Term'!S15:U15)) -> 703 | J15: =IF('HC by Program-Term'!$Y15="","—",'HC by Program-Term'!V15) -> 221 | K15: =IF('HC by Program-Term'!$Y15="","—",SUM(C15:J15)) -> 3465
A16: ='Program List'!A11 -> M762 | B16: ='Program List'!B11 -> Master of Arts in Organizational Leadership | C16: =IF('HC by Program-Term'!$Y16="","—",'HC by Program-Term'!C16) -> 29 | D16: =IF('HC by Program-Term'!$Y16="","—",SUM('HC by Program-Term'!D16:F16)) -> 239 | E16: =IF('HC by Program-Term'!$Y16="","—",SUM('HC by Program-Term'!G16:I16)) -> 424 | F16: =IF('HC by Program-Term'!$Y16="","—",SUM('HC by Program-Term'!J16:L16)) -> 482 | G16: =IF('HC by Program-Term'!$Y16="","—",SUM('HC by Program-Term'!M16:O16)) -> 572 | H16: =IF('HC by Program-Term'!$Y16="","—",SUM('HC by Program-Term'!P16:R16)) -> 558 | I16: =IF('HC by Program-Term'!$Y16="","—",SUM('HC by Program-Term'!S16:U16)) -> 452 | J16: =IF('HC by Program-Term'!$Y16="","—",'HC by Program-Term'!V16) -> 155 | K16: =IF('HC by Program-Term'!$Y16="","—",SUM(C16:J16)) -> 2911
